Workbook

Sheet CRITERIOS CELDAS RAT-MTGE
B2: CRITERIOS MTGE
X4: LISTAS PARA DERECHOS Y LIBERTADES FUNDAMENTALES - IMPACTO - DAÑO - NIVEL DE SEGURIDAD
B6: NÚMERO DE TITULARES | C6: Puntos | E6: VOLÚMEN DE DATOS TRATADOS | F6: Puntos | H6: CATEGORÍAS DE DATOS PERSONALES TRATADOS | I6: Puntos | K6: FRECUENCIA DEL TRATAMIENTO | L6: Puntos | N6: PERMANENCIA DEL TRATAMIENTO | O6: Puntos | Q6: ALCANCE GEOGRÁFICO DEL TRATAMIENTO | R6: Puntos | T6: MTGE | U6: SECTOR ECONÓMICO | V6: BASE LICITUD | Y6: 0 | AB6: 0 | AE6: 0 | AH6: 0
B7: DE 0 A 1.000 | C7: 1 | E7: HASTA 10 TIPOS DE DATOS POR TITULAR | F7: 0.5 | H7: BÁSICOS | I7: 0.5 | K7: TRATAMIENTO PUNTUAL | L7: 0.5 | N7: OCASIONAL | O7: 0.5 | Q7: ALCANCE LOCAL | R7: 1 | T7: =SUM(R7,O7,L7,I7,F7,C7) -> 4 | X7: BRECHA IDENTIFICADA. NO HECHA PÚBLICA. DATOS BÁSICOS. MENOS DE 100 TITULARES. SG-PDP VALIDADO Y MANTENIDO. GRC ARTICULADO Y REFRESCADO | Y7: 1 | AA7: BRECHA IDENTIFICADA. NO HECHA PÚBLICA. DATOS BÁSICOS. MAS DE 100 TITULARES. SG-PDP VALIDADO EN FASE PROYECTO. SE TRABAJA 47 LOPDP. GRC ARTICULADO | AB7: 2 | AD7: BRECHA IDENTIFICADA. HECHA PÚBLICA. DATOS ESPECIALES. MAS DE 100 TITULARES. NO HAY PROYECTO SG-PDP. NO SE TRABAJA 47 LOPDP. HAY GRC DESARTICULADO. | AE7: 3 | AG7: BRECHA IDENTIFICADA. HECHA PÚBLICA. DATOS ESPECIALES. MAS DE 100 TITULARES. NO HAY PROYECTO SG-PDP. NO HAY GRC. | AH7: 4
B8: DE 1.001 A 10.000 | C8: 2 | E8: ENTRE 11 Y 30 TIPOS DE DATOS | F8: 1 | H8: ESPECIALES | I8: 2 | K8: PERIÓDICA RECURRENTE | L8: 1 | N8: TEMPORAL | O8: 1 | Q8: NACIONAL | R8: 2 | T8: =SUM(R7,O9,L7,I8,F8,C7) -> 7.5 | U8: CONTRATO MANUFACTURA | V8: 7.5
B9: DE 10.001 A 100.000 | C9: 3 | E9: ENTRE 31 Y 100 TIPOS DE DATOS | F9: 2 | H9: ESPECIAL GRUPOS VULNERABLES | I9: 3 | K9: CONTINUA EN TIEMPO REAL | L9: 2 | N9: PROLONGADA | O9: 2 | Q9: GLOBAL | R9: 3 | T9: =SUM(R8,O8,L7,I8,F9,C7) -> 8.5 | U9: LEY TRANSPORTE SEGURO | V9: 7.2 | X9: LISTAS PARA NIVEL DE PROBABILIDAD - OPERACIONES - NIVEL DE SEGURIDAD
B10: DE 101.000 O MÁS | C10: 4 | E10: DESDE 101 O MÁS | F10: 3
X11: EXISTE UN SG-PDP VALIDADO Y MANTENIDO. LAS RUTINAS PDP SE PRACTICAN. PLAN DE SIMULACROS ACTIVO. GRC ARTICULADO Y REFERESCADO | Y11: 1 | AA11: EXISTE PROYECTO SG-PDP. NO ESTÁ VALIDADO. LAS RUTINAS PDP SE PRACTICAN. PLAN DE SIMULACROS FASE INICIAL. PANSI EN FASE INICIAL. | AB11: 2 | AD11: PROYECTO SG-PDP INSIPIENTE. HAY DPO, ALGUNOS DOCUMENTOS, HAY EQUIPO INTERNO. NO HAY GRC. NO HAY PANSI | AE11: 3 | AG11: NO HAY PROYECTO SG-PDP. HAY DPO, ALGUNOS DOCUMENTOS, NO HAY EQUIPO INTERNO. NO HAY APOYO DE LA GERENCIA. EL DPD TIENE TODA LA CARGA | AH11: 4
X13: LISTAS PARA NIVEL DE PROBABILIDAD - MEDIOS - NIVEL DE SEGURIDAD
B14: NINGUNO | E14: BÁSICOS | H14: TITULARES INTERNOS - PATD | K14: SI | N14: NO | Q14: 7.1 - CONSENTIMIENTO | T14: TIEMPO DEL TRATAMIENTO + 3 MESES
B15: SALUD | E15: ESPECIALES | H15: TITULARES INTERNOS - EMPLEADO | K15: NO | N15: SI - USO DE CORREO ELECTRÓNICO | Q15: 7.2 - OBLIGACIÓN LEGAL | T15: TIEMPO DEL TRATAMIENTO + 7 AÑOS | X15: EXISTE UN SG-PDP VALIDADO Y MANTENIDO. LAS RUTINAS PDP SE PRACTICAN. PLAN DE SIMULACROS ACTIVO. GRC ARTICULADO Y REFERESCADO | Y15: 1 | AA15: EXISTE PROYECTO SG-PDP. NO ESTÁ VALIDADO. LAS RUTINAS PDP SE PRACTICAN. PLAN DE SIMULACROS FASE INICIAL. PANSI EN FASE INICIAL. | AB15: 2 | AD15: PROYECTO SG-PDP INSIPIENTE. HAY DPO, ALGUNOS DOCUMENTOS, HAY EQUIPO INTERNO. NO HAY GRC. NO HAY PANSI | AE15: 3 | AG15: NO HAY PROYECTO SG-PDP. HAY DPO, ALGUNOS DOCUMENTOS, NO HAY EQUIPO INTERNO. NO HAY APOYO DE LA GERENCIA. EL DPD TIENE TODA LA CARGA | AH15: 4
B16: TRATAMIENTOS AUTOMATIZADOS | E16: COMBINADOS | H16: TITULARES EXTERNOS ENTREGADOS POR UN RESPONSABLE | N16: SI - USO DE PLATAFORMA OODO | Q16: 7.3 - ORDEN JUDICIAL | T16: TIEMPO DEL TRATAMIENTO
B17: VIGILANCIA MONITOREO | E17: GRUPOS VULNERABLES | H17: TITULAREES EXTERNOS - VISITAS | N17: SI - POR TIPO DE DESTINATARIO | Q17: 7.4 - INTERÉS PÚBLICO | T17: NO DETERMINADA. CAPACIDAD DE MEMORIA DEL DISPOSITIVO
B18: DATOS BIOMETRICOS | H18: TITULARES EXTERNOS - PATD HONORARIOS | N18: SI - POR REPORTE A MATRIZ | Q18: 7.5 - PRE CONTRACTUAL O CONTRACTUAL | T18: TITULARES INTERNOS - EMPLEADOS
B19: CREDITICIA FINANCIERA | H19: TITULARES EXTERNOS - CANDIDATOS | Q19: 7.6 - INTERESES VITALES | T19: TITULARES EXTERNOS - ENTREGADOS POR UN RESPONSABLE
B20: NIÑAS, NIÑOS Y ADOLECENTES EN ENTORNOS INSTITUCIONALES Y TECNOLÓICOS | Q20: 7.7 - BASES DE ACCESO PÚBLICO | T20: TITULARES EXTERNOS - RECOGIDOS POR UN PATD
B21: TRANSFERENCIAS SISTEMÁTICAS LOCAL O NTERNACIONAL | O21: NO HAY DESTINATARIOS | Q21: 7.8 - INTERÉS LEGÍTIMO | T21: TITULARES EXTERNOS - NNA - ENTREGADOS POR UN RESPONSABLES
B22: MENSAJERIA ACELERADA O COURIER | E22: PATD INTERNO | F22: NACIONAL | H22: ANTES DEL PROYECTO PDP | I22: TRATAMIENTO ACTIVO | L22: BÁSICOS | N22: NO HAY ENCARGADO DE TRATAMIENTO | O22: IESS | T22: TITULARES EXTERNOS - NNA - RECOGIDOS POR UN PATD
E23: PATD DESTINATARIO | F23: INTERNACIONAL | H23: DURANTE PROYECTO PDP | I23: TRATAMIENTO INACTIVO | L23: IDENTIFICACIÓN | N23: NACIONAL | O23: MIN. TRABAJO | T23: TITULARES EXTERNOS - VISITANTES - RECOGIDOS POR UN PATD
E24: PATD ENCARGADO | F24: NO HAY CADENA DE 3ras PARTES | H24: SG-PDP VALIDADO | I24: CAMBIOS EN MEDIDA DE SEGURIDAD | L24: IDENTIFICACIÓN Y UBICACIÓN | N24: INTERNACIONAL | O24: UAFE | T24: TITULARES EXTERNOS - CANDIDATOS - TOMADOS DE PÁGINA WEB
E25: PATD 3ra PARTE | I25: CAMBIO DE ENCARGADO | L25: PROFESION | O25: SEPS | T25: TITULARES EXTERNOS - CANDIDATOS - RECOGIDOS POR PATD
I26: CAMBIO EN LA CADENA 3ras PARTES | L26: CONTACTO | O26: ARCOTEL
L27: ESPECIALES | O27: PLATAFORMA DIGITAL OODO
L28: SENSIBLES | O28: CORREO ELECTRÓNICO (MS OFFICE, GMAIL, OTRO)
L29: SALUD | O29: PLATAFORMA OODO y MS OFFICE
L30: NNA | O30: PLATAFORMA OODO y FACTURADOR SRI
L31: CREDITICIOS
L32: DISCAPACIDAD
L33: DIFUNTOS
L34: COMBINADOS
L35: HOJA DE VIDA, CÉDULA, OTROS
L36: VIDEOS
L37: IMÁGENES
L38: REFERENCIAS

Sheet RAT-MTGE MEDICINA OCUPACIONAL
C3: NOMBRE DE LA ACTIVIDAD DE TRATAMIENTO | D3: EXÁMENES MÉDICOS OBLIGATORIOS (Pre ocupacional, Periódica y Retiro)
C4: UBICACIÓN DE LA ACTIVIDAD DE TRATAMIENTO
C5: DEPARTAMENTO QUE REALIZA EL TRATAMIENTO | D5: PATD DONDE SE REALIZA EL TRATAMIENTO | E5: UBICACIÓN DEL ENCARGADO DE TRATAMIENTO | F5: UBICACIÓN CADENA DE 3ras PARTES COMUNICADAS | G5: IDENTIFICACIÓN DEL PATD DONDE SE REALIZA EL TRATAMIENTO
C6: OFICINAS TRAUMA ORTOPEDICS | D6: PATD ENCARGADO | E6: LABORATORIOS CLÍNICOS | F6: NACIONAL | G6: ENCARGADO DE TRATAMIENTO
C7: CONTROL DE CAMBIOS DE LA ACTIVIDAD DE TRATAMIENTO
C8: INICIO DE LA ACTIVIDAD DE TRATAMIENTO | D8: FECHA DE REVISÓN-AUDITORÍA DEL TRATAMIENTO | E8: PRÓXIMA REVISIÓN-AUDITORÍA | F8: RESULTADO DE LA REVISIÓN.AUDITORÍA
C9: ANTES DEL PROYECTO PDP | F9: TRATAMIENTO ACTIVO
L10: CATEGORÍAS DE DATOS PERSONALES (R-005-2026, 15.2) | Q10: MEDIDAS DE SEGURIDAD REFORZADAS DERIVADAS DE LA EIPD (R-005-2026, 12.4)
C11: NOMBRE RESPONSABLES DE TRATAMIENTO (38.1-A) | D11: DATOS DE CONTACTO RESPONSABLE DE TRATAMIENTO (38.1-B) | E11: NOMBRE DELEGADO PROTECCION DATOS (38.1-C) | F11: DATOS DE CONTACTO DPD (38.1-D) | G11: FINALIDADES DEL TRATAMIENTO (38.2) | H11: DESTINATARIOS (38.3) | K11: DESCRIPCIÓN DEL TRATAMIENTO (R-005-2026, 15.1) | L11: CATEGORÍA DE LOS DATOS RECOGIDOS | M11: TIPOS DE DATOS DE DATOS RECOGIDOS | N11: TITULARES DE DATOS PERSONALES DE QUIENES SE TRATA LA INFORMACIÓN (R-005-2026, 15.3) | O11: FRECUENCIA DEL TRATAMIENTO (R-005-2026, 15.4) | P11: PERMANENCIA DEL TRATAMIENTO (R-005-2026, 15.5) | Q11: REFUERZO MEDIDAS JURÍDICAS (R-005-2026, 12.4) | R11: REFUERZO MEDIDAS ORGANIZATIVAS (R-005-2026, 12.4) | S11: REFUERZO MEDIDAS ADMINISTRATIVAS (R-005-2026, 12.4) | T11: REFUERZO MEDIDAS TÉCNICAS (R-005-2026, 12.4) | U11: REFUERZO MEDIDAS FÍSICAS (R-005-2026, 12.4)
G12: Cumplir con el marco normativo impuesto por el Código del Trabajo (Art. 42 - Obligaciones del empleador) y la normativa del IESS (Resolución CD 513 - Reglamento del seguro general de riesgos del trabajo) | H12: MÉDICO OCUPACIONAL + PLATAFORMA LABORATORIO + CORREO ELECTRÓNICO | K12: COMO REQUISITO DE INGRESO SE REALIZAN EXÁMENES MÉDICOS AL NUEVO INGRESO, DE MANERA PERIÓDICA A TRABAJADORES ACTIVOS Y A TODO TRABAJADOR QUE FINALICE LA RELACIÓN LABORAL. EL TIPO DE EXAMEN DEPENDERÁ DE LA MATRIZ DE RIESGO DE LA POSICIÓN QUE OCUPE EL TRABAJADOR | L12: =+D14 -> ESPECIALES | M12: SALUD | N12: =+C14 -> TITULARES INTERNOS - EMPLEADO | O12: PERIÓDICA RECURRENTE | P12: TEMPORAL | Q12: Las medidas reforzadas del área JURÍDICA están listadas en el documento de MS.EXCEL: EIPD - MEDICINA OCUPACIONAL - TRAUMA ORTOPEDICS - JUNIO2026.XLS | R12: Las medidas reforzadas del área JURÍDICA están listadas en el documento de MS.EXCEL: EIPD - MEDICINA OCUPACIONAL - TRAUMA ORTOPEDICS - JUNIO2026.XLS | S12: Las medidas reforzadas del área JURÍDICA están listadas en el documento de MS.EXCEL: EIPD - MEDICINA OCUPACIONAL - TRAUMA ORTOPEDICS - JUNIO2026.XLS | T12: Las medidas reforzadas del área JURÍDICA están listadas en el documento de MS.EXCEL: EIPD - MEDICINA OCUPACIONAL - TRAUMA ORTOPEDICS - JUNIO2026.XLS | U12: Las medidas reforzadas del área JURÍDICA están listadas en el documento de MS.EXCEL: EIPD - MEDICINA OCUPACIONAL - TRAUMA ORTOPEDICS - JUNIO2026.XLS
C13: TITULARES (38.4-A) (EMPLEADOS, NIÑOS, ADOLESCENTES, DIFUNTOS, RESPONSABLES, VISITANTES, OTROS) | D13: CATEGORIA DE LOS DATOS (38.4-B) ESPECIALES, COMUNES, MIXTOS | E13: USO DE PERFILES (38.5) | F13: TRANSFERENCIA INTERNACIONAL DE DATOS (38.6) | G13: BASES LEGITIMADORAS DEL TRATAMIENTO (38.7) | H13: PLAZOS DE RETENCION PARA LA SUPRESION (38.8-A)
C14: TITULARES INTERNOS - EMPLEADO | D14: ESPECIALES | E14: SI | F14: SI - USO DE CORREO ELECTRÓNICO | G14: 7.2 - OBLIGACIÓN LEGAL | H14: RELACIÓN CONTRACTUAL + 7 AÑOS | K14: TRATAMIETOS QUE OBLIGAN LA EIPD (GRAN ESCALA) (SI NO ELIJA NINGUNO) (R-005-2026, Art. 14) | L14: NÚMERO DE TITULARES (R-005-2026, 7.1) | M14: VOLUMEN DE DATOS PERSONALES (R-005-2026, 7.2) | N14: CATEGORÍAS DE DATOS PERSONALES (R-005-2026, 7.3) | O14: FRECUENCIA DEL TRATAMIENTO DATOS PERSONALES (R-005-2026, 7.4) | P14: PERMANENCIA DEL TRATAMIENTO DE DATOS PERSONALES (R-005-2026, 7.5) | Q14: ALCANCE GEOGRÁFICO DEL TRATAMIENTO (R-005-2026, 7.6) | R14: MTGE (R-005-2026, Art. 7) | S14: EIPD (R-005-2026, 12.1) | T14: DPD (R-005-2026, 12.2) | U14: REFORZAR PANSI (R-005-2026, 12.4)
D15: BREVE DESCRIPCION DE LAS MEDIDAS TECNICAS JURIDICAS ADMINISTRATIVAS ORGANIZATIVAS Y FISICAS PARA PROTEGER LOS DATOS (Artículo 38 del RGLOPDP + R-005-2026, 15.6) | K15: SALUD | L15: DE 0 A 1.000 | M15: HASTA 10 TIPOS DE DATOS POR TITULAR | N15: ESPECIALES | O15: PERIÓDICA RECURRENTE | P15: TEMPORAL | Q15: ALCANCE LOCAL | R15: =VLOOKUP(L15,'[1]CRITERIOS MTGE'!$B$7:$C$10,2,FALSE)+VLOOKUP(M15,'[1]CRITERIOS MTGE'!$E$7:$F$10,2,FALSE)+VLOOKUP(N15,'[1]CRITERIOS MTGE'!$H$7:$I$9,2,FALSE)+VLOOKUP(O15,'[1]CRITERIOS MTGE'!$K$7:$L$9,2,FALSE)+VLOOKUP(P15,'[1]CRITERIOS MTGE'!$N$7:$O$9,2,FALSE)+VLOOKUP(Q15,'[1]CRITERIOS MTGE'!$Q$7:$R$9,2,FALSE) -> 6.5 | S15: =IF($R$15>=6,"OBLIGADO","NO OBLIGADO") -> OBLIGADO | T15: =IF($R$15>=6,"OBLIGADO","NO OBLIGADO") -> OBLIGADO | U15: =IF($R$15>=6,"OBLIGADO","NO OBLIGADO") -> OBLIGADO
C16: EL TRATAMIENTO SE REALIZA CON IA | D16: JURIDICAS (38.9-A) | E16: ORGANIZATIVAS (38.9-B) | F16: ADMINISTRATIVAS (38.9-C) | G16: TÉCNICAS (38.9-D) | H16: FÍSICAS (38.9-E)
C17: NO | D17: Las medidas Jurídicas son las definidas para adecuar el nivel de seguridad (PANSI) verificar en este enlace: | E17: Las medidas Organizativas son las definidas para adecuar el nivel de seguridad (PANSI) verificar en este enlace: | F17: Las medidas Administrativas son las definidas para adecuar el nivel de seguridad (PANSI) verificar en este enlace: | G17: Las medidasTécnicas son las definidas para adecuar el nivel de seguridad (PANSI) verificar en este enlace: | H17: Las medidas Físicas son las definidas para adecuar el nivel de seguridad (PANSI) verificar en este enlace:

Sheet DERECHOS Y LIBERTADES AFECTADOS
C2: DERECHOS Y LIBERTADES QUE SON AFECTADOS POR LA CATEGORÍA Y TIPO DE DATOS QUE USA EL TRATAMIENTO
C3: NOMBRE DEL TRATAMIENTO | H3: TIPOS DE DATOS
C4: ='RAT-MTGE MEDICINA OCUPACIONAL'!D3 -> EXÁMENES MÉDICOS OBLIGATORIOS (Pre ocupacional, Periódica y Retiro) | H4: =+'RAT-MTGE MEDICINA OCUPACIONAL'!M12 -> SALUD
C5: NÚMERO DE TITULARES | H5: DESCRIPCIÓN DEL TRATAMIENTO
C6: =+'RAT-MTGE MEDICINA OCUPACIONAL'!L15 -> DE 0 A 1.000 | D6: ESTADO DE LA TÉCNICA | H6: =+'RAT-MTGE MEDICINA OCUPACIONAL'!K12 -> COMO REQUISITO DE INGRESO SE REALIZAN EXÁMENES MÉDICOS AL NUEVO INGRESO, DE MANERA PERIÓDICA A TRABAJADORES ACTIVOS Y A TODO TRABAJADOR QUE FINALICE LA RELACIÓN LABORAL. EL TIPO DE EXAMEN DEPENDERÁ DE LA MATRIZ DE RIESGO DE LA POSICIÓN QUE OCUPE EL TRABAJADOR
D8: SG-PDP VALIDADO Y EN PRIMER TRIMESTRE OPERATIVO | E8: GRC DOCUMENTADO CON PDP INCLUIDO. PANSI FASE 1 | F8: DOCUMENTACIÓN SIN PDP INCLUIDO | G8: DOCUMENTACIÓN INEXISTENTE | H8: COMENTARIOS
D9: 1 MÍNIMO | E9: 2 ALTO | F9: 3 GRAVE | G9: 4 MUY GRAVE
C10: 1 DERECHO A LA PRIVACIDAD E INTIMIDAD Garantiza que nadie puede entrometerse en ciertos espacios o aspectos de tu vida sin tu consentimiento, abarca vida personal y familiar, inviolabilidad de domicilio y secreto de las comunicaciones. La triada PDP le otorga el derecho de control y decisión sobre como las organizaciones utilizan los datos del Titular | F10: BRECHA IDENTIFICADA. HECHA PÚBLICA. DATOS ESPECIALES. MAS DE 100 TITULARES. NO HAY PROYECTO SG-PDP. NO SE TRABAJA 47 LOPDP. HAY GRC DESARTICULADO. | H10: Los datos están en distintos repositorios (Laboratorio, Correo electronico, Médico ocupacional, Área de recursos humanos, archivo impreso, otros), sin esquema PDP y con bajo nivel de seguridad en PDP (PANSI EN FASE INICIAL). No hay contratos con cláusulas PDP con encargados de tratamiento . | I10: =IFERROR(_xlfn.IFS(D10="BRECHA IDENTIFICADA. NO HECHA PÚBLICA. DATOS BÁSICOS. MENOS DE 100 TITULARES. SG-PDP VALIDADO Y MANTENIDO. GRC ARTICULADO Y REFRESCADO",1,E10="BRECHA IDENTIFICADA. NO HECHA PÚBLICA. DATOS BÁSICOS. MAS DE 100 TITULARES. SG-PDP VALIDADO EN FASE PROYECTO. SE TRABAJA 47 LOPDP. GRC ARTICULADO",2,F10="BRECHA IDENTIFICADA. HECHA PÚBLICA. DATOS ESPECIALES. MAS DE 100 TITULARES. NO HAY PROYECTO SG-PDP. NO SE TRABAJA 47 LOPDP. HAY GRC DESARTICULADO.",3,G10="BRECHA IDENTIFICADA. HECHA PÚBLICA. DATOS ESPECIALES. MAS DE 100 TITULARES. NO HAY PROYECTO SG-PDP. NO HAY GRC.",4),0) -> 3
B11: DERECHOS Y LIBERTADES DE LOS TITULARES | C11: 2 DERECHO A LA VIDA Reconoce la existencia de cualquier persona por el simple hecho de estar viva. Es el requisito indispensable para poder disfrutar de todos los demás derechos. Abarca protección contra terceros, el deber de garantizar que nadie, ni otros individuos ni el Estado, atente arbitrariamente contra tu vida. También se debe asegurar las condiciones básicas para el desarrollo humano, como la salud, la alimentación y un entorno seguro. | F11: BRECHA IDENTIFICADA. HECHA PÚBLICA. DATOS ESPECIALES. MAS DE 100 TITULARES. NO HAY PROYECTO SG-PDP. NO SE TRABAJA 47 LOPDP. HAY GRC DESARTICULADO. | H11: Si bien son datos de categoría especial una posible brecha no pone en riesgo la vida de ningún Titular ni las condiciones para el desarrollo humano como la salud, alimentación o entorno seguro. Se está trabajando para iniciar el proyecto de adecuación del nivel de seguridad inicial y por ello se califica el nivel de impacto o posible daño como alto por tratarse de datos de categoría especial pero con impacto menor sobre el derecho a la vida digna, pero una brecha de datos de categoría especial puede comprometer otros derechos y libertades causando un daño a los titulares de los datos. | I11: =IFERROR(_xlfn.IFS(D11="BRECHA IDENTIFICADA. NO HECHA PÚBLICA. DATOS BÁSICOS. MENOS DE 100 TITULARES. SG-PDP VALIDADO Y MANTENIDO. GRC ARTICULADO Y REFRESCADO",1,E11="BRECHA IDENTIFICADA. NO HECHA PÚBLICA. DATOS BÁSICOS. MAS DE 100 TITULARES. SG-PDP VALIDADO EN FASE PROYECTO. SE TRABAJA 47 LOPDP. GRC ARTICULADO",2,F11="BRECHA IDENTIFICADA. HECHA PÚBLICA. DATOS ESPECIALES. MAS DE 100 TITULARES. NO HAY PROYECTO SG-PDP. NO SE TRABAJA 47 LOPDP. HAY GRC DESARTICULADO.",3,G11="BRECHA IDENTIFICADA. HECHA PÚBLICA. DATOS ESPECIALES. MAS DE 100 TITULARES. NO HAY PROYECTO SG-PDP. NO HAY GRC.",4),0) -> 3
C12: 3 DERECHO A LA SALUD Es un derecho inclusivo y comprende un amplio conjunto de factores que pueden contribuir a una vida sana, entre otros, el agua potable salubre, el saneamiento adecuado, la alimentación segura y unas condiciones laborales saludables | I12: =IFERROR(_xlfn.IFS(D12="BRECHA IDENTIFICADA. NO HECHA PÚBLICA. DATOS BÁSICOS. MENOS DE 100 TITULARES. SG-PDP VALIDADO Y MANTENIDO. GRC ARTICULADO Y REFRESCADO",1,E12="BRECHA IDENTIFICADA. NO HECHA PÚBLICA. DATOS BÁSICOS. MAS DE 100 TITULARES. SG-PDP VALIDADO EN FASE PROYECTO. SE TRABAJA 47 LOPDP. GRC ARTICULADO",2,F12="BRECHA IDENTIFICADA. HECHA PÚBLICA. DATOS ESPECIALES. MAS DE 100 TITULARES. NO HAY PROYECTO SG-PDP. NO SE TRABAJA 47 LOPDP. HAY GRC DESARTICULADO.",3,G12="BRECHA IDENTIFICADA. HECHA PÚBLICA. DATOS ESPECIALES. MAS DE 100 TITULARES. NO HAY PROYECTO SG-PDP. NO HAY GRC.",4),0) -> 0
C13: 4 DERECHO A LA SEGURIDAD SOCIAL Garantiza a las personas protección contra riesgos e imprevistos sociales, como enfermedad, desempleo, invalidez, vejez o maternidad. Su objetivo es asegurar ingresos y acceso a la salud para mantener una vida digna. | I13: =IFERROR(_xlfn.IFS(D13="BRECHA IDENTIFICADA. NO HECHA PÚBLICA. DATOS BÁSICOS. MENOS DE 100 TITULARES. SG-PDP VALIDADO Y MANTENIDO. GRC ARTICULADO Y REFRESCADO",1,E13="BRECHA IDENTIFICADA. NO HECHA PÚBLICA. DATOS BÁSICOS. MAS DE 100 TITULARES. SG-PDP VALIDADO EN FASE PROYECTO. SE TRABAJA 47 LOPDP. GRC ARTICULADO",2,F13="BRECHA IDENTIFICADA. HECHA PÚBLICA. DATOS ESPECIALES. MAS DE 100 TITULARES. NO HAY PROYECTO SG-PDP. NO SE TRABAJA 47 LOPDP. HAY GRC DESARTICULADO.",3,G13="BRECHA IDENTIFICADA. HECHA PÚBLICA. DATOS ESPECIALES. MAS DE 100 TITULARES. NO HAY PROYECTO SG-PDP. NO HAY GRC.",4),0) -> 0
C14: 5 DERECHO A LA IDENTIDAD Garantiza el derecho a tener un nombre, un apellido, una nacionalidad, y la potestad de decidir sobre la conformación de la propia individualidad familiar, cultural, social y de género | I14: =IFERROR(_xlfn.IFS(D14="BRECHA IDENTIFICADA. NO HECHA PÚBLICA. DATOS BÁSICOS. MENOS DE 100 TITULARES. SG-PDP VALIDADO Y MANTENIDO. GRC ARTICULADO Y REFRESCADO",1,E14="BRECHA IDENTIFICADA. NO HECHA PÚBLICA. DATOS BÁSICOS. MAS DE 100 TITULARES. SG-PDP VALIDADO EN FASE PROYECTO. SE TRABAJA 47 LOPDP. GRC ARTICULADO",2,F14="BRECHA IDENTIFICADA. HECHA PÚBLICA. DATOS ESPECIALES. MAS DE 100 TITULARES. NO HAY PROYECTO SG-PDP. NO SE TRABAJA 47 LOPDP. HAY GRC DESARTICULADO.",3,G14="BRECHA IDENTIFICADA. HECHA PÚBLICA. DATOS ESPECIALES. MAS DE 100 TITULARES. NO HAY PROYECTO SG-PDP. NO HAY GRC.",4),0) -> 0
C15: 6 DERECHO A LA EDUCACIÓN Garantiza el acceso a una enseñanza inclusiva, equitativa y de calidad para todas las personas. Es considerado un "derecho multiplicador" porque es esencial para poder ejercer, exigir y disfrutar del resto de derechos humanos | I15: =IFERROR(_xlfn.IFS(D15="BRECHA IDENTIFICADA. NO HECHA PÚBLICA. DATOS BÁSICOS. MENOS DE 100 TITULARES. SG-PDP VALIDADO Y MANTENIDO. GRC ARTICULADO Y REFRESCADO",1,E15="BRECHA IDENTIFICADA. NO HECHA PÚBLICA. DATOS BÁSICOS. MAS DE 100 TITULARES. SG-PDP VALIDADO EN FASE PROYECTO. SE TRABAJA 47 LOPDP. GRC ARTICULADO",2,F15="BRECHA IDENTIFICADA. HECHA PÚBLICA. DATOS ESPECIALES. MAS DE 100 TITULARES. NO HAY PROYECTO SG-PDP. NO SE TRABAJA 47 LOPDP. HAY GRC DESARTICULADO.",3,G15="BRECHA IDENTIFICADA. HECHA PÚBLICA. DATOS ESPECIALES. MAS DE 100 TITULARES. NO HAY PROYECTO SG-PDP. NO HAY GRC.",4),0) -> 0
C16: 7 DERECHO A NO SER DISCRIMINADO Garantiza que todas las personas sean tratadas con la misma dignidad y tengan acceso a los mismos derechos y oportunidades. La Constitución de la República prohíbe cualquier forma de exclusión o distinción que busque menoscabar el pleno ejercicio de los derechos de una persona. Dentro de las discriminaciones prohibidas en Ecuador están: Por genero, etnia, religión, ideología política. | I16: =IFERROR(_xlfn.IFS(D16="BRECHA IDENTIFICADA. NO HECHA PÚBLICA. DATOS BÁSICOS. MENOS DE 100 TITULARES. SG-PDP VALIDADO Y MANTENIDO. GRC ARTICULADO Y REFRESCADO",1,E16="BRECHA IDENTIFICADA. NO HECHA PÚBLICA. DATOS BÁSICOS. MAS DE 100 TITULARES. SG-PDP VALIDADO EN FASE PROYECTO. SE TRABAJA 47 LOPDP. GRC ARTICULADO",2,F16="BRECHA IDENTIFICADA. HECHA PÚBLICA. DATOS ESPECIALES. MAS DE 100 TITULARES. NO HAY PROYECTO SG-PDP. NO SE TRABAJA 47 LOPDP. HAY GRC DESARTICULADO.",3,G16="BRECHA IDENTIFICADA. HECHA PÚBLICA. DATOS ESPECIALES. MAS DE 100 TITULARES. NO HAY PROYECTO SG-PDP. NO HAY GRC.",4),0) -> 0
C17: 8 DERECHO A LA AUTODETERMINACIÓN Reconocido principalmente a favor de las comunidades, pueblos y nacionalidades indígenas. Les garantiza la libertad de decidir su propio destino político, económico, social y cultural, así como el control sobre sus territorios y formas de organización, sin interferencia externa | I17: =IFERROR(_xlfn.IFS(D17="BRECHA IDENTIFICADA. NO HECHA PÚBLICA. DATOS BÁSICOS. MENOS DE 100 TITULARES. SG-PDP VALIDADO Y MANTENIDO. GRC ARTICULADO Y REFRESCADO",1,E17="BRECHA IDENTIFICADA. NO HECHA PÚBLICA. DATOS BÁSICOS. MAS DE 100 TITULARES. SG-PDP VALIDADO EN FASE PROYECTO. SE TRABAJA 47 LOPDP. GRC ARTICULADO",2,F17="BRECHA IDENTIFICADA. HECHA PÚBLICA. DATOS ESPECIALES. MAS DE 100 TITULARES. NO HAY PROYECTO SG-PDP. NO SE TRABAJA 47 LOPDP. HAY GRC DESARTICULADO.",3,G17="BRECHA IDENTIFICADA. HECHA PÚBLICA. DATOS ESPECIALES. MAS DE 100 TITULARES. NO HAY PROYECTO SG-PDP. NO HAY GRC.",4),0) -> 0
C18: 9 DERECHO A LA LIBERTAD Garantiza el pleno desarrollo de la personalidad de cada individuo sin injerencias arbitrarias. Está consagrado en la Constitución e incluye tanto la libertad física (no ser detenido sin orden legal) como las libertades civiles (expresión, tránsito, conciencia) | I18: =IFERROR(_xlfn.IFS(D18="BRECHA IDENTIFICADA. NO HECHA PÚBLICA. DATOS BÁSICOS. MENOS DE 100 TITULARES. SG-PDP VALIDADO Y MANTENIDO. GRC ARTICULADO Y REFRESCADO",1,E18="BRECHA IDENTIFICADA. NO HECHA PÚBLICA. DATOS BÁSICOS. MAS DE 100 TITULARES. SG-PDP VALIDADO EN FASE PROYECTO. SE TRABAJA 47 LOPDP. GRC ARTICULADO",2,F18="BRECHA IDENTIFICADA. HECHA PÚBLICA. DATOS ESPECIALES. MAS DE 100 TITULARES. NO HAY PROYECTO SG-PDP. NO SE TRABAJA 47 LOPDP. HAY GRC DESARTICULADO.",3,G18="BRECHA IDENTIFICADA. HECHA PÚBLICA. DATOS ESPECIALES. MAS DE 100 TITULARES. NO HAY PROYECTO SG-PDP. NO HAY GRC.",4),0) -> 0
C19: 10 DERECHO A LA INTEGRIDAD FÍSICA Garantiza el respeto, cuidado y preservación de tu cuerpo y salud. Los ciudadanos no pueden ser víctima de agresiones, lesiones, dolores o sufrimientos corporales. Protege a los ciudadanos de toda forma de violencia y maltrato | I19: =IFERROR(_xlfn.IFS(D19="BRECHA IDENTIFICADA. NO HECHA PÚBLICA. DATOS BÁSICOS. MENOS DE 100 TITULARES. SG-PDP VALIDADO Y MANTENIDO. GRC ARTICULADO Y REFRESCADO",1,E19="BRECHA IDENTIFICADA. NO HECHA PÚBLICA. DATOS BÁSICOS. MAS DE 100 TITULARES. SG-PDP VALIDADO EN FASE PROYECTO. SE TRABAJA 47 LOPDP. GRC ARTICULADO",2,F19="BRECHA IDENTIFICADA. HECHA PÚBLICA. DATOS ESPECIALES. MAS DE 100 TITULARES. NO HAY PROYECTO SG-PDP. NO SE TRABAJA 47 LOPDP. HAY GRC DESARTICULADO.",3,G19="BRECHA IDENTIFICADA. HECHA PÚBLICA. DATOS ESPECIALES. MAS DE 100 TITULARES. NO HAY PROYECTO SG-PDP. NO HAY GRC.",4),0) -> 0
C20: 11 DERECHO A LA INTEGRIDAD MORAL Este derecho protege al individuo frente a humillaciones, coacciones para actuar en contra de su conciencia y tratos que menosprecien su estima | I20: =IFERROR(_xlfn.IFS(D20="BRECHA IDENTIFICADA. NO HECHA PÚBLICA. DATOS BÁSICOS. MENOS DE 100 TITULARES. SG-PDP VALIDADO Y MANTENIDO. GRC ARTICULADO Y REFRESCADO",1,E20="BRECHA IDENTIFICADA. NO HECHA PÚBLICA. DATOS BÁSICOS. MAS DE 100 TITULARES. SG-PDP VALIDADO EN FASE PROYECTO. SE TRABAJA 47 LOPDP. GRC ARTICULADO",2,F20="BRECHA IDENTIFICADA. HECHA PÚBLICA. DATOS ESPECIALES. MAS DE 100 TITULARES. NO HAY PROYECTO SG-PDP. NO SE TRABAJA 47 LOPDP. HAY GRC DESARTICULADO.",3,G20="BRECHA IDENTIFICADA. HECHA PÚBLICA. DATOS ESPECIALES. MAS DE 100 TITULARES. NO HAY PROYECTO SG-PDP. NO HAY GRC.",4),0) -> 0
C21: 12 DERECHO A LA INTEGRIDAD PSIQUICA Garantiza el desarrollo de la salud mental y una vida libre de violencia tanto en el ámbito público como privado para conservar intactas y proteger las habilidades emocionales, psicológicas e intelectuales frente a cualquier tipo de agresión o vulneración. | I21: =IFERROR(_xlfn.IFS(D21="BRECHA IDENTIFICADA. NO HECHA PÚBLICA. DATOS BÁSICOS. MENOS DE 100 TITULARES. SG-PDP VALIDADO Y MANTENIDO. GRC ARTICULADO Y REFRESCADO",1,E21="BRECHA IDENTIFICADA. NO HECHA PÚBLICA. DATOS BÁSICOS. MAS DE 100 TITULARES. SG-PDP VALIDADO EN FASE PROYECTO. SE TRABAJA 47 LOPDP. GRC ARTICULADO",2,F21="BRECHA IDENTIFICADA. HECHA PÚBLICA. DATOS ESPECIALES. MAS DE 100 TITULARES. NO HAY PROYECTO SG-PDP. NO SE TRABAJA 47 LOPDP. HAY GRC DESARTICULADO.",3,G21="BRECHA IDENTIFICADA. HECHA PÚBLICA. DATOS ESPECIALES. MAS DE 100 TITULARES. NO HAY PROYECTO SG-PDP. NO HAY GRC.",4),0) -> 0
G22: IMPACTO SOBRE DERECHOS Y LIBERTADES VALORACIÓN DEL DAÑO SOBRE EL TITULAR DE LOS DATOS | I22: =AVERAGEIF(I10:I21,"<>0") -> 3

Sheet OPERACIONES-MEDIOS-PROBABILIDAD
C2: PROBABILIDAD QUE SEAN EXPLOTADAS LAS VULNERABILIDADES DE LAS OPERACIOES DE TRATAMIENTO O LOS MEDIOS UTILIZADOS
C3: NOMBRE DEL TRATAMIENTO | H3: UBICACIÓN 3ras PARTES
C4: ='RAT-MTGE MEDICINA OCUPACIONAL'!D3 -> EXÁMENES MÉDICOS OBLIGATORIOS (Pre ocupacional, Periódica y Retiro) | H4: =+'RAT-MTGE MEDICINA OCUPACIONAL'!F6 -> NACIONAL
C5: UBICACIÓN ENCARGADO DE TRATAMIENTO | H5: TRANSFERENCIAS INTERNACIONALES | O5: Como la fase de implantación del SG-PDP incide sobre la probabilidad que exista una brecha o fuga de los datos a causa de malas practicas en el PATD
C6: =+'RAT-MTGE MEDICINA OCUPACIONAL'!E6 -> LABORATORIOS CLÍNICOS | D6: ESTADO DE LA TÉCNICA | H6: =+'RAT-MTGE MEDICINA OCUPACIONAL'!F14 -> SI - USO DE CORREO ELECTRÓNICO | M6: NULO | N6: EXISTE UN ESQUEMA DE PROTECCIÓN DE DATOS IMPLANTADO Y VALIDADO. LAS RUTINAS PDP SE PRACTICAN Y ESTÁN DENTRO DEL PLAN DE SIMULACROS. EL TITULAR INTERNO QUE REALIZA EL TRATAMIENTO ESTÁ CUMPLIENDO CON EL PROGRAMA DE CONSCIENCIACIÓN.
C8: OPERACIONES DEL TRATAMIENTO ACTIVIDADES REQUERIDAS PARA RECOGER, CONSERVAR, TRANSFERIR, BLOQUEAR, ENCRIPTAR, PSEUDONIMIZAR O DAR TRATAMIENTO A DATOS PERSONALES | D8: SG-PDP VALIDADO Y EN PRIMER TRIMESTRE OPERATIVO | E8: GRC DOCUMENTADO CON PDP INCLUIDO. PANSI FASE 1 | F8: DOCUMENTACIÓN SIN PDP INCLUIDO | G8: DOCUMENTACIÓN INEXISTENTE | H8: COMENTARIOS SOBRE AMENAZAS | M8: BAJO | N8: EXISTE UN ESQUEMA DE PROTECCIÓN DE DATOS EN FASE DE IMPLANTACIÓN. LAS RUTINAS PDP ESTÁN DISEÑADAS, SE PRACTICAN Y ESTÁN DENTRO DEL PLAN DE SIMULACROS. EL TITULAR INTERNO QUE REALIZA EL TRATAMIENTO ESTÁ CUMPLIENDO CON EL PROGRAMA DE CONSCIENCIACIÓN. LAS OPERACIONES DEL TRATAMIENTO POSEEN UN NIVEL DE SEGURIDAD EN PROCESO DE FORTALECIMIENTO.
D9: 1 IMPROBABLE | E9: 2 MEDIA - BAJA | F9: 3 MEDIA - ALTA | G9: 4 MUY PROBABLE | M9: MEDIO | N9: EXISTE UN ESQUEMA DE PROTECCIÓN DE DATOS EN FASE DE DOCUMENTAL. LAS RUTINAS PDP ESTÁN DISEÑADAS, AÚN NO SE PRACTICAN NI ESTÁN DENTRO DEL PLAN DE SIMULACROS. EL TITULAR INTERNO QUE REALIZA EL TRATAMIENTO ESTÁ CUMPLIENDO CON EL PROGRAMA DE profesonalización del PANSI. SOLO SE HA CUBIERTO LA FASE INICIAL DEL PANSI. AÚN NO HAY CLARIDAD SOBRE ¿QUE ES UN SG-PDP?. LAS OPERACIONES DEL TRATAMIENTO SON VULNERABLES Y PUEDEN PERMITIR PRACTICAS INSEGURAS.
C10: ENVIO DE LISTADO AL LABORATORIO (PATD RESPONSABLE) | F10: PROYECTO SG-PDP INSIPIENTE. HAY DPO, ALGUNOS DOCUMENTOS, HAY EQUIPO INTERNO. NO HAY GRC. NO HAY PANSI | H10: Los datos están en distintos repositorios (Laboratorio, Correo electronico, Médico ocupacional, Área de recursos humanos, archivo impreso, otros), sin esquema PDP y con bajo nivel de seguridad en PDP (PANSI EN FASE INICIAL). No hay contratos con cláusulas PDP con encargados de tratamiento (Laboratoio y Médico Ocupacional), ni con PATD de TRAUMA ORTOPEDICS). | I10: =IFERROR(_xlfn.IFS(D10="EXISTE UN SG-PDP VALIDADO Y MANTENIDO. LAS RUTINAS PDP SE PRACTICAN. PLAN DE SIMULACROS ACTIVO. GRC ARTICULADO Y REFERESCADO",1,E10="EXISTE PROYECTO SG-PDP. NO ESTÁ VALIDADO. LAS RUTINAS PDP SE PRACTICAN. PLAN DE SIMULACROS FASE INICIAL. PANSI EN FASE INICIAL.",2,F10="PROYECTO SG-PDP INSIPIENTE. HAY DPO, ALGUNOS DOCUMENTOS, HAY EQUIPO INTERNO. NO HAY GRC. NO HAY PANSI",3,G10="NO HAY PROYECTO SG-PDP. HAY DPO, ALGUNOS DOCUMENTOS, NO HAY EQUIPO INTERNO. NO HAY APOYO DE LA GERENCIA. EL DPD TIENE TODA LA CARGA",4),0) -> 3 | M10: ALTO | N10: Solo existen documentos desarticulados, no cumple los requisitos del artículo 47, no están identificados los PATD ni los puntos de interacción Titular - RT, la R-0028-2025 y LA R-0005-2026 están consideradas en la documentación existente. Todo esto plantea un escenario de alta probabilidad de prácticas inseguras
B11: DERECHOS Y LIBERTADES DE LOS TITULARES | C11: CARGA DE DATOS EN PLATAFORMA (PATD ENCARGADO) | F11: PROYECTO SG-PDP INSIPIENTE. HAY DPO, ALGUNOS DOCUMENTOS, HAY EQUIPO INTERNO. NO HAY GRC. NO HAY PANSI | H11: Los datos están en distintos repositorios (Laboratorio, Correo electronico, Médico ocupacional, Área de recursos humanos, archivo impreso, otros), sin esquema PDP y con bajo nivel de seguridad en PDP (PANSI EN FASE INICIAL). No hay contratos con cláusulas PDP con encargados de tratamiento (Laboratoio y Médico Ocupacional) | I11: =IFERROR(_xlfn.IFS(D11="EXISTE UN SG-PDP VALIDADO Y MANTENIDO. LAS RUTINAS PDP SE PRACTICAN. PLAN DE SIMULACROS ACTIVO. GRC ARTICULADO Y REFERESCADO",1,E11="EXISTE PROYECTO SG-PDP. NO ESTÁ VALIDADO. LAS RUTINAS PDP SE PRACTICAN. PLAN DE SIMULACROS FASE INICIAL. PANSI EN FASE INICIAL.",2,F11="PROYECTO SG-PDP INSIPIENTE. HAY DPO, ALGUNOS DOCUMENTOS, HAY EQUIPO INTERNO. NO HAY GRC. NO HAY PANSI",3,G11="NO HAY PROYECTO SG-PDP. HAY DPO, ALGUNOS DOCUMENTOS, NO HAY EQUIPO INTERNO. NO HAY APOYO DE LA GERENCIA. EL DPD TIENE TODA LA CARGA",4),0) -> 3
C12: ACCESO A LA PLATAFORMA (PATD RESPONSABLE) | F12: PROYECTO SG-PDP INSIPIENTE. HAY DPO, ALGUNOS DOCUMENTOS, HAY EQUIPO INTERNO. NO HAY GRC. NO HAY PANSI | H12: Si bien son datos de categoría especial una posible brecha no pone en riesgo la vida de ningún Titular ni las condiciones para el desarrollo humano como la salud, alimentación o entorno seguro. Se está trabajando para iniciar el proyecto de adecuación del nivel de seguridad inicial y por ello se califica el nivel de impacto o posible daño como alto por tratarse de datos de categoría especial pero con impacto menor sobre el derecho a la vida digna, pero una brecha de datos de categoría especial puede comprometer otros derechos y libertades causando un daño a los titulares de los datos. | I12: =IFERROR(_xlfn.IFS(D12="EXISTE UN SG-PDP VALIDADO Y MANTENIDO. LAS RUTINAS PDP SE PRACTICAN. PLAN DE SIMULACROS ACTIVO. GRC ARTICULADO Y REFERESCADO",1,E12="EXISTE PROYECTO SG-PDP. NO ESTÁ VALIDADO. LAS RUTINAS PDP SE PRACTICAN. PLAN DE SIMULACROS FASE INICIAL. PANSI EN FASE INICIAL.",2,F12="PROYECTO SG-PDP INSIPIENTE. HAY DPO, ALGUNOS DOCUMENTOS, HAY EQUIPO INTERNO. NO HAY GRC. NO HAY PANSI",3,G12="NO HAY PROYECTO SG-PDP. HAY DPO, ALGUNOS DOCUMENTOS, NO HAY EQUIPO INTERNO. NO HAY APOYO DE LA GERENCIA. EL DPD TIENE TODA LA CARGA",4),0) -> 3
C13: DESCARGA DE RESULTADOS EN DISCO DURO (PATD RESPONSABLE) | F13: PROYECTO SG-PDP INSIPIENTE. HAY DPO, ALGUNOS DOCUMENTOS, HAY EQUIPO INTERNO. NO HAY GRC. NO HAY PANSI | H13: La calificación se corresponde a que aún no existe un esquema de protección de datos extendido a los proveedores del servicio (Encargados de tratamiento) ni están especificados en el contrato las condiciones que impone la triada PDP ecuatoriana. El riesgo sobre el derecho a la Salud NO se ve cmprometido, pero una brecha de datos de categoría especial puede comprometer otros derechos y libertades causando un daño a los titulares de los datos. | I13: =IFERROR(_xlfn.IFS(D13="EXISTE UN SG-PDP VALIDADO Y MANTENIDO. LAS RUTINAS PDP SE PRACTICAN. PLAN DE SIMULACROS ACTIVO. GRC ARTICULADO Y REFERESCADO",1,E13="EXISTE PROYECTO SG-PDP. NO ESTÁ VALIDADO. LAS RUTINAS PDP SE PRACTICAN. PLAN DE SIMULACROS FASE INICIAL. PANSI EN FASE INICIAL.",2,F13="PROYECTO SG-PDP INSIPIENTE. HAY DPO, ALGUNOS DOCUMENTOS, HAY EQUIPO INTERNO. NO HAY GRC. NO HAY PANSI",3,G13="NO HAY PROYECTO SG-PDP. HAY DPO, ALGUNOS DOCUMENTOS, NO HAY EQUIPO INTERNO. NO HAY APOYO DE LA GERENCIA. EL DPD TIENE TODA LA CARGA",4),0) -> 3
C14: TRANSFERENCIA DE DATOS A MÉDICO OCUPACIONAL (PATD RESPONSABLE) | I14: =IFERROR(_xlfn.IFS(D14="EXISTE UN SG-PDP VALIDADO Y MANTENIDO. LAS RUTINAS PDP SE PRACTICAN. PLAN DE SIMULACROS ACTIVO. GRC ARTICULADO Y REFERESCADO",1,E14="EXISTE PROYECTO SG-PDP. NO ESTÁ VALIDADO. LAS RUTINAS PDP SE PRACTICAN. PLAN DE SIMULACROS FASE INICIAL. PANSI EN FASE INICIAL.",2,F14="PROYECTO SG-PDP INSIPIENTE. HAY DPO, ALGUNOS DOCUMENTOS, HAY EQUIPO INTERNO. NO HAY GRC. NO HAY PANSI",3,G14="NO HAY PROYECTO SG-PDP. HAY DPO, ALGUNOS DOCUMENTOS, NO HAY EQUIPO INTERNO. NO HAY APOYO DE LA GERENCIA. EL DPD TIENE TODA LA CARGA",4),0) -> 0
C15: TRANSFERENCIA DE DATOS A TITULAR DE LOS DATOS (PATD RESPONSABLE) | I15: =IFERROR(_xlfn.IFS(D15="EXISTE UN SG-PDP VALIDADO Y MANTENIDO. LAS RUTINAS PDP SE PRACTICAN. PLAN DE SIMULACROS ACTIVO. GRC ARTICULADO Y REFERESCADO",1,E15="EXISTE PROYECTO SG-PDP. NO ESTÁ VALIDADO. LAS RUTINAS PDP SE PRACTICAN. PLAN DE SIMULACROS FASE INICIAL. PANSI EN FASE INICIAL.",2,F15="PROYECTO SG-PDP INSIPIENTE. HAY DPO, ALGUNOS DOCUMENTOS, HAY EQUIPO INTERNO. NO HAY GRC. NO HAY PANSI",3,G15="NO HAY PROYECTO SG-PDP. HAY DPO, ALGUNOS DOCUMENTOS, NO HAY EQUIPO INTERNO. NO HAY APOYO DE LA GERENCIA. EL DPD TIENE TODA LA CARGA",4),0) -> 0
C16: RECEPCIÓN DE TRANSFERENCIA DE RESULTADOS (PATD ENCARGADO) | I16: =IFERROR(_xlfn.IFS(D16="EXISTE UN SG-PDP VALIDADO Y MANTENIDO. LAS RUTINAS PDP SE PRACTICAN. PLAN DE SIMULACROS ACTIVO. GRC ARTICULADO Y REFERESCADO",1,E16="EXISTE PROYECTO SG-PDP. NO ESTÁ VALIDADO. LAS RUTINAS PDP SE PRACTICAN. PLAN DE SIMULACROS FASE INICIAL. PANSI EN FASE INICIAL.",2,F16="PROYECTO SG-PDP INSIPIENTE. HAY DPO, ALGUNOS DOCUMENTOS, HAY EQUIPO INTERNO. NO HAY GRC. NO HAY PANSI",3,G16="NO HAY PROYECTO SG-PDP. HAY DPO, ALGUNOS DOCUMENTOS, NO HAY EQUIPO INTERNO. NO HAY APOYO DE LA GERENCIA. EL DPD TIENE TODA LA CARGA",4),0) -> 0
C17: CONSERVACIÓN DE RESULTADOS (PATD ENCARGADO) | I17: =IFERROR(_xlfn.IFS(D17="EXISTE UN SG-PDP VALIDADO Y MANTENIDO. LAS RUTINAS PDP SE PRACTICAN. PLAN DE SIMULACROS ACTIVO. GRC ARTICULADO Y REFERESCADO",1,E17="EXISTE PROYECTO SG-PDP. NO ESTÁ VALIDADO. LAS RUTINAS PDP SE PRACTICAN. PLAN DE SIMULACROS FASE INICIAL. PANSI EN FASE INICIAL.",2,F17="PROYECTO SG-PDP INSIPIENTE. HAY DPO, ALGUNOS DOCUMENTOS, HAY EQUIPO INTERNO. NO HAY GRC. NO HAY PANSI",3,G17="NO HAY PROYECTO SG-PDP. HAY DPO, ALGUNOS DOCUMENTOS, NO HAY EQUIPO INTERNO. NO HAY APOYO DE LA GERENCIA. EL DPD TIENE TODA LA CARGA",4),0) -> 0
I18: =IFERROR(_xlfn.IFS(D18="EXISTE UN SG-PDP VALIDADO Y MANTENIDO. LAS RUTINAS PDP SE PRACTICAN. PLAN DE SIMULACROS ACTIVO. GRC ARTICULADO Y REFERESCADO",1,E18="EXISTE PROYECTO SG-PDP. NO ESTÁ VALIDADO. LAS RUTINAS PDP SE PRACTICAN. PLAN DE SIMULACROS FASE INICIAL. PANSI EN FASE INICIAL.",2,F18="PROYECTO SG-PDP INSIPIENTE. HAY DPO, ALGUNOS DOCUMENTOS, HAY EQUIPO INTERNO. NO HAY GRC. NO HAY PANSI",3,G18="NO HAY PROYECTO SG-PDP. HAY DPO, ALGUNOS DOCUMENTOS, NO HAY EQUIPO INTERNO. NO HAY APOYO DE LA GERENCIA. EL DPD TIENE TODA LA CARGA",4),0) -> 0
D20: ESTADO DE LA TÉCNICA
C21: MEDIOS DONDE SE REALIZA EL TRATAMIENTO MEDIOS Y DISPOSITIVOS REQUERIDAS Y UTILIZADOS PARA RECOGER, CONSERVAR, TRANSFERIR, BLOQUEAR, ENCRIPTAR, PSEUDONIMIZAR O DAR TRATAMIENTO A DATOS PERSONALES | D21: SG-PDP VALIDADO Y EN PRIMER TRIMESTRE OPERATIVO | E21: GRC DOCUMENTADO CON PDP INCLUIDO. PANSI FASE 1 | F21: DOCUMENTACIÓN SIN PDP INCLUIDO | G21: DOCUMENTACIÓN INEXISTENTE | H21: COMENTARIOS SOBRE AMENAZAS
D22: 1 IMPROBABLE | E22: 2 MEDIA - BAJA | F22: 3 MEDIA - ALTA | G22: 4 MUY PROBABLE
C23: CORREO ELECTRÓNICO | G23: NO HAY PROYECTO SG-PDP. HAY DPO, ALGUNOS DOCUMENTOS, NO HAY EQUIPO INTERNO. NO HAY APOYO DE LA GERENCIA. EL DPD TIENE TODA LA CARGA | I23: =IFERROR(_xlfn.IFS(D23="EXISTE UN SG-PDP VALIDADO Y MANTENIDO. LAS RUTINAS PDP SE PRACTICAN. PLAN DE SIMULACROS ACTIVO. GRC ARTICULADO Y REFERESCADO",1,E23="EXISTE PROYECTO SG-PDP. NO ESTÁ VALIDADO. LAS RUTINAS PDP SE PRACTICAN. PLAN DE SIMULACROS FASE INICIAL. PANSI EN FASE INICIAL.",2,F23="PROYECTO SG-PDP INSIPIENTE. HAY DPO, ALGUNOS DOCUMENTOS, HAY EQUIPO INTERNO. NO HAY GRC. NO HAY PANSI",3,G23="NO HAY PROYECTO SG-PDP. HAY DPO, ALGUNOS DOCUMENTOS, NO HAY EQUIPO INTERNO. NO HAY APOYO DE LA GERENCIA. EL DPD TIENE TODA LA CARGA",4),0) -> 4
C24: PLATAFORMA LABORATORIO | F24: PROYECTO SG-PDP INSIPIENTE. HAY DPO, ALGUNOS DOCUMENTOS, HAY EQUIPO INTERNO. NO HAY GRC. NO HAY PANSI | I24: =IFERROR(_xlfn.IFS(D24="EXISTE UN SG-PDP VALIDADO Y MANTENIDO. LAS RUTINAS PDP SE PRACTICAN. PLAN DE SIMULACROS ACTIVO. GRC ARTICULADO Y REFERESCADO",1,E24="EXISTE PROYECTO SG-PDP. NO ESTÁ VALIDADO. LAS RUTINAS PDP SE PRACTICAN. PLAN DE SIMULACROS FASE INICIAL. PANSI EN FASE INICIAL.",2,F24="PROYECTO SG-PDP INSIPIENTE. HAY DPO, ALGUNOS DOCUMENTOS, HAY EQUIPO INTERNO. NO HAY GRC. NO HAY PANSI",3,G24="NO HAY PROYECTO SG-PDP. HAY DPO, ALGUNOS DOCUMENTOS, NO HAY EQUIPO INTERNO. NO HAY APOYO DE LA GERENCIA. EL DPD TIENE TODA LA CARGA",4),0) -> 3
C25: REPOSITORIO FÍSICO | F25: PROYECTO SG-PDP INSIPIENTE. HAY DPO, ALGUNOS DOCUMENTOS, HAY EQUIPO INTERNO. NO HAY GRC. NO HAY PANSI | I25: =IFERROR(_xlfn.IFS(D25="EXISTE UN SG-PDP VALIDADO Y MANTENIDO. LAS RUTINAS PDP SE PRACTICAN. PLAN DE SIMULACROS ACTIVO. GRC ARTICULADO Y REFERESCADO",1,E25="EXISTE PROYECTO SG-PDP. NO ESTÁ VALIDADO. LAS RUTINAS PDP SE PRACTICAN. PLAN DE SIMULACROS FASE INICIAL. PANSI EN FASE INICIAL.",2,F25="PROYECTO SG-PDP INSIPIENTE. HAY DPO, ALGUNOS DOCUMENTOS, HAY EQUIPO INTERNO. NO HAY GRC. NO HAY PANSI",3,G25="NO HAY PROYECTO SG-PDP. HAY DPO, ALGUNOS DOCUMENTOS, NO HAY EQUIPO INTERNO. NO HAY APOYO DE LA GERENCIA. EL DPD TIENE TODA LA CARGA",4),0) -> 3
C26: LAPTOP DEL MÉDICO OCUPACIONAL | F26: PROYECTO SG-PDP INSIPIENTE. HAY DPO, ALGUNOS DOCUMENTOS, HAY EQUIPO INTERNO. NO HAY GRC. NO HAY PANSI | I26: =IFERROR(_xlfn.IFS(D26="EXISTE UN SG-PDP VALIDADO Y MANTENIDO. LAS RUTINAS PDP SE PRACTICAN. PLAN DE SIMULACROS ACTIVO. GRC ARTICULADO Y REFERESCADO",1,E26="EXISTE PROYECTO SG-PDP. NO ESTÁ VALIDADO. LAS RUTINAS PDP SE PRACTICAN. PLAN DE SIMULACROS FASE INICIAL. PANSI EN FASE INICIAL.",2,F26="PROYECTO SG-PDP INSIPIENTE. HAY DPO, ALGUNOS DOCUMENTOS, HAY EQUIPO INTERNO. NO HAY GRC. NO HAY PANSI",3,G26="NO HAY PROYECTO SG-PDP. HAY DPO, ALGUNOS DOCUMENTOS, NO HAY EQUIPO INTERNO. NO HAY APOYO DE LA GERENCIA. EL DPD TIENE TODA LA CARGA",4),0) -> 3
C27: FIREWALL | F27: PROYECTO SG-PDP INSIPIENTE. HAY DPO, ALGUNOS DOCUMENTOS, HAY EQUIPO INTERNO. NO HAY GRC. NO HAY PANSI | I27: =IFERROR(_xlfn.IFS(D27="EXISTE UN SG-PDP VALIDADO Y MANTENIDO. LAS RUTINAS PDP SE PRACTICAN. PLAN DE SIMULACROS ACTIVO. GRC ARTICULADO Y REFERESCADO",1,E27="EXISTE PROYECTO SG-PDP. NO ESTÁ VALIDADO. LAS RUTINAS PDP SE PRACTICAN. PLAN DE SIMULACROS FASE INICIAL. PANSI EN FASE INICIAL.",2,F27="PROYECTO SG-PDP INSIPIENTE. HAY DPO, ALGUNOS DOCUMENTOS, HAY EQUIPO INTERNO. NO HAY GRC. NO HAY PANSI",3,G27="NO HAY PROYECTO SG-PDP. HAY DPO, ALGUNOS DOCUMENTOS, NO HAY EQUIPO INTERNO. NO HAY APOYO DE LA GERENCIA. EL DPD TIENE TODA LA CARGA",4),0) -> 3
C28: ANTIVIRUS | F28: PROYECTO SG-PDP INSIPIENTE. HAY DPO, ALGUNOS DOCUMENTOS, HAY EQUIPO INTERNO. NO HAY GRC. NO HAY PANSI | I28: =IFERROR(_xlfn.IFS(D28="EXISTE UN SG-PDP VALIDADO Y MANTENIDO. LAS RUTINAS PDP SE PRACTICAN. PLAN DE SIMULACROS ACTIVO. GRC ARTICULADO Y REFERESCADO",1,E28="EXISTE PROYECTO SG-PDP. NO ESTÁ VALIDADO. LAS RUTINAS PDP SE PRACTICAN. PLAN DE SIMULACROS FASE INICIAL. PANSI EN FASE INICIAL.",2,F28="PROYECTO SG-PDP INSIPIENTE. HAY DPO, ALGUNOS DOCUMENTOS, HAY EQUIPO INTERNO. NO HAY GRC. NO HAY PANSI",3,G28="NO HAY PROYECTO SG-PDP. HAY DPO, ALGUNOS DOCUMENTOS, NO HAY EQUIPO INTERNO. NO HAY APOYO DE LA GERENCIA. EL DPD TIENE TODA LA CARGA",4),0) -> 3
I29: =IFERROR(_xlfn.IFS(D29="EXISTE UN SG-PDP VALIDADO Y MANTENIDO. LAS RUTINAS PDP SE PRACTICAN. PLAN DE SIMULACROS ACTIVO. GRC ARTICULADO Y REFERESCADO",1,E29="EXISTE PROYECTO SG-PDP. NO ESTÁ VALIDADO. LAS RUTINAS PDP SE PRACTICAN. PLAN DE SIMULACROS FASE INICIAL. PANSI EN FASE INICIAL.",2,F29="PROYECTO SG-PDP INSIPIENTE. HAY DPO, ALGUNOS DOCUMENTOS, HAY EQUIPO INTERNO. NO HAY GRC. NO HAY PANSI",3,G29="NO HAY PROYECTO SG-PDP. HAY DPO, ALGUNOS DOCUMENTOS, NO HAY EQUIPO INTERNO. NO HAY APOYO DE LA GERENCIA. EL DPD TIENE TODA LA CARGA",4),0) -> 0

Sheet RIESGO Y MITIGADORES
N3: CONCLUSIÓN: LAS CONDICIONES DE SEGURIDAD QUE OFRECE LAS OFICINAS REDUCEN LA POSIBILIDAD DE INTRUSIÓN AL ÁREA DONDE ESTA EL DISPOSITIVO QUE CONSERVA LAS IMÁGENES. LAS MEDIDAS DE SEGURIDAD QUE SE LISTAN EN EL PANSI SON SUFICIENTES PARA GARANTIZAR EL NIVEL DE SEGURIDAD ÓPTIMO PARA EVITAR QUE ESTE TRATAMIENTO SEA DE ALTO RIESGO
N7: MEDIDAS, CONTROLES y HERRAMIENTAS PARA REFORZAR MITIGADORES PANSI
Q9: FÍSICAS | S9: TÉCNICAS
B10: RIESGO INHERENTE A LAS OPERACIONES | C10: ACTIVIDAD DE TRATAMIENTO | D10: VULNERABILIDAD | E10: AMENAZA | F10: IMPACTO | G10: PONDERACIÓN (A) | H10: PROBABILIDAD | I10: PONDERACIÓN (B) | K10: RIESGO INHERENTE DERECHOS y LIBERTADES | L10: RIESGO INHERENTE (AxB) | N10: ORGANIZATIVAS | O10: ADMINISTRATIVAS | P10: JURÍDICAS | Q10: OPERATIVAS | R10: INFRAESTRUCTURA | S10: COMPETENCIAS | T10: TECNOLOGÍA | V10: RIESGO RESIDUAL
C11: ='RAT-MTGE MEDICINA OCUPACIONAL'!D3 -> EXÁMENES MÉDICOS OBLIGATORIOS (Pre ocupacional, Periódica y Retiro) | D11: =+'OPERACIONES-MEDIOS-PROBABILIDAD'!C10 -> ENVIO DE LISTADO AL LABORATORIO (PATD RESPONSABLE) | E11: ='OPERACIONES-MEDIOS-PROBABILIDAD'!H10 -> Los datos están en distintos repositorios (Laboratorio, Correo electronico, Médico ocupacional, Área de recursos humanos, archivo impreso, otros), sin esquema PDP y con bajo nivel de seguridad en PDP (PANSI EN FASE INICIAL). No hay contratos con cláusulas PDP con encargados de tratamiento (Laboratoio y Médico Ocupacional), ni con PATD de TRAUMA ORTOPEDICS). | F11: =IF(G11<=2,"MÍNIMO",IF(G11>=12,"MUY GRAVE",IF(AND(G11>=2.01,G11<=6),"GRAVE","ALTO"))) -> GRAVE | G11: ='DERECHOS Y LIBERTADES AFECTADOS'!$I$22 -> 3 | H11: =IF(I11<=2,"IMPROBABLE",IF(I11>=12,"MUY PROBABLE",IF(AND(I11>=2.01,I11<=6),"MEDIA BAJA","MEDIA ALTA"))) -> MEDIA BAJA | I11: ='OPERACIONES-MEDIOS-PROBABILIDAD'!I10 -> 3 | K11: =IF(L11<=2,"MÍNIMO-ESTIMADO",IF(L11>=12,"MUY ALTO",IF(AND(L11>=6.01,L11<=11.99),"ALTO","MEDIO"))) -> ALTO | L11: =G11*I11 -> 9 | V11: 1. Se debe completar y respetar los compromisos de aplicabilidad del PANSI 2. Se debe redactar un procedimiento que garantice que de producirse cambios en la operación o en los medios necesarios para el tratamiento se deben respetar las especificaciones actuales de los dispositivos. 3. Cambios en el entorno seguro que ofrece la ubicación de las oficinas de Trauma Ortopedics deben activar una nueva EIPD 4. Evitar que por decisiones no informadas se detenga el PANSI
D12: =+'OPERACIONES-MEDIOS-PROBABILIDAD'!C11 -> CARGA DE DATOS EN PLATAFORMA (PATD ENCARGADO) | E12: ='OPERACIONES-MEDIOS-PROBABILIDAD'!H11 -> Los datos están en distintos repositorios (Laboratorio, Correo electronico, Médico ocupacional, Área de recursos humanos, archivo impreso, otros), sin esquema PDP y con bajo nivel de seguridad en PDP (PANSI EN FASE INICIAL). No hay contratos con cláusulas PDP con encargados de tratamiento (Laboratoio y Médico Ocupacional) | F12: =IF(G12<=2,"MÍNIMO",IF(G12>=12,"MUY GRAVE",IF(AND(G12>=2.01,G12<=6),"GRAVE","ALTO"))) -> GRAVE | G12: ='DERECHOS Y LIBERTADES AFECTADOS'!$I$22 -> 3 | H12: =IF(I12<=2,"IMPROBABLE",IF(I12>=12,"ALTA",IF(AND(I12>=2.01,I12<=6),"MEDIA BAJA","MEDIA ALTA"))) -> MEDIA BAJA | I12: ='OPERACIONES-MEDIOS-PROBABILIDAD'!I11 -> 3 | K12: =IF(L12<=2,"MÍNIMO-ESTIMADO",IF(L12>=12,"MUY ALTO",IF(AND(L12>=6.01,L12<=11.99),"ALTO","MEDIO"))) -> ALTO | L12: =G12*I12 -> 9
D13: =+'OPERACIONES-MEDIOS-PROBABILIDAD'!C12 -> ACCESO A LA PLATAFORMA (PATD RESPONSABLE) | E13: ='OPERACIONES-MEDIOS-PROBABILIDAD'!H12 -> Si bien son datos de categoría especial una posible brecha no pone en riesgo la vida de ningún Titular ni las condiciones para el desarrollo humano como la salud, alimentación o entorno seguro. Se está trabajando para iniciar el proyecto de adecuación del nivel de seguridad inicial y por ello se califica el nivel de impacto o posible daño como alto por tratarse de datos de categoría especial pero con impacto menor sobre el derecho a la vida digna, pero una brecha de datos de categoría especial puede comprometer otros derechos y libertades causando un daño a los titulares de los datos. | F13: =IF(G13<=2,"MÍNIMO",IF(G13>=12,"MUY GRAVE",IF(AND(G13>=2.01,G13<=6),"GRAVE","ALTO"))) -> GRAVE | G13: ='DERECHOS Y LIBERTADES AFECTADOS'!$I$22 -> 3 | H13: =IF(I13<=2,"IMPROBABLE",IF(I13>=12,"ALTA",IF(AND(I13>=2.01,I13<=6),"MEDIA BAJA","MEDIA ALTA"))) -> MEDIA BAJA | I13: ='OPERACIONES-MEDIOS-PROBABILIDAD'!I12 -> 3 | K13: =IF(L13<=2,"MÍNIMO-ESTIMADO",IF(L13>=12,"MUY ALTO",IF(AND(L13>=6.01,L13<=11.99),"ALTO","MEDIO"))) -> ALTO | L13: =G13*I13 -> 9
D14: =+'OPERACIONES-MEDIOS-PROBABILIDAD'!C13 -> DESCARGA DE RESULTADOS EN DISCO DURO (PATD RESPONSABLE) | E14: ='OPERACIONES-MEDIOS-PROBABILIDAD'!H13 -> La calificación se corresponde a que aún no existe un esquema de protección de datos extendido a los proveedores del servicio (Encargados de tratamiento) ni están especificados en el contrato las condiciones que impone la triada PDP ecuatoriana. El riesgo sobre el derecho a la Salud NO se ve cmprometido, pero una brecha de datos de categoría especial puede comprometer otros derechos y libertades causando un daño a los titulares de los datos. | F14: =IF(G14<=2,"MÍNIMO",IF(G14>=12,"MUY GRAVE",IF(AND(G14>=2.01,G14<=6),"GRAVE","ALTO"))) -> GRAVE | G14: ='DERECHOS Y LIBERTADES AFECTADOS'!$I$22 -> 3 | H14: =IF(I14<=2,"IMPROBABLE",IF(I14>=12,"ALTA",IF(AND(I14>=2.01,I14<=6),"MEDIA BAJA","MEDIA ALTA"))) -> MEDIA BAJA | I14: ='OPERACIONES-MEDIOS-PROBABILIDAD'!I13 -> 3 | K14: =IF(L14<=2,"MÍNIMO-ESTIMADO",IF(L14>=12,"MUY ALTO",IF(AND(L14>=6.01,L14<=11.99),"ALTO","MEDIO"))) -> ALTO | L14: =G14*I14 -> 9
D15: =+'OPERACIONES-MEDIOS-PROBABILIDAD'!C14 -> TRANSFERENCIA DE DATOS A MÉDICO OCUPACIONAL (PATD RESPONSABLE) | E15: ='OPERACIONES-MEDIOS-PROBABILIDAD'!H14 -> 0 | F15: =IF(G15<=2,"MÍNIMO",IF(G15>=12,"MUY GRAVE",IF(AND(G15>=2.01,G15<=6),"GRAVE","ALTO"))) -> GRAVE | G15: ='DERECHOS Y LIBERTADES AFECTADOS'!$I$22 -> 3 | H15: =IF(I15<=2,"IMPROBABLE",IF(I15>=12,"ALTA",IF(AND(I15>=2.01,I15<=6),"MEDIA BAJA","MEDIA ALTA"))) -> IMPROBABLE | I15: ='OPERACIONES-MEDIOS-PROBABILIDAD'!I14 -> 0 | K15: =IF(L15<=2,"MÍNIMO-ESTIMADO",IF(L15>=12,"MUY ALTO",IF(AND(L15>=6.01,L15<=11.99),"ALTO","MEDIO"))) -> MÍNIMO-ESTIMADO | L15: =G15*I15 -> 0
D16: =+'OPERACIONES-MEDIOS-PROBABILIDAD'!C15 -> TRANSFERENCIA DE DATOS A TITULAR DE LOS DATOS (PATD RESPONSABLE) | E16: ='OPERACIONES-MEDIOS-PROBABILIDAD'!H15 -> 0 | F16: =IF(G16<=2,"MÍNIMO",IF(G16>=12,"MUY GRAVE",IF(AND(G16>=2.01,G16<=6),"GRAVE","ALTO"))) -> GRAVE | G16: ='DERECHOS Y LIBERTADES AFECTADOS'!$I$22 -> 3 | H16: =IF(I16<=2,"IMPROBABLE",IF(I16>=12,"ALTA",IF(AND(I16>=2.01,I16<=6),"MEDIA BAJA","MEDIA ALTA"))) -> IMPROBABLE | I16: ='OPERACIONES-MEDIOS-PROBABILIDAD'!I15 -> 0 | K16: =IF(L16<=2,"MÍNIMO-ESTIMADO",IF(L16>=12,"MUY ALTO",IF(AND(L16>=6.01,L16<=11.99),"ALTO","MEDIO"))) -> MÍNIMO-ESTIMADO | L16: =G16*I16 -> 0
D17: =+'OPERACIONES-MEDIOS-PROBABILIDAD'!C16 -> RECEPCIÓN DE TRANSFERENCIA DE RESULTADOS (PATD ENCARGADO) | E17: ='OPERACIONES-MEDIOS-PROBABILIDAD'!H16 -> 0 | F17: =IF(G17<=2,"MÍNIMO",IF(G17>=12,"MUY GRAVE",IF(AND(G17>=2.01,G17<=6),"GRAVE","ALTO"))) -> GRAVE | G17: ='DERECHOS Y LIBERTADES AFECTADOS'!$I$22 -> 3 | H17: =IF(I17<=2,"IMPROBABLE",IF(I17>=12,"ALTA",IF(AND(I17>=2.01,I17<=6),"MEDIA BAJA","MEDIA ALTA"))) -> IMPROBABLE | I17: ='OPERACIONES-MEDIOS-PROBABILIDAD'!I16 -> 0 | K17: =IF(L17<=2,"MÍNIMO-ESTIMADO",IF(L17>=12,"MUY ALTO",IF(AND(L17>=6.01,L17<=11.99),"ALTO","MEDIO"))) -> MÍNIMO-ESTIMADO | L17: =G17*I17 -> 0
D18: =+'OPERACIONES-MEDIOS-PROBABILIDAD'!C17 -> CONSERVACIÓN DE RESULTADOS (PATD ENCARGADO) | E18: ='OPERACIONES-MEDIOS-PROBABILIDAD'!H17 -> 0 | F18: =IF(G18<=2,"MÍNIMO",IF(G18>=12,"MUY GRAVE",IF(AND(G18>=2.01,G18<=6),"GRAVE","ALTO"))) -> GRAVE | G18: ='DERECHOS Y LIBERTADES AFECTADOS'!I$22 -> 3 | H18: =IF(I18<=2,"IMPROBABLE",IF(I18>=12,"ALTA",IF(AND(I18>=2.01,I18<=6),"MEDIA BAJA","MEDIA ALTA"))) -> IMPROBABLE | I18: ='OPERACIONES-MEDIOS-PROBABILIDAD'!I17 -> 0 | K18: =IF(L18<=2,"MÍNIMO-ESTIMADO",IF(L18>=12,"MUY ALTO",IF(AND(L18>=6.01,L18<=11.99),"ALTO","MEDIO"))) -> MÍNIMO-ESTIMADO | L18: =G18*I18 -> 0
B20: RIESGO INHERENTE A LOS MEDIOS REQUERIDOS Y UTILIZADOS | C20: ACTIVIDAD DE TRATAMIENTO | D20: VULNERABILIDAD | E20: AMENAZA | F20: IMPACTO | G20: PONDERACIÓN (A) | H20: PROBABILIDAD | I20: PONDERACIÓN (B) | K20: RIESGO INHERENTE DERECHOS y LIBERTADES | L20: RIESGO INHERENTE (AxB) | N20: ORGANIZATIVAS | O20: ADMINISTRATIVAS | P20: JURÍDICAS | Q20: OPERATIVAS | R20: INFRAESTRUCTURA | S20: COMPETENCIAS | T20: TECNOLOGÍA | V20: RIESGO RESIDUAL
D21: =+'OPERACIONES-MEDIOS-PROBABILIDAD'!C23 -> CORREO ELECTRÓNICO | E21: ='OPERACIONES-MEDIOS-PROBABILIDAD'!H23 -> 0 | F21: =IF(G21<=2,"MÍNIMO",IF(G21>=12,"MUY GRAVE",IF(AND(G21>=2.01,G21<=6),"GRAVE","ALTO"))) -> GRAVE | G21: ='DERECHOS Y LIBERTADES AFECTADOS'!I10 -> 3 | H21: =IF(I21<=2,"IMPROBABLE",IF(I21>=12,"ALTA",IF(AND(I21>=2.01,I21<=6),"MEDIA BAJA","MEDIA ALTA"))) -> MEDIA BAJA | I21: ='OPERACIONES-MEDIOS-PROBABILIDAD'!I23 -> 4 | K21: =IF(L21<=2,"MÍNIMO-ESTIMADO",IF(L21>=12,"MUY ALTO",IF(AND(L21>=6.01,L21<=11.99),"ALTO","MEDIO"))) -> MUY ALTO | L21: =G21*I21 -> 12 | V21: 1. Se debe completar y respetar los compromisos de aplicabilidad del PANSI 2. Se debe redactar un procedimiento que garantice que de producirse cambios en la operación o en los medios necesarios para el tratamiento se deben respetar las especificaciones actuales de los dispositivos. 3. Cambios en el entorno seguro que ofrece la ubicación de las oficinas de Trauma Ortopedics deben activar una nueva EIPD 4. Evitar que por decisiones no informadas se detenga el PANSI
D22: =+'OPERACIONES-MEDIOS-PROBABILIDAD'!C24 -> PLATAFORMA LABORATORIO | E22: ='OPERACIONES-MEDIOS-PROBABILIDAD'!H24 -> 0 | F22: =IF(G22<=2,"MÍNIMO",IF(G22>=12,"MUY GRAVE",IF(AND(G22>=2.01,G22<=6),"GRAVE","ALTO"))) -> GRAVE | G22: ='DERECHOS Y LIBERTADES AFECTADOS'!I11 -> 3 | H22: =IF(I22<=2,"IMPROBABLE",IF(I22>=12,"ALTA",IF(AND(I22>=2.01,I22<=6),"MEDIA BAJA","MEDIA ALTA"))) -> MEDIA BAJA | I22: ='OPERACIONES-MEDIOS-PROBABILIDAD'!I24 -> 3 | K22: =IF(L22<=2,"MÍNIMO-ESTIMADO",IF(L22>=12,"MUY ALTO",IF(AND(L22>=6.01,L22<=11.99),"ALTO","MEDIO"))) -> ALTO | L22: =G22*I22 -> 9
D23: =+'OPERACIONES-MEDIOS-PROBABILIDAD'!C25 -> REPOSITORIO FÍSICO | E23: ='OPERACIONES-MEDIOS-PROBABILIDAD'!H25 -> 0 | F23: =IF(G23<=2,"MÍNIMO",IF(G23>=12,"MUY GRAVE",IF(AND(G23>=2.01,G23<=6),"GRAVE","ALTO"))) -> MÍNIMO | G23: ='DERECHOS Y LIBERTADES AFECTADOS'!I12 -> 0 | H23: =IF(I23<=2,"IMPROBABLE",IF(I23>=12,"ALTA",IF(AND(I23>=2.01,I23<=6),"MEDIA BAJA","MEDIA ALTA"))) -> MEDIA BAJA | I23: ='OPERACIONES-MEDIOS-PROBABILIDAD'!I25 -> 3 | K23: =IF(L23<=2,"MÍNIMO-ESTIMADO",IF(L23>=12,"MUY ALTO",IF(AND(L23>=6.01,L23<=11.99),"ALTO","MEDIO"))) -> MÍNIMO-ESTIMADO | L23: =G23*I23 -> 0
D24: =+'OPERACIONES-MEDIOS-PROBABILIDAD'!C26 -> LAPTOP DEL MÉDICO OCUPACIONAL | E24: ='OPERACIONES-MEDIOS-PROBABILIDAD'!H26 -> 0 | F24: =IF(G24<=2,"MÍNIMO",IF(G24>=12,"MUY GRAVE",IF(AND(G24>=2.01,G24<=6),"GRAVE","ALTO"))) -> MÍNIMO | G24: ='DERECHOS Y LIBERTADES AFECTADOS'!I13 -> 0 | H24: =IF(I24<=2,"IMPROBABLE",IF(I24>=12,"ALTA",IF(AND(I24>=2.01,I24<=6),"MEDIA BAJA","MEDIA ALTA"))) -> MEDIA BAJA | I24: ='OPERACIONES-MEDIOS-PROBABILIDAD'!I26 -> 3 | K24: =IF(L24<=2,"MÍNIMO-ESTIMADO",IF(L24>=12,"MUY ALTO",IF(AND(L24>=6.01,L24<=11.99),"ALTO","MEDIO"))) -> MÍNIMO-ESTIMADO | L24: =G24*I24 -> 0
D25: =+'OPERACIONES-MEDIOS-PROBABILIDAD'!C27 -> FIREWALL | E25: ='OPERACIONES-MEDIOS-PROBABILIDAD'!H27 -> 0 | F25: =IF(G25<=2,"MÍNIMO",IF(G25>=12,"MUY GRAVE",IF(AND(G25>=2.01,G25<=6),"GRAVE","ALTO"))) -> MÍNIMO | G25: ='DERECHOS Y LIBERTADES AFECTADOS'!I14 -> 0 | H25: =IF(I25<=2,"IMPROBABLE",IF(I25>=12,"ALTA",IF(AND(I25>=2.01,I25<=6),"MEDIA BAJA","MEDIA ALTA"))) -> MEDIA BAJA | I25: ='OPERACIONES-MEDIOS-PROBABILIDAD'!I27 -> 3 | K25: =IF(L25<=2,"MÍNIMO-ESTIMADO",IF(L25>=12,"MUY ALTO",IF(AND(L25>=6.01,L25<=11.99),"ALTO","MEDIO"))) -> MÍNIMO-ESTIMADO | L25: =G25*I25 -> 0
D26: =+'OPERACIONES-MEDIOS-PROBABILIDAD'!C28 -> ANTIVIRUS | E26: ='OPERACIONES-MEDIOS-PROBABILIDAD'!H28 -> 0 | F26: =IF(G26<=2,"MÍNIMO",IF(G26>=12,"MUY GRAVE",IF(AND(G26>=2.01,G26<=6),"GRAVE","ALTO"))) -> MÍNIMO | G26: ='DERECHOS Y LIBERTADES AFECTADOS'!I15 -> 0 | H26: =IF(I26<=2,"IMPROBABLE",IF(I26>=12,"ALTA",IF(AND(I26>=2.01,I26<=6),"MEDIA BAJA","MEDIA ALTA"))) -> MEDIA BAJA | I26: ='OPERACIONES-MEDIOS-PROBABILIDAD'!I28 -> 3 | K26: =IF(L26<=2,"MÍNIMO-ESTIMADO",IF(L26>=12,"MUY ALTO",IF(AND(L26>=6.01,L26<=11.99),"ALTO","MEDIO"))) -> MÍNIMO-ESTIMADO | L26: =G26*I26 -> 0
