Workbook
Name SegmentaciónDeDatos_MEDIDAS: #N/A
Name SegmentaciónDeDatos_SUB_MEDIDAS: #N/A

Sheet LISTAS Y CRITERIOS
C5: ESTADO DE LA TÉCNICA POR ÁREA DEL 47.2 LOPDP | F5: COMENTARIO RESULTADO DEL PROMEDIO DE LAS AREAS DEL 47.2 LOPDP CALIFICACIÓN PANSI PARA EET | J5: INVERSIÓN ESTIMADA HORAS - HOMBRE | L5: FECHAS PROBABLES | N5: INVERSIÓN ESTIMADA DINERO
C6: NO EXISTE DOCUMENTACIÓN, NI MÉTODOS. ORGANIZACIÓN EMPÍRICA. CERO CAPACIDAD DE REACCIÓN | D6: 1 | F6: ESTADO DE LA TÉCNICA MUY BAJO. ELEVAR EL PROMEDIO HASTA EL VALOR DESEADO TOMARÁ 6< MESES<9 | G6: 1 | J6: DESCRITO EN COMENTARIOS | L6: DESCRITO EN COMENTARIOS | N6: DESCRITO EN COMENTARIOS
C7: EXISTEN DOCUMENTOS. HAY MÉTODOS SIN RIGUROSIDAD. NO HAY PROYECTO PDP. HAY UN DPD. NIVEL MÍNIMO DE SEGURIDAD. BAJA CAPACIDAD DE IDENTIFICAR Y RESTAURAR BRECHAS | D7: 2 | F7: ESTADO DE LA TÉCNICA MEDIO Y SIN DOCUMENTACIÓN PDP. ELEVAR EL PROMEDIO HASTA EL VALOR DESEADO TOMARÁ 3< MESES<6 | G7: 2 | J7: 4 HORAS SEMANALES X 12 MESES | L7: JUNIO 2026 | N7: US$100<MONTO<US$500
C8: PROYECTO PDP EN FASE INICIAL PANSI. HAY DPD. HAY APOYO POR EL RTD. NIVEL MÍNIMO DESEADO DE SEGURIDAD. VULNERABILIDADES IDENTIFICADAS Y ATENDIDAS | D8: 3 | F8: ESTADO DE LA TÉCNICA INCLUYE DOCUMENTACIÓN PDP. SE CUMPLE FASE I DEL PANSI. INICIA PROYECTO PDP Y TOMARÁ 6< MESES<9 | G8: 3 | J8: 6 HORAS SEMANALES X 10 MESES | L8: JULIO 2026 | N8: US$500<MONTO<US$1000
C9: SG-PDP VALIDADO Y EN PRIMER TRIMESTE DE OPERACIÓN. NIVEL DE SEGURIDAD ADECUADO | D9: 4 | F9: ESTADO DE LA TÉCNICA ALTO, MANTENIDO, MEJORADO Y RESILIENTE GRACIAS AL SG-PDP VALIDADO. | G9: 4 | J9: 8 HORAS SEMANALES X 9 MESES | L9: AGOSTO 2026 | N9: US$1000<MONTO<US$1500
L10: SEPTIEMBRE 2026 | N10: US$1500<MONTO<US$2000
C11: RIESGO INHERENTE COMO RESULTADO DEL PROMEDIO DE LAS AREAS DEL 47.2 LOPDP CALIFICACIÓN PANSI PARA SG | F11: RIESGO INHERENTE COMO RESULTADO DEL PROMEDIO DE LAS AREAS DEL 47.2 LOPDP CALIFICACIÓN PANSI PARA DECISIONES | I11: RIESGO INHERENTE COMO RESULTADO DEL PROMEDIO DE LAS AREAS DEL 47.2 LOPDP CALIFICACIÓN PANSI PARA RESULTADOS | L11: OCTUBRE 2026 | N11: US$2000<MONTO<US$2500
C12: NO HAY NINGÚN TIPO DE DOCUMENTACIÓN. NO HAY PLAN ESTRATEGICO. GESTIÓN POR REACCIÓN. FASE I PANSI TOMARÁ 6< MESES<9 Y LUEGO INICIA EL PROYECTO SG-PDP | D12: 1 | F12: NO EXISTE NINGÚN MODELO PARA TOMAR DECISIONES INFORMADAS. LAS DECISIONES SON POR REACCIÓN, POR JERARQUÍA E IMPROVISACIÓN. | G12: 1 | I12: NO EXISTE NINGÚN MODELO PARA GESTIONAR RESULTADOS. SE ACTUA POR REACCIÓN, IMPROVISACIÓN Y SIN COMUNICACIÓN ENTRE ÁREAS | J12: 1 | L12: NOVIEMBRE 2026 | N12: US$2500<MONTO<US$3000
C13: HAY PLAN ESTRATEGICO. SIN PLAN DE CONTINUIDAD DE NEGOCIO. SG VOLUNTARIO Y VALIDADO. FASE I PANSI TOMARÁ 3< MESES<6 Y LUEGO INICIA EL PROYECTO SG-PDP | D13: 2 | F13: ESTRUCTURA ORGANIZACIONAL RESPETADA Y JERARQUÍAS DEFINIDAS. NO HAY MÉTRICAS ASOCIADAS A PDP. NADA SE HACE SIN APROBACIÓN DE LA MÁXIMA AUTORIDAD. | G13: 2 | I13: MÉTRICAS Y KPI's CON POCA RIGUROSIDAD DE SEGUIMIENTO. NO INCLUYEN PDP. TODA ACCIÓN DEBE SER APROBADA POR LA MÁXIMA AUTORIDAD | J13: 2 | L13: DICIEMBRE 2026 | N13: US$3000<MONTO<US$3500
C14: FASE I PANSI COMPLETADA. INICIA PROYECTO SG-PDP TOMARÁ 6< MESES<9 PARA SER VALIDADO CON 1ra AUDITORÍA INTERNA | D14: 3 | F14: FASE I DEL PANSI IMPACTA SOBRE LA TOMA DE DECISIONES INFORMADAS. INCLUIDOS MÉTRICAS Y KPI's LAS DEL PANSI, EIPD. NO TODO LO DECIDE LA MÁXIMA AUTORIDAD. | G14: 3 | I14: TOMA DE DECISIONES INFORMADAS DIRECCIONA Y ORDENA LA GESTIÓN DE RESULTADOS. TRABAJO EN EQUIPO SOBRE OBJETIVOS ORGAIZACIONALES CLAROS | J14: 3 | L14: ENERO 2027 | N14: US$3500<MONTO<US$4000
C15: SG-PDP MANTENIDO, MEJORADO Y RESILIENTE | D15: 4 | F15: SE DECIDE RIGUROSAMENTE SOBRE LAS TENDENCIAS QUE MUESTREN LOS KPI DEL SG-PDP. SE CUMPLE DE MANERA RIGUROSA EL CRONOGRAMA DE SIMULACROS Y EL CRONOGRAMA DE AUDITORÍAS. | G15: 4 | I15: LA GESTIÓN DE RESULTADOS SE BASA RIGUROSAMENTE SOBRE LAS TENDENCIAS QUE MUESTREN LOS KPI DEL SG-PDP. SE CUMPLE DE MANERA RIGUROSA EL CRONOGRAMA DE SIMULACROS Y EL CRONOGRAMA DE AUDITORÍAS. | J15: 4 | L15: FEBRERO 2027 | N15: US$4500<MONTO<US$5000
L16: MARZO 2027 | N16: US$5000<MONTO<US$5500
L17: ABRIL 2027
L18: MAYO 2027
L19: JUNIO 2027

Sheet Análisis NSI
A4: MEDIDAS | B4: ETT | G4: MEDIDAS | H4: =A5 -> ORGANIZATIVAS ETT 2025 | I4: =A6 -> ADMINISTRATIVAS ETT 2025 | J4: =A7 -> JURIDICAS ETT 2025 | K4: =A8 -> FISICAS - OPERATIVAS ETT 2025 | L4: =A9 -> FISICAS - INFRAESTRUCTURA ETT 2025 | M4: =A10 -> TÉCNICAS - COMPETENCIAS ETT 2025 | N4: =A11 -> TÉCNICAS - TECNOLOGÍA ETT 2025 | P4: =+A17 -> PROMEDIO EET 2025 | R4: =$A$42 -> PROMEDIO EET PROYECTADO (2026)
A5: ORGANIZATIVAS ETT 2025 | B5: ='ORGANIZATIVAS EET + PANSI'!I21 -> #DIV/0! | G5: PROMEDIO | H5: =B5 -> #DIV/0! | I5: =B6 -> #DIV/0! | J5: =B7 -> #DIV/0! | K5: =B8 -> #DIV/0! | L5: =B9 -> #DIV/0! | M5: =B10 -> #DIV/0! | N5: =B11 -> #DIV/0! | P5: =+B15 -> #DIV/0! | R5: =$B$42 -> #DIV/0!
A6: ADMINISTRATIVAS ETT 2025 | B6: ='ADMINISTRATIVAS EET + PANSI'!I19 -> #DIV/0!
A7: JURIDICAS ETT 2025 | B7: ='JURÍDICAS EET + PANSI'!I18 -> #DIV/0!
A8: FISICAS - OPERATIVAS ETT 2025 | B8: ='FÍSICAS - OPER EET + PANSI'!I18 -> #DIV/0!
A9: FISICAS - INFRAESTRUCTURA ETT 2025 | B9: ='FÍSICAS - INFRSTRA EET + PANSI'!I19 -> #DIV/0! | G9: =H4 -> ORGANIZATIVAS ETT 2025 | J9: =I4 -> ADMINISTRATIVAS ETT 2025 | M9: =J4 -> JURIDICAS ETT 2025 | P9: =K4 -> FISICAS - OPERATIVAS ETT 2025 | S9: =L4 -> FISICAS - INFRAESTRUCTURA ETT 2025 | V9: =M4 -> TÉCNICAS - COMPETENCIAS ETT 2025 | Y9: =N4 -> TÉCNICAS - TECNOLOGÍA ETT 2025 | AB9: =+P4 -> PROMEDIO EET 2025
A10: TÉCNICAS - COMPETENCIAS ETT 2025 | B10: ='TÉCNICAS COMPET EET + PANSI'!I18 -> #DIV/0! | G10: INDICADOR | H10: =H5-0.05 -> #DIV/0! | J10: INDICADOR | K10: =I5-0.5 -> #DIV/0! | M10: INDICADOR | N10: =J5-0.05 -> #DIV/0! | P10: INDICADOR | Q10: =K5-0.05 -> #DIV/0! | S10: INDICADOR | T10: =L5-0.05 -> #DIV/0! | V10: INDICADOR | W10: =M5-0.05 -> #DIV/0! | Y10: INDICADOR | Z10: =N5-0.05 -> #DIV/0! | AB10: INDICADOR | AC10: =$P$5 -> #DIV/0!
A11: TÉCNICAS - TECNOLOGÍA ETT 2025 | B11: ='TÉCNICAS TECNOL EET + PANSI'!I19 -> #DIV/0! | G11: AGUJA | H11: 0.1 | J11: AGUJA | K11: 0.1 | M11: AGUJA | N11: 0.1 | P11: AGUJA | Q11: 0.1 | S11: AGUJA | T11: 0.1 | V11: AGUJA | W11: =0.1 -> 0.1 | Y11: AGUJA | Z11: 0.1 | AB11: AGUJA | AC11: 0.1
G12: RESTO | H12: =8-H10-H11 -> #DIV/0! | J12: RESTO | K12: =8-K10-K11 -> #DIV/0! | M12: RESTO | N12: =8-N10-N11 -> #DIV/0! | P12: RESTO | Q12: =8-Q10-Q11 -> #DIV/0! | S12: RESTO | T12: =8-T10-T11 -> #DIV/0! | V12: RESTO | W12: =8-W10-W11 -> #DIV/0! | Y12: RESTO | Z12: =8-Z10-Z11 -> #DIV/0! | AB12: RESTO | AC12: =8-AC10-AC11 -> #DIV/0!
A15: NIVEL DE SEGURIDAD INICIAL | B15: ='NIVEL DE SEGURIDAD'!$I$15 -> #DIV/0!
A17: PROMEDIO EET 2025 | B17: =+(B5*0.3)+(B6*0.2)+(B7*0.2)+(B8+B9+B10+B11)/4*0.3 -> #DIV/0!
F27: 4 | G27: 5 | H27: 6 | I27: 7 | J27: 8 | K27: 9 | L27: 10 | M27: 11 | N27: 12 | O27: 13 | P27: 14 | Q27: 15 | R27: 16
F28: POBRE | I28: MEDIO BAJO | M28: MEDIO ALTO | Q28: PROFESIONAL
A32: PROYECTADO
A33: MEDIDAS | B33: PANSI | G33: MEDIDAS | H33: =A34 -> ORGANIZATIVAS PROYECTADA | I33: =A35 -> ADMINISTRATIVAS PROYECTADA | J33: =A36 -> JURIDICAS PROYECTADA | K33: =A37 -> FISICAS - OPERATIVAS PROYECTADA | L33: =A38 -> FISICAS - INFRAESTRUCTURA PROYECTADA | M33: =A39 -> TÉCNICAS - COMPETENCIAS PROYECTADA | N33: =A40 -> TÉCNICAS - TECNOLOGÍA PROYECTADA
A34: ORGANIZATIVAS PROYECTADA | B34: ='ORGANIZATIVAS EET + PANSI'!I42 -> #DIV/0! | G34: PROMEDIO | H34: =B34 -> #DIV/0! | I34: =B35 -> #DIV/0! | J34: =B36 -> #DIV/0! | K34: =B37 -> #DIV/0! | L34: =B38 -> #DIV/0! | M34: =B39 -> #DIV/0! | N34: =B40 -> #DIV/0!
A35: ADMINISTRATIVAS PROYECTADA | B35: ='ADMINISTRATIVAS EET + PANSI'!I39 -> #DIV/0!
A36: JURIDICAS PROYECTADA | B36: ='JURÍDICAS EET + PANSI'!I37 -> #DIV/0!
A37: FISICAS - OPERATIVAS PROYECTADA | B37: ='FÍSICAS - OPER EET + PANSI'!I35 -> #DIV/0!
A38: FISICAS - INFRAESTRUCTURA PROYECTADA | B38: ='FÍSICAS - INFRSTRA EET + PANSI'!I37 -> #DIV/0! | G38: =H33 -> ORGANIZATIVAS PROYECTADA | J38: =I33 -> ADMINISTRATIVAS PROYECTADA | M38: =J33 -> JURIDICAS PROYECTADA | P38: =K33 -> FISICAS - OPERATIVAS PROYECTADA | S38: =L33 -> FISICAS - INFRAESTRUCTURA PROYECTADA | V38: =M33 -> TÉCNICAS - COMPETENCIAS PROYECTADA | Y38: =N33 -> TÉCNICAS - TECNOLOGÍA PROYECTADA
A39: TÉCNICAS - COMPETENCIAS PROYECTADA | B39: ='TÉCNICAS COMPET EET + PANSI'!I35 -> #DIV/0! | G39: INDICADOR | H39: =H34-0.05 -> #DIV/0! | J39: INDICADOR | K39: =I34-0.5 -> #DIV/0! | M39: INDICADOR | N39: =J34-0.05 -> #DIV/0! | P39: INDICADOR | Q39: =K34-0.05 -> #DIV/0! | S39: INDICADOR | T39: =L34-0.05 -> #DIV/0! | V39: INDICADOR | W39: =M34-0.05 -> #DIV/0! | Y39: INDICADOR | Z39: =N34-0.05 -> #DIV/0!
A40: TÉCNICAS - TECNOLOGÍA PROYECTADA | B40: ='TÉCNICAS TECNOL EET + PANSI'!I38 -> #DIV/0! | G40: AGUJA | H40: 0.1 | J40: AGUJA | K40: 0.1 | M40: AGUJA | N40: 0.1 | P40: AGUJA | Q40: 0.1 | S40: AGUJA | T40: 0.1 | V40: AGUJA | W40: =0.1 -> 0.1 | Y40: AGUJA | Z40: 0.1
G41: RESTO | H41: =8-H39-H40 -> #DIV/0! | J41: RESTO | K41: =8-K39-K40 -> #DIV/0! | M41: RESTO | N41: =8-N39-N40 -> #DIV/0! | P41: RESTO | Q41: =8-Q39-Q40 -> #DIV/0! | S41: RESTO | T41: =8-T39-T40 -> #DIV/0! | V41: RESTO | W41: =8-W39-W40 -> #DIV/0! | Y41: RESTO | Z41: =8-Z39-Z40 -> #DIV/0!
A42: PROMEDIO EET PROYECTADO (2026) | B42: =+(B34*0.3)+(B35*0.2)+(B36*0.2)+(B37+B38+B39+B40)/4*0.3 -> #DIV/0!
A44: NIVEL DE SEGURIDAD PROYECTADO
K60: =R4 -> PROMEDIO EET PROYECTADO (2026)
K61: INDICADOR | L61: =R5-0.5 -> #DIV/0!
K62: AGUJA | L62: 0.1
K63: RESTO | L63: =8-L61-L62 -> #DIV/0!

Sheet Resumen NSI
A2: MEDIDAS | B2: SUB MEDIDAS | C2: NSI | D2: WEB | E2: DIGITAL | F2: PATD | G2: REMOTO | H2: CALIFICACIÓN | L2: 1
A3: ORGANIZATIVAS | B3: JERARQUIAS | C3: =#REF! -> #REF! | L3: 2
A4: ORGANIZATIVAS | B4: ROLES | C4: =#REF! -> #REF! | L4: 3
A5: ORGANIZATIVAS | B5: DEFINICIÓN CONTEXTOS | C5: =#REF! -> #REF! | L5: 4
A6: ORGANIZATIVAS | B6: IDENTIFICACIÓN 3ras PARTES | C6: =#REF! -> #REF!
A7: ORGANIZATIVAS | B7: IDENTIFICACIÓN ÁMBITOS | C7: =#REF! -> #REF!
A8: ORGANIZATIVAS | B8: GESTIÓN POR ÁMBITOS | C8: =#REF! -> #REF!
A9: ORGANIZATIVAS | B9: ESTRATEGIA | C9: =#REF! -> #REF!
A10: ORGANIZATIVAS | B10: PLAN ESTRATÉGICO | C10: =#REF! -> #REF!
A11: ORGANIZATIVAS | B11: PLAN CONTINUIDAD | C11: =#REF! -> #REF!
A12: ORGANIZATIVAS | B12: DOCUMENTACIÓN GRC | C12: =#REF! -> #REF!
A13: ORGANIZATIVAS | B13: GESTIÓN TALENTO | C13: =#REF! -> #REF!
A14: ORGANIZATIVAS | B14: GESTIÓN DEL CAMBIO | C14: =#REF! -> #REF!
A15: ORGANIZATIVAS | B15: TOMA DE DECISIONES | C15: =#REF! -> #REF!
A16: ORGANIZATIVAS | B16: SANCIONES Y RECOMPENSAS | C16: =#REF! -> #REF!
A17: ADMINISTRATIVAS | B17: SANCIONES Y RECOMPENSAS | C17: =#REF! -> #REF!
... A74: TÉCNICAS - INFRAESTRUCTURA | B74: ENCRIPTACIÓN Y SEUDONIMIZACIÓN | C74: =#REF! -> #REF!

Sheet ORGANIZATIVAS EET + PANSI
D2: EVALUACIÓN DEL ESTADO DE LA TECNICA ÁREA ORGANIZATIVAS REQUISITO LOPDP:2021, ARTÍCULO 10.j
D6: CAÓTICO | E6: PSEUDO - PROFESIONAL | G6: PROFESIONAL
D7: 1 | E7: MEDIO BAJO 2 | F7: MEDIO ALTO 3 | G7: 4 | H7: COMENTARIOS
D8: DOCUMENTACIÓN INEXISTENTE | E8: DOCUMENTACIÓN SIN PDP INCLUIDO | F8: GRC DOCUMENTADO CON PDP INCLUIDO. PANSI FASE 1 | G8: SG-PDP VALIDADO Y EN PRIMER TRIMESTRE OPERATIVO
C9: ESTRATEGIA Debe existir esta documentación: (Filosofía organizacional, Visión, Misión, Principios y Valores), | I9: =IFERROR(_xlfn.IFS(D9="NO EXISTE DOCUMENTACIÓN, NI MÉTODOS. ORGANIZACIÓN EMPÍRICA. CERO CAPACIDAD DE REACCIÓN",1,E9="EXISTEN DOCUMENTOS. HAY MÉTODOS SIN RIGUROSIDAD. NO HAY PROYECTO PDP. HAY UN DPD. NIVEL MÍNIMO DE SEGURIDAD. BAJA CAPACIDAD DE IDENTIFICAR Y RESTAURAR BRECHAS",2,F9="PROYECTO PDP EN FASE INICIAL PANSI. HAY DPD. HAY APOYO POR EL RTD. NIVEL MÍNIMO DESEADO DE SEGURIDAD. VULNERABILIDADES IDENTIFICADAS Y ATENDIDAS",3,G9="SG-PDP VALIDADO Y EN PRIMER TRIMESTE DE OPERACIÓN. NIVEL DE SEGURIDAD ADECUADO",4),0) -> 0
B10: VULNERABILIDADES ORGANIZATIVAS | C10: PLAN ESTRATÉGICO Debe existir esta documentación: (Objetivos estratégicos, Proyectos Inductores, Actividades, metas, tiempos y responsables, todo documentado y en ejecución) | I10: =IFERROR(_xlfn.IFS(D10="NO EXISTE DOCUMENTACIÓN, NI MÉTODOS. ORGANIZACIÓN EMPÍRICA. CERO CAPACIDAD DE REACCIÓN",1,E10="EXISTEN DOCUMENTOS. HAY MÉTODOS SIN RIGUROSIDAD. NO HAY PROYECTO PDP. HAY UN DPD. NIVEL MÍNIMO DE SEGURIDAD. BAJA CAPACIDAD DE IDENTIFICAR Y RESTAURAR BRECHAS",2,F10="PROYECTO PDP EN FASE INICIAL PANSI. HAY DPD. HAY APOYO POR EL RTD. NIVEL MÍNIMO DESEADO DE SEGURIDAD. VULNERABILIDADES IDENTIFICADAS Y ATENDIDAS",3,G10="SG-PDP VALIDADO Y EN PRIMER TRIMESTE DE OPERACIÓN. NIVEL DE SEGURIDAD ADECUADO",4),0) -> 0
C11: PLAN CONTINUIDAD Debe existir esta documentación (Evaluación de riesgos sobre el plan estratégico, Protocolo de crisis o plan de atención a intermitencias), | I11: =IFERROR(_xlfn.IFS(D11="NO EXISTE DOCUMENTACIÓN, NI MÉTODOS. ORGANIZACIÓN EMPÍRICA. CERO CAPACIDAD DE REACCIÓN",1,E11="EXISTEN DOCUMENTOS. HAY MÉTODOS SIN RIGUROSIDAD. NO HAY PROYECTO PDP. HAY UN DPD. NIVEL MÍNIMO DE SEGURIDAD. BAJA CAPACIDAD DE IDENTIFICAR Y RESTAURAR BRECHAS",2,F11="PROYECTO PDP EN FASE INICIAL PANSI. HAY DPD. HAY APOYO POR EL RTD. NIVEL MÍNIMO DESEADO DE SEGURIDAD. VULNERABILIDADES IDENTIFICADAS Y ATENDIDAS",3,G11="SG-PDP VALIDADO Y EN PRIMER TRIMESTE DE OPERACIÓN. NIVEL DE SEGURIDAD ADECUADO",4),0) -> 0
C12: DOCUMENTACIÓN GRC Debe existir esta documentación (Políticas, gestión de indicadores claves, Registros y métricas, todo alineado con Continuidad de negocio, atención intermitencias y PDP), | I12: =IFERROR(_xlfn.IFS(D12="NO EXISTE DOCUMENTACIÓN, NI MÉTODOS. ORGANIZACIÓN EMPÍRICA. CERO CAPACIDAD DE REACCIÓN",1,E12="EXISTEN DOCUMENTOS. HAY MÉTODOS SIN RIGUROSIDAD. NO HAY PROYECTO PDP. HAY UN DPD. NIVEL MÍNIMO DE SEGURIDAD. BAJA CAPACIDAD DE IDENTIFICAR Y RESTAURAR BRECHAS",2,F12="PROYECTO PDP EN FASE INICIAL PANSI. HAY DPD. HAY APOYO POR EL RTD. NIVEL MÍNIMO DESEADO DE SEGURIDAD. VULNERABILIDADES IDENTIFICADAS Y ATENDIDAS",3,G12="SG-PDP VALIDADO Y EN PRIMER TRIMESTE DE OPERACIÓN. NIVEL DE SEGURIDAD ADECUADO",4),0) -> 0
C13: GESTIÓN TALENTO Debe existir esta documentación (Cronogramas de conscienciación y capacitación, esquema de evaluación de la eficacia y eficiencia de ambos e impacto en SG-PDP,esto desde el G-R-C) | I13: =IFERROR(_xlfn.IFS(D13="NO EXISTE DOCUMENTACIÓN, NI MÉTODOS. ORGANIZACIÓN EMPÍRICA. CERO CAPACIDAD DE REACCIÓN",1,E13="EXISTEN DOCUMENTOS. HAY MÉTODOS SIN RIGUROSIDAD. NO HAY PROYECTO PDP. HAY UN DPD. NIVEL MÍNIMO DE SEGURIDAD. BAJA CAPACIDAD DE IDENTIFICAR Y RESTAURAR BRECHAS",2,F13="PROYECTO PDP EN FASE INICIAL PANSI. HAY DPD. HAY APOYO POR EL RTD. NIVEL MÍNIMO DESEADO DE SEGURIDAD. VULNERABILIDADES IDENTIFICADAS Y ATENDIDAS",3,G13="SG-PDP VALIDADO Y EN PRIMER TRIMESTE DE OPERACIÓN. NIVEL DE SEGURIDAD ADECUADO",4),0) -> 0
C14: CONTROL DE CAMBIO Debe existir esta documentación (Política, procedimiento y registros que garanticen la PDP en eventos de cambio como vacaciones, ausencias, promociones, otros) | I14: =IFERROR(_xlfn.IFS(D14="NO EXISTE DOCUMENTACIÓN, NI MÉTODOS. ORGANIZACIÓN EMPÍRICA. CERO CAPACIDAD DE REACCIÓN",1,E14="EXISTEN DOCUMENTOS. HAY MÉTODOS SIN RIGUROSIDAD. NO HAY PROYECTO PDP. HAY UN DPD. NIVEL MÍNIMO DE SEGURIDAD. BAJA CAPACIDAD DE IDENTIFICAR Y RESTAURAR BRECHAS",2,F14="PROYECTO PDP EN FASE INICIAL PANSI. HAY DPD. HAY APOYO POR EL RTD. NIVEL MÍNIMO DESEADO DE SEGURIDAD. VULNERABILIDADES IDENTIFICADAS Y ATENDIDAS",3,G14="SG-PDP VALIDADO Y EN PRIMER TRIMESTE DE OPERACIÓN. NIVEL DE SEGURIDAD ADECUADO",4),0) -> 0
C15: TOMA DE DECISIONES Debe existir esta documentación (Política, procedimiento, registros y esquema de sanciones y recompensas para segumiento y control de métricas y KPI's relacionados al SG-PDP) | I15: =IFERROR(_xlfn.IFS(D15="NO EXISTE DOCUMENTACIÓN, NI MÉTODOS. ORGANIZACIÓN EMPÍRICA. CERO CAPACIDAD DE REACCIÓN",1,E15="EXISTEN DOCUMENTOS. HAY MÉTODOS SIN RIGUROSIDAD. NO HAY PROYECTO PDP. HAY UN DPD. NIVEL MÍNIMO DE SEGURIDAD. BAJA CAPACIDAD DE IDENTIFICAR Y RESTAURAR BRECHAS",2,F15="PROYECTO PDP EN FASE INICIAL PANSI. HAY DPD. HAY APOYO POR EL RTD. NIVEL MÍNIMO DESEADO DE SEGURIDAD. VULNERABILIDADES IDENTIFICADAS Y ATENDIDAS",3,G15="SG-PDP VALIDADO Y EN PRIMER TRIMESTE DE OPERACIÓN. NIVEL DE SEGURIDAD ADECUADO",4),0) -> 0
C16: SANCIONES Y RECOMPENSAS Debe existir esta documentación (Políticas, procedimientos y registros que establezcan la gobernanza y cumplimiento del SG-PDP y el plan de continuidad del negocio) | I16: =IFERROR(_xlfn.IFS(D16="NO EXISTE DOCUMENTACIÓN, NI MÉTODOS. ORGANIZACIÓN EMPÍRICA. CERO CAPACIDAD DE REACCIÓN",1,E16="EXISTEN DOCUMENTOS. HAY MÉTODOS SIN RIGUROSIDAD. NO HAY PROYECTO PDP. HAY UN DPD. NIVEL MÍNIMO DE SEGURIDAD. BAJA CAPACIDAD DE IDENTIFICAR Y RESTAURAR BRECHAS",2,F16="PROYECTO PDP EN FASE INICIAL PANSI. HAY DPD. HAY APOYO POR EL RTD. NIVEL MÍNIMO DESEADO DE SEGURIDAD. VULNERABILIDADES IDENTIFICADAS Y ATENDIDAS",3,G16="SG-PDP VALIDADO Y EN PRIMER TRIMESTE DE OPERACIÓN. NIVEL DE SEGURIDAD ADECUADO",4),0) -> 0
C17: ORGANIGRAMA Debe existir esta documentación (Estructura organizacional, departamental, mapa de procesos, niveles de autoridad, niveles de responsabilidad, todo desde la estructura G-R-C y SG-PDP) | I17: =IFERROR(_xlfn.IFS(D17="NO EXISTE DOCUMENTACIÓN, NI MÉTODOS. ORGANIZACIÓN EMPÍRICA. CERO CAPACIDAD DE REACCIÓN",1,E17="EXISTEN DOCUMENTOS. HAY MÉTODOS SIN RIGUROSIDAD. NO HAY PROYECTO PDP. HAY UN DPD. NIVEL MÍNIMO DE SEGURIDAD. BAJA CAPACIDAD DE IDENTIFICAR Y RESTAURAR BRECHAS",2,F17="PROYECTO PDP EN FASE INICIAL PANSI. HAY DPD. HAY APOYO POR EL RTD. NIVEL MÍNIMO DESEADO DE SEGURIDAD. VULNERABILIDADES IDENTIFICADAS Y ATENDIDAS",3,G17="SG-PDP VALIDADO Y EN PRIMER TRIMESTE DE OPERACIÓN. NIVEL DE SEGURIDAD ADECUADO",4),0) -> 0
C18: ROLES SEGREGADOS Debe existir esta documentación (desde el G-R-C definir responsabilidad, autoridad y ejecución sobre rutinas PDP, continuidad de negocio, atención a intermitencias y relación con SG-PDP) | I18: =IFERROR(_xlfn.IFS(D18="NO EXISTE DOCUMENTACIÓN, NI MÉTODOS. ORGANIZACIÓN EMPÍRICA. CERO CAPACIDAD DE REACCIÓN",1,E18="EXISTEN DOCUMENTOS. HAY MÉTODOS SIN RIGUROSIDAD. NO HAY PROYECTO PDP. HAY UN DPD. NIVEL MÍNIMO DE SEGURIDAD. BAJA CAPACIDAD DE IDENTIFICAR Y RESTAURAR BRECHAS",2,F18="PROYECTO PDP EN FASE INICIAL PANSI. HAY DPD. HAY APOYO POR EL RTD. NIVEL MÍNIMO DESEADO DE SEGURIDAD. VULNERABILIDADES IDENTIFICADAS Y ATENDIDAS",3,G18="SG-PDP VALIDADO Y EN PRIMER TRIMESTE DE OPERACIÓN. NIVEL DE SEGURIDAD ADECUADO",4),0) -> 0
C19: DEFINICIÓN CONTEXTOS Debe existir esta documentación (Interno, Externo y PDP, caracterización de los ecosistemas de cada contexto, Ejercicio ABC de las figuras críticas de los ecosistemas) | I19: =IFERROR(_xlfn.IFS(D19="NO EXISTE DOCUMENTACIÓN, NI MÉTODOS. ORGANIZACIÓN EMPÍRICA. CERO CAPACIDAD DE REACCIÓN",1,E19="EXISTEN DOCUMENTOS. HAY MÉTODOS SIN RIGUROSIDAD. NO HAY PROYECTO PDP. HAY UN DPD. NIVEL MÍNIMO DE SEGURIDAD. BAJA CAPACIDAD DE IDENTIFICAR Y RESTAURAR BRECHAS",2,F19="PROYECTO PDP EN FASE INICIAL PANSI. HAY DPD. HAY APOYO POR EL RTD. NIVEL MÍNIMO DESEADO DE SEGURIDAD. VULNERABILIDADES IDENTIFICADAS Y ATENDIDAS",3,G19="SG-PDP VALIDADO Y EN PRIMER TRIMESTE DE OPERACIÓN. NIVEL DE SEGURIDAD ADECUADO",4),0) -> 0
C20: 3ras PARTES Debe existir esta documentación (Estructura G-R-C para las relaciones contractuales con proveedores y cadena de subcontratistas asociadas para garanteizar Continuidad del negocio, Antencion a intermitencias Y PDP desde los cronogramas de auditoría y simulacros del SG-PDP) | I20: =IFERROR(_xlfn.IFS(D20="NO EXISTE DOCUMENTACIÓN, NI MÉTODOS. ORGANIZACIÓN EMPÍRICA. CERO CAPACIDAD DE REACCIÓN",1,E20="EXISTEN DOCUMENTOS. HAY MÉTODOS SIN RIGUROSIDAD. NO HAY PROYECTO PDP. HAY UN DPD. NIVEL MÍNIMO DE SEGURIDAD. BAJA CAPACIDAD DE IDENTIFICAR Y RESTAURAR BRECHAS",2,F20="PROYECTO PDP EN FASE INICIAL PANSI. HAY DPD. HAY APOYO POR EL RTD. NIVEL MÍNIMO DESEADO DE SEGURIDAD. VULNERABILIDADES IDENTIFICADAS Y ATENDIDAS",3,G20="SG-PDP VALIDADO Y EN PRIMER TRIMESTE DE OPERACIÓN. NIVEL DE SEGURIDAD ADECUADO",4),0) -> 0
H21: ESTADO DE LA TÉCNICA | I21: =AVERAGEIF(I9:I20,"<>0") -> #DIV/0!
D23: ADECUACIÓN DEL NIVEL DE SEGURIDAD (PANSI) ÁREA: ORGANIZATIVAS OBLIGACIÓN LOPDP:2021, ARTÍCULO 47.6
K26: REQUISITO ARTÍCULO 22.2 -RESOLUCIÓN 2025-0028-R (GARANTÍA DE INDEPENDENCIA PARA DPO) | W26: ESTATUS DEL COMPROMISO DE APLICABILIDAD
D27: CAÓTICO | E27: PSEUDO - PROFESIONAL | G27: PROFESIONAL
D28: 1 | E28: MEDIO BAJO 2 | F28: MEDIO ALTO 3 | G28: 4 | H28: ACCIONES MITIGADORAS | K28: RECURSOS NECESARIO | Q28: COMPROMISOS DE APLICABILIDAD | W28: CUMPLIDO | X28: DEMORADO | Y28: EN PROCESO
D29: DOCUMENTACIÓN INEXISTENTE | E29: DOCUMENTACIÓN SIN PDP INCLUIDO | F29: GRC DOCUMENTADO CON PDP INCLUIDO. PANSI FASE 1 | G29: SG-PDP VALIDADO Y EN PRIMER TRIMESTRE OPERATIVO | H29: MEDIDAS, HERRAMIENTAS Y CONTROLES para elevar el nivel del estado de la técnica | K29: HUMANO | L29: TECNOLOGÍCO | M29: FINANCIERO | N29: TIEMPO | O29: INFRAESTRUCTURA | Q29: FECHA PROBABLE INICIO | R29: INVERSIÓN ESTIMADA HORAS - HOMBRE | S29: INVERSIÓN ESTIMADA DINERO | T29: COMENTARIOS Y ACCIONES REQUERIDAS
C30: ESTRATEGIA Debe existir esta documentación: (Filosofía organizacional, Visión, Misión, Principios y Valores), | I30: =IFERROR(_xlfn.IFS(D30="NO EXISTE DOCUMENTACIÓN, NI MÉTODOS. ORGANIZACIÓN EMPÍRICA. CERO CAPACIDAD DE REACCIÓN",1,E30="EXISTEN DOCUMENTOS. HAY MÉTODOS SIN RIGUROSIDAD. NO HAY PROYECTO PDP. HAY UN DPD. NIVEL MÍNIMO DE SEGURIDAD. BAJA CAPACIDAD DE IDENTIFICAR Y RESTAURAR BRECHAS",2,F30="PROYECTO PDP EN FASE INICIAL PANSI. HAY DPD. HAY APOYO POR EL RTD. NIVEL MÍNIMO DESEADO DE SEGURIDAD. VULNERABILIDADES IDENTIFICADAS Y ATENDIDAS",3,G30="SG-PDP VALIDADO Y EN PRIMER TRIMESTE DE OPERACIÓN. NIVEL DE SEGURIDAD ADECUADO",4),0) -> 0 | Q30: DESCRITO EN COMENTARIOS | R30: DESCRITO EN COMENTARIOS | S30: DESCRITO EN COMENTARIOS
B31: VULNERABILIDADES ORGANIZATIVAS | C31: PLAN ESTRATÉGICO Debe existir esta documentación: (Objetivos estratégicos, Proyectos Inductores, Actividades, metas, tiempos y responsables, todo documentado y en ejecución) | I31: =IFERROR(_xlfn.IFS(D31="NO EXISTE DOCUMENTACIÓN, NI MÉTODOS. ORGANIZACIÓN EMPÍRICA. CERO CAPACIDAD DE REACCIÓN",1,E31="EXISTEN DOCUMENTOS. HAY MÉTODOS SIN RIGUROSIDAD. NO HAY PROYECTO PDP. HAY UN DPD. NIVEL MÍNIMO DE SEGURIDAD. BAJA CAPACIDAD DE IDENTIFICAR Y RESTAURAR BRECHAS",2,F31="PROYECTO PDP EN FASE INICIAL PANSI. HAY DPD. HAY APOYO POR EL RTD. NIVEL MÍNIMO DESEADO DE SEGURIDAD. VULNERABILIDADES IDENTIFICADAS Y ATENDIDAS",3,G31="SG-PDP VALIDADO Y EN PRIMER TRIMESTE DE OPERACIÓN. NIVEL DE SEGURIDAD ADECUADO",4),0) -> 0 | K31: X | N31: X | Q31: JUNIO 2026 | R31: DESCRITO EN COMENTARIOS | S31: DESCRITO EN COMENTARIOS | T31: Se solicitará al responsable del tratamiento los recursos para llevar el proyecto. Se comunicarán las horas que serán necesarias.
C32: PLAN CONTINUIDAD Debe existir esta documentación (Evaluación de riesgos sobre el plan estratégico, Protocolo de crisis o plan de atención a intermitencias), | I32: =IFERROR(_xlfn.IFS(D32="NO EXISTE DOCUMENTACIÓN, NI MÉTODOS. ORGANIZACIÓN EMPÍRICA. CERO CAPACIDAD DE REACCIÓN",1,E32="EXISTEN DOCUMENTOS. HAY MÉTODOS SIN RIGUROSIDAD. NO HAY PROYECTO PDP. HAY UN DPD. NIVEL MÍNIMO DE SEGURIDAD. BAJA CAPACIDAD DE IDENTIFICAR Y RESTAURAR BRECHAS",2,F32="PROYECTO PDP EN FASE INICIAL PANSI. HAY DPD. HAY APOYO POR EL RTD. NIVEL MÍNIMO DESEADO DE SEGURIDAD. VULNERABILIDADES IDENTIFICADAS Y ATENDIDAS",3,G32="SG-PDP VALIDADO Y EN PRIMER TRIMESTE DE OPERACIÓN. NIVEL DE SEGURIDAD ADECUADO",4),0) -> 0 | K32: X | M32: X | N32: X | Q32: DESCRITO EN COMENTARIOS | R32: DESCRITO EN COMENTARIOS | S32: DESCRITO EN COMENTARIOS
C33: DOCUMENTACIÓN GRC Debe existir esta documentación (Políticas, gestión de indicadores claves, Registros y métricas, todo alineado con Continuidad de negocio, atención intermitencias y PDP), | I33: =IFERROR(_xlfn.IFS(D33="NO EXISTE DOCUMENTACIÓN, NI MÉTODOS. ORGANIZACIÓN EMPÍRICA. CERO CAPACIDAD DE REACCIÓN",1,E33="EXISTEN DOCUMENTOS. HAY MÉTODOS SIN RIGUROSIDAD. NO HAY PROYECTO PDP. HAY UN DPD. NIVEL MÍNIMO DE SEGURIDAD. BAJA CAPACIDAD DE IDENTIFICAR Y RESTAURAR BRECHAS",2,F33="PROYECTO PDP EN FASE INICIAL PANSI. HAY DPD. HAY APOYO POR EL RTD. NIVEL MÍNIMO DESEADO DE SEGURIDAD. VULNERABILIDADES IDENTIFICADAS Y ATENDIDAS",3,G33="SG-PDP VALIDADO Y EN PRIMER TRIMESTE DE OPERACIÓN. NIVEL DE SEGURIDAD ADECUADO",4),0) -> 0 | K33: X | M33: X | N33: X | Q33: DESCRITO EN COMENTARIOS | R33: DESCRITO EN COMENTARIOS | S33: DESCRITO EN COMENTARIOS
C34: GESTIÓN TALENTO Debe existir esta documentación (Cronogramas de conscienciación y capacitación, esquema de evaluación de la eficacia y eficiencia de ambos e impacto en SG-PDP,esto desde el G-R-C) | I34: =IFERROR(_xlfn.IFS(D34="NO EXISTE DOCUMENTACIÓN, NI MÉTODOS. ORGANIZACIÓN EMPÍRICA. CERO CAPACIDAD DE REACCIÓN",1,E34="EXISTEN DOCUMENTOS. HAY MÉTODOS SIN RIGUROSIDAD. NO HAY PROYECTO PDP. HAY UN DPD. NIVEL MÍNIMO DE SEGURIDAD. BAJA CAPACIDAD DE IDENTIFICAR Y RESTAURAR BRECHAS",2,F34="PROYECTO PDP EN FASE INICIAL PANSI. HAY DPD. HAY APOYO POR EL RTD. NIVEL MÍNIMO DESEADO DE SEGURIDAD. VULNERABILIDADES IDENTIFICADAS Y ATENDIDAS",3,G34="SG-PDP VALIDADO Y EN PRIMER TRIMESTE DE OPERACIÓN. NIVEL DE SEGURIDAD ADECUADO",4),0) -> 0 | K34: X | M34: X | N34: X | Q34: DESCRITO EN COMENTARIOS | R34: DESCRITO EN COMENTARIOS | S34: DESCRITO EN COMENTARIOS
C35: CONTROL DE CAMBIOS Debe existir esta documentación (Política, procedimiento y registros que garanticen la PDP en eventos de cambio como vacaciones, ausencias, promociones, otros) | I35: =IFERROR(_xlfn.IFS(D35="NO EXISTE DOCUMENTACIÓN, NI MÉTODOS. ORGANIZACIÓN EMPÍRICA. CERO CAPACIDAD DE REACCIÓN",1,E35="EXISTEN DOCUMENTOS. HAY MÉTODOS SIN RIGUROSIDAD. NO HAY PROYECTO PDP. HAY UN DPD. NIVEL MÍNIMO DE SEGURIDAD. BAJA CAPACIDAD DE IDENTIFICAR Y RESTAURAR BRECHAS",2,F35="PROYECTO PDP EN FASE INICIAL PANSI. HAY DPD. HAY APOYO POR EL RTD. NIVEL MÍNIMO DESEADO DE SEGURIDAD. VULNERABILIDADES IDENTIFICADAS Y ATENDIDAS",3,G35="SG-PDP VALIDADO Y EN PRIMER TRIMESTE DE OPERACIÓN. NIVEL DE SEGURIDAD ADECUADO",4),0) -> 0 | K35: X | M35: X | N35: X | Q35: DESCRITO EN COMENTARIOS | R35: DESCRITO EN COMENTARIOS | S35: DESCRITO EN COMENTARIOS
C36: TOMA DE DECISIONES Debe existir esta documentación (Política, procedimiento, registros y esquema de sanciones y recompensas para segumiento y control de métricas y KPI's relacionados al SG-PDP) | I36: =IFERROR(_xlfn.IFS(D36="NO EXISTE DOCUMENTACIÓN, NI MÉTODOS. ORGANIZACIÓN EMPÍRICA. CERO CAPACIDAD DE REACCIÓN",1,E36="EXISTEN DOCUMENTOS. HAY MÉTODOS SIN RIGUROSIDAD. NO HAY PROYECTO PDP. HAY UN DPD. NIVEL MÍNIMO DE SEGURIDAD. BAJA CAPACIDAD DE IDENTIFICAR Y RESTAURAR BRECHAS",2,F36="PROYECTO PDP EN FASE INICIAL PANSI. HAY DPD. HAY APOYO POR EL RTD. NIVEL MÍNIMO DESEADO DE SEGURIDAD. VULNERABILIDADES IDENTIFICADAS Y ATENDIDAS",3,G36="SG-PDP VALIDADO Y EN PRIMER TRIMESTE DE OPERACIÓN. NIVEL DE SEGURIDAD ADECUADO",4),0) -> 0 | K36: X | M36: X | N36: X | Q36: DESCRITO EN COMENTARIOS | R36: DESCRITO EN COMENTARIOS | S36: DESCRITO EN COMENTARIOS
C37: SANCIONES Y RECOMPENSAS Debe existir esta documentación (Políticas, procedimientos y registros que establezcan la gobernanza y cumplimiento del SG-PDP y el plan de continuidad del negocio) | I37: =IFERROR(_xlfn.IFS(D37="NO EXISTE DOCUMENTACIÓN, NI MÉTODOS. ORGANIZACIÓN EMPÍRICA. CERO CAPACIDAD DE REACCIÓN",1,E37="EXISTEN DOCUMENTOS. HAY MÉTODOS SIN RIGUROSIDAD. NO HAY PROYECTO PDP. HAY UN DPD. NIVEL MÍNIMO DE SEGURIDAD. BAJA CAPACIDAD DE IDENTIFICAR Y RESTAURAR BRECHAS",2,F37="PROYECTO PDP EN FASE INICIAL PANSI. HAY DPD. HAY APOYO POR EL RTD. NIVEL MÍNIMO DESEADO DE SEGURIDAD. VULNERABILIDADES IDENTIFICADAS Y ATENDIDAS",3,G37="SG-PDP VALIDADO Y EN PRIMER TRIMESTE DE OPERACIÓN. NIVEL DE SEGURIDAD ADECUADO",4),0) -> 0 | K37: X | M37: X | N37: X | Q37: DESCRITO EN COMENTARIOS | R37: DESCRITO EN COMENTARIOS | S37: DESCRITO EN COMENTARIOS
C38: ORGANIGRAMA Debe existir esta documentación (Estructura organizacional, departamental, mapa de procesos, niveles de autoridad, niveles de responsabilidad, todo desde la estructura G-R-C y SG-PDP) | I38: =IFERROR(_xlfn.IFS(D38="NO EXISTE DOCUMENTACIÓN, NI MÉTODOS. ORGANIZACIÓN EMPÍRICA. CERO CAPACIDAD DE REACCIÓN",1,E38="EXISTEN DOCUMENTOS. HAY MÉTODOS SIN RIGUROSIDAD. NO HAY PROYECTO PDP. HAY UN DPD. NIVEL MÍNIMO DE SEGURIDAD. BAJA CAPACIDAD DE IDENTIFICAR Y RESTAURAR BRECHAS",2,F38="PROYECTO PDP EN FASE INICIAL PANSI. HAY DPD. HAY APOYO POR EL RTD. NIVEL MÍNIMO DESEADO DE SEGURIDAD. VULNERABILIDADES IDENTIFICADAS Y ATENDIDAS",3,G38="SG-PDP VALIDADO Y EN PRIMER TRIMESTE DE OPERACIÓN. NIVEL DE SEGURIDAD ADECUADO",4),0) -> 0 | K38: X | M38: X | N38: X | Q38: DESCRITO EN COMENTARIOS | R38: DESCRITO EN COMENTARIOS | S38: DESCRITO EN COMENTARIOS
C39: ROLES SEGREGADOS Debe existir esta documentación (desde el G-R-C definir responsabilidad, autoridad y ejecución sobre rutinas PDP, continuidad de negocio, atención a intermitencias y relación con SG-PDP) | I39: =IFERROR(_xlfn.IFS(D39="NO EXISTE DOCUMENTACIÓN, NI MÉTODOS. ORGANIZACIÓN EMPÍRICA. CERO CAPACIDAD DE REACCIÓN",1,E39="EXISTEN DOCUMENTOS. HAY MÉTODOS SIN RIGUROSIDAD. NO HAY PROYECTO PDP. HAY UN DPD. NIVEL MÍNIMO DE SEGURIDAD. BAJA CAPACIDAD DE IDENTIFICAR Y RESTAURAR BRECHAS",2,F39="PROYECTO PDP EN FASE INICIAL PANSI. HAY DPD. HAY APOYO POR EL RTD. NIVEL MÍNIMO DESEADO DE SEGURIDAD. VULNERABILIDADES IDENTIFICADAS Y ATENDIDAS",3,G39="SG-PDP VALIDADO Y EN PRIMER TRIMESTE DE OPERACIÓN. NIVEL DE SEGURIDAD ADECUADO",4),0) -> 0 | K39: X | M39: X | N39: X | Q39: DESCRITO EN COMENTARIOS | R39: DESCRITO EN COMENTARIOS | S39: DESCRITO EN COMENTARIOS
C40: DEFINICIÓN CONTEXTOS Debe existir esta documentación (Interno, Externo y PDP, caracterización de los ecosistemas de cada contexto, Ejercicio ABC de las figuras críticas de los ecosistemas) | I40: =IFERROR(_xlfn.IFS(D40="NO EXISTE DOCUMENTACIÓN, NI MÉTODOS. ORGANIZACIÓN EMPÍRICA. CERO CAPACIDAD DE REACCIÓN",1,E40="EXISTEN DOCUMENTOS. HAY MÉTODOS SIN RIGUROSIDAD. NO HAY PROYECTO PDP. HAY UN DPD. NIVEL MÍNIMO DE SEGURIDAD. BAJA CAPACIDAD DE IDENTIFICAR Y RESTAURAR BRECHAS",2,F40="PROYECTO PDP EN FASE INICIAL PANSI. HAY DPD. HAY APOYO POR EL RTD. NIVEL MÍNIMO DESEADO DE SEGURIDAD. VULNERABILIDADES IDENTIFICADAS Y ATENDIDAS",3,G40="SG-PDP VALIDADO Y EN PRIMER TRIMESTE DE OPERACIÓN. NIVEL DE SEGURIDAD ADECUADO",4),0) -> 0 | K40: X | M40: X | N40: X | Q40: DESCRITO EN COMENTARIOS | R40: DESCRITO EN COMENTARIOS | S40: DESCRITO EN COMENTARIOS
C41: 3ras PARTES Debe existir esta documentación (Estructura G-R-C para las relaciones contractuales con proveedores y cadena de subcontratistas asociadas para garanteizar Continuidad del negocio, Antencion a intermitencias Y PDP desde los cronogramas de auditoría y simulacros del SG-PDP) | I41: =IFERROR(_xlfn.IFS(D41="NO EXISTE DOCUMENTACIÓN, NI MÉTODOS. ORGANIZACIÓN EMPÍRICA. CERO CAPACIDAD DE REACCIÓN",1,E41="EXISTEN DOCUMENTOS. HAY MÉTODOS SIN RIGUROSIDAD. NO HAY PROYECTO PDP. HAY UN DPD. NIVEL MÍNIMO DE SEGURIDAD. BAJA CAPACIDAD DE IDENTIFICAR Y RESTAURAR BRECHAS",2,F41="PROYECTO PDP EN FASE INICIAL PANSI. HAY DPD. HAY APOYO POR EL RTD. NIVEL MÍNIMO DESEADO DE SEGURIDAD. VULNERABILIDADES IDENTIFICADAS Y ATENDIDAS",3,G41="SG-PDP VALIDADO Y EN PRIMER TRIMESTE DE OPERACIÓN. NIVEL DE SEGURIDAD ADECUADO",4),0) -> 0 | K41: X | M41: X | N41: X | Q41: DESCRITO EN COMENTARIOS | R41: DESCRITO EN COMENTARIOS | S41: DESCRITO EN COMENTARIOS
I42: =AVERAGEIF(I30:I41,"<>0") -> #DIV/0!

Sheet ADMINISTRATIVAS EET + PANSI
D2: EVALUACIÓN DEL ESTADO DE LA TECNICA ÁREA: ADMINISTRATIVAS REQUISITO LOPDP:2021, ARTÍCULO 10.j
D6: CAÓTICO | E6: PSEUDO - PROFESIONAL | G6: PROFESIONAL
D7: 1 | E7: MEDIO BAJO 2 | F7: MEDIO ALTO 3 | G7: 4 | H7: COMENTARIOS
D8: DOCUMENTACIÓN INEXISTENTE | E8: DOCUMENTACIÓN SIN PDP INCLUIDO | F8: GRC DOCUMENTADO CON PDP INCLUIDO. PANSI FASE 1 | G8: SG-PDP VALIDADO Y EN PRIMER TRIMESTRE OPERATIVO
C9: SANCIONES Y RECOMPENSAS Debe existir esta documentación: (INDICADORES DE EFICIENCIA Y EFICACIA DEL ESQUEMA) | I9: =IFERROR(_xlfn.IFS(D9="NO EXISTE DOCUMENTACIÓN, NI MÉTODOS. ORGANIZACIÓN EMPÍRICA. CERO CAPACIDAD DE REACCIÓN",1,E9="EXISTEN DOCUMENTOS. HAY MÉTODOS SIN RIGUROSIDAD. NO HAY PROYECTO PDP. HAY UN DPD. NIVEL MÍNIMO DE SEGURIDAD. BAJA CAPACIDAD DE IDENTIFICAR Y RESTAURAR BRECHAS",2,F9="PROYECTO PDP EN FASE INICIAL PANSI. HAY DPD. HAY APOYO POR EL RTD. NIVEL MÍNIMO DESEADO DE SEGURIDAD. VULNERABILIDADES IDENTIFICADAS Y ATENDIDAS",3,G9="SG-PDP VALIDADO Y EN PRIMER TRIMESTE DE OPERACIÓN. NIVEL DE SEGURIDAD ADECUADO",4),0) -> 0
B10: VULNERABILIDADES ADMINISTRATIVAS | C10: GESTIÓN DEL TALENTO Debe existir esta documentación: (INDICADORES COMPETENCIA Y CONSCIENCIA) | I10: =IFERROR(_xlfn.IFS(D10="NO EXISTE DOCUMENTACIÓN, NI MÉTODOS. ORGANIZACIÓN EMPÍRICA. CERO CAPACIDAD DE REACCIÓN",1,E10="EXISTEN DOCUMENTOS. HAY MÉTODOS SIN RIGUROSIDAD. NO HAY PROYECTO PDP. HAY UN DPD. NIVEL MÍNIMO DE SEGURIDAD. BAJA CAPACIDAD DE IDENTIFICAR Y RESTAURAR BRECHAS",2,F10="PROYECTO PDP EN FASE INICIAL PANSI. HAY DPD. HAY APOYO POR EL RTD. NIVEL MÍNIMO DESEADO DE SEGURIDAD. VULNERABILIDADES IDENTIFICADAS Y ATENDIDAS",3,G10="SG-PDP VALIDADO Y EN PRIMER TRIMESTE DE OPERACIÓN. NIVEL DE SEGURIDAD ADECUADO",4),0) -> 0
C11: GESTIÓN INGRESOS Y DESVINCULACIÓN Debe existir esta documentación: (INDICADORES DE EFICIENCIA Y EFICACIA DEL ESQUEMA) | I11: =IFERROR(_xlfn.IFS(D11="NO EXISTE DOCUMENTACIÓN, NI MÉTODOS. ORGANIZACIÓN EMPÍRICA. CERO CAPACIDAD DE REACCIÓN",1,E11="EXISTEN DOCUMENTOS. HAY MÉTODOS SIN RIGUROSIDAD. NO HAY PROYECTO PDP. HAY UN DPD. NIVEL MÍNIMO DE SEGURIDAD. BAJA CAPACIDAD DE IDENTIFICAR Y RESTAURAR BRECHAS",2,F11="PROYECTO PDP EN FASE INICIAL PANSI. HAY DPD. HAY APOYO POR EL RTD. NIVEL MÍNIMO DESEADO DE SEGURIDAD. VULNERABILIDADES IDENTIFICADAS Y ATENDIDAS",3,G11="SG-PDP VALIDADO Y EN PRIMER TRIMESTE DE OPERACIÓN. NIVEL DE SEGURIDAD ADECUADO",4),0) -> 0
C12: ESTRUCTURA DOCUMENTAL Debe existir esta documentación: (ESQUEMA DE CONTROL DE DOCUMENTOS, LISTA MAESTRA REGISTROS, MÉTRICAS Y KPI's) | I12: =IFERROR(_xlfn.IFS(D12="NO EXISTE DOCUMENTACIÓN, NI MÉTODOS. ORGANIZACIÓN EMPÍRICA. CERO CAPACIDAD DE REACCIÓN",1,E12="EXISTEN DOCUMENTOS. HAY MÉTODOS SIN RIGUROSIDAD. NO HAY PROYECTO PDP. HAY UN DPD. NIVEL MÍNIMO DE SEGURIDAD. BAJA CAPACIDAD DE IDENTIFICAR Y RESTAURAR BRECHAS",2,F12="PROYECTO PDP EN FASE INICIAL PANSI. HAY DPD. HAY APOYO POR EL RTD. NIVEL MÍNIMO DESEADO DE SEGURIDAD. VULNERABILIDADES IDENTIFICADAS Y ATENDIDAS",3,G12="SG-PDP VALIDADO Y EN PRIMER TRIMESTE DE OPERACIÓN. NIVEL DE SEGURIDAD ADECUADO",4),0) -> 0
C13: ESQUEMA DE PROTECCIÓN DE DATOS - INFORMACIÓN Debe existir esta documentación: (CICLO DE VIDA DE DATOS, MAPA DE PROCESOS, ESTACIONES AUTOGESTIONADAS, OTRO) | I13: =IFERROR(_xlfn.IFS(D13="NO EXISTE DOCUMENTACIÓN, NI MÉTODOS. ORGANIZACIÓN EMPÍRICA. CERO CAPACIDAD DE REACCIÓN",1,E13="EXISTEN DOCUMENTOS. HAY MÉTODOS SIN RIGUROSIDAD. NO HAY PROYECTO PDP. HAY UN DPD. NIVEL MÍNIMO DE SEGURIDAD. BAJA CAPACIDAD DE IDENTIFICAR Y RESTAURAR BRECHAS",2,F13="PROYECTO PDP EN FASE INICIAL PANSI. HAY DPD. HAY APOYO POR EL RTD. NIVEL MÍNIMO DESEADO DE SEGURIDAD. VULNERABILIDADES IDENTIFICADAS Y ATENDIDAS",3,G13="SG-PDP VALIDADO Y EN PRIMER TRIMESTE DE OPERACIÓN. NIVEL DE SEGURIDAD ADECUADO",4),0) -> 0
C14: GESTIÓN DE INDICADORES Debe existir esta documentación: (MEJORA CONTINUA, RESILIENCIA y EJERCICIO DE DERECHOS, OTROS PDP) | I14: =IFERROR(_xlfn.IFS(D14="NO EXISTE DOCUMENTACIÓN, NI MÉTODOS. ORGANIZACIÓN EMPÍRICA. CERO CAPACIDAD DE REACCIÓN",1,E14="EXISTEN DOCUMENTOS. HAY MÉTODOS SIN RIGUROSIDAD. NO HAY PROYECTO PDP. HAY UN DPD. NIVEL MÍNIMO DE SEGURIDAD. BAJA CAPACIDAD DE IDENTIFICAR Y RESTAURAR BRECHAS",2,F14="PROYECTO PDP EN FASE INICIAL PANSI. HAY DPD. HAY APOYO POR EL RTD. NIVEL MÍNIMO DESEADO DE SEGURIDAD. VULNERABILIDADES IDENTIFICADAS Y ATENDIDAS",3,G14="SG-PDP VALIDADO Y EN PRIMER TRIMESTE DE OPERACIÓN. NIVEL DE SEGURIDAD ADECUADO",4),0) -> 0
C15: PLAN AUDITORÍAS INTERNAS Debe existir esta documentación: (AUDITORÍAS AL SG 1ra y 2da PARTE, EVIDENCIA DE MEJORA CONTINUA) | I15: =IFERROR(_xlfn.IFS(D15="NO EXISTE DOCUMENTACIÓN, NI MÉTODOS. ORGANIZACIÓN EMPÍRICA. CERO CAPACIDAD DE REACCIÓN",1,E15="EXISTEN DOCUMENTOS. HAY MÉTODOS SIN RIGUROSIDAD. NO HAY PROYECTO PDP. HAY UN DPD. NIVEL MÍNIMO DE SEGURIDAD. BAJA CAPACIDAD DE IDENTIFICAR Y RESTAURAR BRECHAS",2,F15="PROYECTO PDP EN FASE INICIAL PANSI. HAY DPD. HAY APOYO POR EL RTD. NIVEL MÍNIMO DESEADO DE SEGURIDAD. VULNERABILIDADES IDENTIFICADAS Y ATENDIDAS",3,G15="SG-PDP VALIDADO Y EN PRIMER TRIMESTE DE OPERACIÓN. NIVEL DE SEGURIDAD ADECUADO",4),0) -> 0
C16: PLAN AUDITOÍAS 3ras PARTES Debe existir esta documentación: (AUDITORÍAS 2da PARTE, A ENCARGADOS Y 3ros) | I16: =IFERROR(_xlfn.IFS(D16="NO EXISTE DOCUMENTACIÓN, NI MÉTODOS. ORGANIZACIÓN EMPÍRICA. CERO CAPACIDAD DE REACCIÓN",1,E16="EXISTEN DOCUMENTOS. HAY MÉTODOS SIN RIGUROSIDAD. NO HAY PROYECTO PDP. HAY UN DPD. NIVEL MÍNIMO DE SEGURIDAD. BAJA CAPACIDAD DE IDENTIFICAR Y RESTAURAR BRECHAS",2,F16="PROYECTO PDP EN FASE INICIAL PANSI. HAY DPD. HAY APOYO POR EL RTD. NIVEL MÍNIMO DESEADO DE SEGURIDAD. VULNERABILIDADES IDENTIFICADAS Y ATENDIDAS",3,G16="SG-PDP VALIDADO Y EN PRIMER TRIMESTE DE OPERACIÓN. NIVEL DE SEGURIDAD ADECUADO",4),0) -> 0
C17: PLAN DE SIMULACROS Debe existir esta documentación: (EFICACIA Y EFICIENCIA DE CONTROLES Y MEDIDAS DEL SG-PDP) | I17: =IFERROR(_xlfn.IFS(D17="NO EXISTE DOCUMENTACIÓN, NI MÉTODOS. ORGANIZACIÓN EMPÍRICA. CERO CAPACIDAD DE REACCIÓN",1,E17="EXISTEN DOCUMENTOS. HAY MÉTODOS SIN RIGUROSIDAD. NO HAY PROYECTO PDP. HAY UN DPD. NIVEL MÍNIMO DE SEGURIDAD. BAJA CAPACIDAD DE IDENTIFICAR Y RESTAURAR BRECHAS",2,F17="PROYECTO PDP EN FASE INICIAL PANSI. HAY DPD. HAY APOYO POR EL RTD. NIVEL MÍNIMO DESEADO DE SEGURIDAD. VULNERABILIDADES IDENTIFICADAS Y ATENDIDAS",3,G17="SG-PDP VALIDADO Y EN PRIMER TRIMESTE DE OPERACIÓN. NIVEL DE SEGURIDAD ADECUADO",4),0) -> 0
C18: SIMULACROS 3ras PARTES Debe existir esta documentación: (EFICACIA Y EFICIENCIA DE CONTROLES Y MEDIDAS 3ras PARTES) | I18: =IFERROR(_xlfn.IFS(D18="NO EXISTE DOCUMENTACIÓN, NI MÉTODOS. ORGANIZACIÓN EMPÍRICA. CERO CAPACIDAD DE REACCIÓN",1,E18="EXISTEN DOCUMENTOS. HAY MÉTODOS SIN RIGUROSIDAD. NO HAY PROYECTO PDP. HAY UN DPD. NIVEL MÍNIMO DE SEGURIDAD. BAJA CAPACIDAD DE IDENTIFICAR Y RESTAURAR BRECHAS",2,F18="PROYECTO PDP EN FASE INICIAL PANSI. HAY DPD. HAY APOYO POR EL RTD. NIVEL MÍNIMO DESEADO DE SEGURIDAD. VULNERABILIDADES IDENTIFICADAS Y ATENDIDAS",3,G18="SG-PDP VALIDADO Y EN PRIMER TRIMESTE DE OPERACIÓN. NIVEL DE SEGURIDAD ADECUADO",4),0) -> 0
H19: ESTADO DE LA TÉCNICA | I19: =AVERAGEIF(I9:I18,"<>0") -> #DIV/0!
D22: ADECUACIÓN DEL NIVEL DE SEGURIDAD (PANSI) ÁREA: ADMINISTRATIVAS OBLIGACIÓN LOPDP:2021, ARTÍCULO 47.6 | I22: PANSI | K22: =AVERAGEIF(I29:I38,"<>0") -> #DIV/0!
K25: REQUISITO ARTÍCULO 22.2 -RESOLUCIÓN 2025-0028-R (GARANTÍA DE INDEPENDENCIA PARA DPO) | W25: ESTATUS DEL COMPROMISO DE APLICABILIDAD
D26: CAÓTICO | E26: PSEUDO - PROFESIONAL | G26: PROFESIONAL
D27: 1 | E27: MEDIO BAJO 2 | F27: MEDIO ALTO 3 | G27: 4 | H27: ACCIONES MITIGADORAS | K27: RECURSOS NECESARIO | Q27: COMPROMISOS DE APLICABILIDAD | W27: CUMPLIDO | X27: DEMORADO | Y27: EN PROCESO
D28: DOCUMENTACIÓN INEXISTENTE | E28: DOCUMENTACIÓN SIN PDP INCLUIDO | F28: GRC DOCUMENTADO CON PDP INCLUIDO. PANSI FASE 1 | G28: SG-PDP VALIDADO Y EN PRIMER TRIMESTRE OPERATIVO | H28: MEDIDAS, HERRAMIENTAS Y CONTROLES para elevar el nivel del estado de la técnica | K28: HUMANO | L28: TECNOLOGÍCO | M28: FINANCIERO | N28: TIEMPO | O28: INFRAESTRUCTURA | Q28: FECHA PROBABLE INICIO | R28: INVERSIÓN ESTIMADA HORAS - HOMBRE | S28: INVERSIÓN ESTIMADA DINERO | T28: COMENTARIOS
C29: SANCIONES Y RECOMPENSAS Debe existir esta documentación: (INDICADORES DE EFICIENCIA Y EFICACIA DEL ESQUEMA) | I29: =IFERROR(_xlfn.IFS(D29="NO EXISTE DOCUMENTACIÓN, NI MÉTODOS. ORGANIZACIÓN EMPÍRICA. CERO CAPACIDAD DE REACCIÓN",1,E29="EXISTEN DOCUMENTOS. HAY MÉTODOS SIN RIGUROSIDAD. NO HAY PROYECTO PDP. HAY UN DPD. NIVEL MÍNIMO DE SEGURIDAD. BAJA CAPACIDAD DE IDENTIFICAR Y RESTAURAR BRECHAS",2,F29="PROYECTO PDP EN FASE INICIAL PANSI. HAY DPD. HAY APOYO POR EL RTD. NIVEL MÍNIMO DESEADO DE SEGURIDAD. VULNERABILIDADES IDENTIFICADAS Y ATENDIDAS",3,G29="SG-PDP VALIDADO Y EN PRIMER TRIMESTE DE OPERACIÓN. NIVEL DE SEGURIDAD ADECUADO",4),0) -> 0 | K29: X | M29: X | N29: X | Q29: DESCRITO EN COMENTARIOS | R29: DESCRITO EN COMENTARIOS | S29: DESCRITO EN COMENTARIOS
B30: VULNERABILIDADES ADMINISTRATIVAS | C30: GESTIÓN DEL TALENTO Debe existir esta documentación: (INDICADORES COMPETENCIA Y CONSCIENCIA) | I30: =IFERROR(_xlfn.IFS(D30="NO EXISTE DOCUMENTACIÓN, NI MÉTODOS. ORGANIZACIÓN EMPÍRICA. CERO CAPACIDAD DE REACCIÓN",1,E30="EXISTEN DOCUMENTOS. HAY MÉTODOS SIN RIGUROSIDAD. NO HAY PROYECTO PDP. HAY UN DPD. NIVEL MÍNIMO DE SEGURIDAD. BAJA CAPACIDAD DE IDENTIFICAR Y RESTAURAR BRECHAS",2,F30="PROYECTO PDP EN FASE INICIAL PANSI. HAY DPD. HAY APOYO POR EL RTD. NIVEL MÍNIMO DESEADO DE SEGURIDAD. VULNERABILIDADES IDENTIFICADAS Y ATENDIDAS",3,G30="SG-PDP VALIDADO Y EN PRIMER TRIMESTE DE OPERACIÓN. NIVEL DE SEGURIDAD ADECUADO",4),0) -> 0 | K30: X | M30: X | N30: X | Q30: DESCRITO EN COMENTARIOS | R30: DESCRITO EN COMENTARIOS | S30: DESCRITO EN COMENTARIOS
C31: GESTIÓN INGRESOS Y DESVINCULACIÓN Debe existir esta documentación: (INDICADORES DE EFICIENCIA Y EFICACIA DEL ESQUEMA) | I31: =IFERROR(_xlfn.IFS(D31="NO EXISTE DOCUMENTACIÓN, NI MÉTODOS. ORGANIZACIÓN EMPÍRICA. CERO CAPACIDAD DE REACCIÓN",1,E31="EXISTEN DOCUMENTOS. HAY MÉTODOS SIN RIGUROSIDAD. NO HAY PROYECTO PDP. HAY UN DPD. NIVEL MÍNIMO DE SEGURIDAD. BAJA CAPACIDAD DE IDENTIFICAR Y RESTAURAR BRECHAS",2,F31="PROYECTO PDP EN FASE INICIAL PANSI. HAY DPD. HAY APOYO POR EL RTD. NIVEL MÍNIMO DESEADO DE SEGURIDAD. VULNERABILIDADES IDENTIFICADAS Y ATENDIDAS",3,G31="SG-PDP VALIDADO Y EN PRIMER TRIMESTE DE OPERACIÓN. NIVEL DE SEGURIDAD ADECUADO",4),0) -> 0 | K31: X | M31: X | N31: X | Q31: DESCRITO EN COMENTARIOS | R31: DESCRITO EN COMENTARIOS | S31: DESCRITO EN COMENTARIOS
C32: ESTRUCTURA DOCUMENTAL Debe existir esta documentación: (ESQUEMA DE CONTROL DE DOCUMENTOS, LISTA MAESTRA REGISTROS, MÉTRICAS Y KPI's) | I32: =IFERROR(_xlfn.IFS(D32="NO EXISTE DOCUMENTACIÓN, NI MÉTODOS. ORGANIZACIÓN EMPÍRICA. CERO CAPACIDAD DE REACCIÓN",1,E32="EXISTEN DOCUMENTOS. HAY MÉTODOS SIN RIGUROSIDAD. NO HAY PROYECTO PDP. HAY UN DPD. NIVEL MÍNIMO DE SEGURIDAD. BAJA CAPACIDAD DE IDENTIFICAR Y RESTAURAR BRECHAS",2,F32="PROYECTO PDP EN FASE INICIAL PANSI. HAY DPD. HAY APOYO POR EL RTD. NIVEL MÍNIMO DESEADO DE SEGURIDAD. VULNERABILIDADES IDENTIFICADAS Y ATENDIDAS",3,G32="SG-PDP VALIDADO Y EN PRIMER TRIMESTE DE OPERACIÓN. NIVEL DE SEGURIDAD ADECUADO",4),0) -> 0 | K32: X | M32: X | N32: X | Q32: DESCRITO EN COMENTARIOS | R32: DESCRITO EN COMENTARIOS | S32: DESCRITO EN COMENTARIOS
C33: ESQUEMA DE PROTECCIÓN DE DATOS - INFORMACIÓN Debe existir esta documentación: (CICLO DE VIDA DE DATOS, MAPA DE PROCESOS, ESTACIONES AUTOGESTIONADAS, OTRO) | I33: =IFERROR(_xlfn.IFS(D33="NO EXISTE DOCUMENTACIÓN, NI MÉTODOS. ORGANIZACIÓN EMPÍRICA. CERO CAPACIDAD DE REACCIÓN",1,E33="EXISTEN DOCUMENTOS. HAY MÉTODOS SIN RIGUROSIDAD. NO HAY PROYECTO PDP. HAY UN DPD. NIVEL MÍNIMO DE SEGURIDAD. BAJA CAPACIDAD DE IDENTIFICAR Y RESTAURAR BRECHAS",2,F33="PROYECTO PDP EN FASE INICIAL PANSI. HAY DPD. HAY APOYO POR EL RTD. NIVEL MÍNIMO DESEADO DE SEGURIDAD. VULNERABILIDADES IDENTIFICADAS Y ATENDIDAS",3,G33="SG-PDP VALIDADO Y EN PRIMER TRIMESTE DE OPERACIÓN. NIVEL DE SEGURIDAD ADECUADO",4),0) -> 0 | K33: X | M33: X | N33: X | Q33: DESCRITO EN COMENTARIOS | R33: DESCRITO EN COMENTARIOS | S33: DESCRITO EN COMENTARIOS
C34: GESTIÓN DE INDICADORES Debe existir esta documentación: (MEJORA CONTINUA, RESILIENCIA y EJERCICIO DE DERECHOS, OTROS PDP) | I34: =IFERROR(_xlfn.IFS(D34="NO EXISTE DOCUMENTACIÓN, NI MÉTODOS. ORGANIZACIÓN EMPÍRICA. CERO CAPACIDAD DE REACCIÓN",1,E34="EXISTEN DOCUMENTOS. HAY MÉTODOS SIN RIGUROSIDAD. NO HAY PROYECTO PDP. HAY UN DPD. NIVEL MÍNIMO DE SEGURIDAD. BAJA CAPACIDAD DE IDENTIFICAR Y RESTAURAR BRECHAS",2,F34="PROYECTO PDP EN FASE INICIAL PANSI. HAY DPD. HAY APOYO POR EL RTD. NIVEL MÍNIMO DESEADO DE SEGURIDAD. VULNERABILIDADES IDENTIFICADAS Y ATENDIDAS",3,G34="SG-PDP VALIDADO Y EN PRIMER TRIMESTE DE OPERACIÓN. NIVEL DE SEGURIDAD ADECUADO",4),0) -> 0 | K34: X | M34: X | N34: X | Q34: DESCRITO EN COMENTARIOS | R34: DESCRITO EN COMENTARIOS | S34: DESCRITO EN COMENTARIOS
C35: PLAN AUDITORÍAS INTERNAS Debe existir esta documentación: (AUDITORÍAS AL SG 1ra y 2da PARTE, EVIDENCIA DE MEJORA CONTINUA) | I35: =IFERROR(_xlfn.IFS(D35="NO EXISTE DOCUMENTACIÓN, NI MÉTODOS. ORGANIZACIÓN EMPÍRICA. CERO CAPACIDAD DE REACCIÓN",1,E35="EXISTEN DOCUMENTOS. HAY MÉTODOS SIN RIGUROSIDAD. NO HAY PROYECTO PDP. HAY UN DPD. NIVEL MÍNIMO DE SEGURIDAD. BAJA CAPACIDAD DE IDENTIFICAR Y RESTAURAR BRECHAS",2,F35="PROYECTO PDP EN FASE INICIAL PANSI. HAY DPD. HAY APOYO POR EL RTD. NIVEL MÍNIMO DESEADO DE SEGURIDAD. VULNERABILIDADES IDENTIFICADAS Y ATENDIDAS",3,G35="SG-PDP VALIDADO Y EN PRIMER TRIMESTE DE OPERACIÓN. NIVEL DE SEGURIDAD ADECUADO",4),0) -> 0 | K35: X | M35: X | N35: X | Q35: DESCRITO EN COMENTARIOS | R35: DESCRITO EN COMENTARIOS | S35: DESCRITO EN COMENTARIOS
C36: PLAN AUDITOÍAS 3ras PARTES Debe existir esta documentación: (AUDITORÍAS 2da PARTE, A ENCARGADOS Y 3ros) | I36: =IFERROR(_xlfn.IFS(D36="NO EXISTE DOCUMENTACIÓN, NI MÉTODOS. ORGANIZACIÓN EMPÍRICA. CERO CAPACIDAD DE REACCIÓN",1,E36="EXISTEN DOCUMENTOS. HAY MÉTODOS SIN RIGUROSIDAD. NO HAY PROYECTO PDP. HAY UN DPD. NIVEL MÍNIMO DE SEGURIDAD. BAJA CAPACIDAD DE IDENTIFICAR Y RESTAURAR BRECHAS",2,F36="PROYECTO PDP EN FASE INICIAL PANSI. HAY DPD. HAY APOYO POR EL RTD. NIVEL MÍNIMO DESEADO DE SEGURIDAD. VULNERABILIDADES IDENTIFICADAS Y ATENDIDAS",3,G36="SG-PDP VALIDADO Y EN PRIMER TRIMESTE DE OPERACIÓN. NIVEL DE SEGURIDAD ADECUADO",4),0) -> 0 | K36: X | M36: X | N36: X | Q36: DESCRITO EN COMENTARIOS | R36: DESCRITO EN COMENTARIOS | S36: DESCRITO EN COMENTARIOS
C37: PLAN DE SIMULACROS Debe existir esta documentación: (EFICACIA Y EFICIENCIA DE CONTROLES Y MEDIDAS DEL SG-PDP) | I37: =IFERROR(_xlfn.IFS(D37="NO EXISTE DOCUMENTACIÓN, NI MÉTODOS. ORGANIZACIÓN EMPÍRICA. CERO CAPACIDAD DE REACCIÓN",1,E37="EXISTEN DOCUMENTOS. HAY MÉTODOS SIN RIGUROSIDAD. NO HAY PROYECTO PDP. HAY UN DPD. NIVEL MÍNIMO DE SEGURIDAD. BAJA CAPACIDAD DE IDENTIFICAR Y RESTAURAR BRECHAS",2,F37="PROYECTO PDP EN FASE INICIAL PANSI. HAY DPD. HAY APOYO POR EL RTD. NIVEL MÍNIMO DESEADO DE SEGURIDAD. VULNERABILIDADES IDENTIFICADAS Y ATENDIDAS",3,G37="SG-PDP VALIDADO Y EN PRIMER TRIMESTE DE OPERACIÓN. NIVEL DE SEGURIDAD ADECUADO",4),0) -> 0 | K37: X | M37: X | N37: X | Q37: DESCRITO EN COMENTARIOS | R37: DESCRITO EN COMENTARIOS | S37: DESCRITO EN COMENTARIOS
C38: SIMULACROS 3ras PARTES Debe existir esta documentación: (EFICACIA Y EFICIENCIA DE CONTROLES Y MEDIDAS 3ras PARTES) | I38: =IFERROR(_xlfn.IFS(D38="NO EXISTE DOCUMENTACIÓN, NI MÉTODOS. ORGANIZACIÓN EMPÍRICA. CERO CAPACIDAD DE REACCIÓN",1,E38="EXISTEN DOCUMENTOS. HAY MÉTODOS SIN RIGUROSIDAD. NO HAY PROYECTO PDP. HAY UN DPD. NIVEL MÍNIMO DE SEGURIDAD. BAJA CAPACIDAD DE IDENTIFICAR Y RESTAURAR BRECHAS",2,F38="PROYECTO PDP EN FASE INICIAL PANSI. HAY DPD. HAY APOYO POR EL RTD. NIVEL MÍNIMO DESEADO DE SEGURIDAD. VULNERABILIDADES IDENTIFICADAS Y ATENDIDAS",3,G38="SG-PDP VALIDADO Y EN PRIMER TRIMESTE DE OPERACIÓN. NIVEL DE SEGURIDAD ADECUADO",4),0) -> 0 | K38: X | M38: X | N38: X | Q38: DESCRITO EN COMENTARIOS | R38: DESCRITO EN COMENTARIOS | S38: DESCRITO EN COMENTARIOS
I39: =AVERAGEIF(I29:I38,"<>0") -> #DIV/0!

Sheet JURÍDICAS EET + PANSI
D2: EVALUACIÓN DEL ESTADO DE LA TECNICA ÁREA: JURÍDICAS REQUISITO LOPDP:2021, ARTÍCULO 10.j
D6: CAÓTICO | E6: PSEUDO - PROFESIONAL | G6: PROFESIONAL
D7: 1 | E7: MEDIO BAJO 2 | F7: MEDIO ALTO 3 | G7: 4 | H7: COMENTARIOS
D8: DOCUMENTACIÓN INEXISTENTE | E8: DOCUMENTACIÓN SIN PDP INCLUIDO | F8: GRC DOCUMENTADO CON PDP INCLUIDO. PANSI FASE 1 | G8: SG-PDP VALIDADO Y EN PRIMER TRIMESTRE OPERATIVO
C9: COMUNICADOS Debe existir esta documentación: (AVISOS DE PRIVACIDAD, COMUNICACI[ON PREVIA A LA RECOGIDA DE DATOS, COMUNICADOS AL ECOSISTEMA PDP) | I9: =IFERROR(_xlfn.IFS(D9="NO EXISTE DOCUMENTACIÓN, NI MÉTODOS. ORGANIZACIÓN EMPÍRICA. CERO CAPACIDAD DE REACCIÓN",1,E9="EXISTEN DOCUMENTOS. HAY MÉTODOS SIN RIGUROSIDAD. NO HAY PROYECTO PDP. HAY UN DPD. NIVEL MÍNIMO DE SEGURIDAD. BAJA CAPACIDAD DE IDENTIFICAR Y RESTAURAR BRECHAS",2,F9="PROYECTO PDP EN FASE INICIAL PANSI. HAY DPD. HAY APOYO POR EL RTD. NIVEL MÍNIMO DESEADO DE SEGURIDAD. VULNERABILIDADES IDENTIFICADAS Y ATENDIDAS",3,G9="SG-PDP VALIDADO Y EN PRIMER TRIMESTE DE OPERACIÓN. NIVEL DE SEGURIDAD ADECUADO",4),0) -> 0
B10: VULNERABILIDADES JURÍDICAS | C10: CONTRATOS Debe existir esta documentación: (DEBEN INCLUIR REQUISITOS DE CLÁUSULAS R-006-2025 y R-005-2026) | I10: =IFERROR(_xlfn.IFS(D10="NO EXISTE DOCUMENTACIÓN, NI MÉTODOS. ORGANIZACIÓN EMPÍRICA. CERO CAPACIDAD DE REACCIÓN",1,E10="EXISTEN DOCUMENTOS. HAY MÉTODOS SIN RIGUROSIDAD. NO HAY PROYECTO PDP. HAY UN DPD. NIVEL MÍNIMO DE SEGURIDAD. BAJA CAPACIDAD DE IDENTIFICAR Y RESTAURAR BRECHAS",2,F10="PROYECTO PDP EN FASE INICIAL PANSI. HAY DPD. HAY APOYO POR EL RTD. NIVEL MÍNIMO DESEADO DE SEGURIDAD. VULNERABILIDADES IDENTIFICADAS Y ATENDIDAS",3,G10="SG-PDP VALIDADO Y EN PRIMER TRIMESTE DE OPERACIÓN. NIVEL DE SEGURIDAD ADECUADO",4),0) -> 0
C11: RESPUESTAS y NOTIFICACIONES Debe existir esta documentación: (EJERCICIO DE DERECHOS, NOTIFICACIÓN A ENTES DE CONTROL, TITULARES, CADENA 3ras PARTES) | I11: =IFERROR(_xlfn.IFS(D11="NO EXISTE DOCUMENTACIÓN, NI MÉTODOS. ORGANIZACIÓN EMPÍRICA. CERO CAPACIDAD DE REACCIÓN",1,E11="EXISTEN DOCUMENTOS. HAY MÉTODOS SIN RIGUROSIDAD. NO HAY PROYECTO PDP. HAY UN DPD. NIVEL MÍNIMO DE SEGURIDAD. BAJA CAPACIDAD DE IDENTIFICAR Y RESTAURAR BRECHAS",2,F11="PROYECTO PDP EN FASE INICIAL PANSI. HAY DPD. HAY APOYO POR EL RTD. NIVEL MÍNIMO DESEADO DE SEGURIDAD. VULNERABILIDADES IDENTIFICADAS Y ATENDIDAS",3,G11="SG-PDP VALIDADO Y EN PRIMER TRIMESTE DE OPERACIÓN. NIVEL DE SEGURIDAD ADECUADO",4),0) -> 0
C12: REGISTROS ANTE SPDP Debe existir esta documentación: (EVALUACIONES DE IMPACTO OBLIGATORIAS, DELEGADO DE PROTECCIÓN, BASES DE DATOS, RAT-MTGE) | I12: =IFERROR(_xlfn.IFS(D12="NO EXISTE DOCUMENTACIÓN, NI MÉTODOS. ORGANIZACIÓN EMPÍRICA. CERO CAPACIDAD DE REACCIÓN",1,E12="EXISTEN DOCUMENTOS. HAY MÉTODOS SIN RIGUROSIDAD. NO HAY PROYECTO PDP. HAY UN DPD. NIVEL MÍNIMO DE SEGURIDAD. BAJA CAPACIDAD DE IDENTIFICAR Y RESTAURAR BRECHAS",2,F12="PROYECTO PDP EN FASE INICIAL PANSI. HAY DPD. HAY APOYO POR EL RTD. NIVEL MÍNIMO DESEADO DE SEGURIDAD. VULNERABILIDADES IDENTIFICADAS Y ATENDIDAS",3,G12="SG-PDP VALIDADO Y EN PRIMER TRIMESTE DE OPERACIÓN. NIVEL DE SEGURIDAD ADECUADO",4),0) -> 0
C13: EVALUACIONES TÉCNICO- JURÍDICAS Debe existir esta documentación: (EVALUACIONES DE IMPACTO, EVALUACIONES DE INTERÉS LEGÍTIMO, EVALUACIONES TRANSFERENCIAS INTERNACIONALES) | I13: =IFERROR(_xlfn.IFS(D13="NO EXISTE DOCUMENTACIÓN, NI MÉTODOS. ORGANIZACIÓN EMPÍRICA. CERO CAPACIDAD DE REACCIÓN",1,E13="EXISTEN DOCUMENTOS. HAY MÉTODOS SIN RIGUROSIDAD. NO HAY PROYECTO PDP. HAY UN DPD. NIVEL MÍNIMO DE SEGURIDAD. BAJA CAPACIDAD DE IDENTIFICAR Y RESTAURAR BRECHAS",2,F13="PROYECTO PDP EN FASE INICIAL PANSI. HAY DPD. HAY APOYO POR EL RTD. NIVEL MÍNIMO DESEADO DE SEGURIDAD. VULNERABILIDADES IDENTIFICADAS Y ATENDIDAS",3,G13="SG-PDP VALIDADO Y EN PRIMER TRIMESTE DE OPERACIÓN. NIVEL DE SEGURIDAD ADECUADO",4),0) -> 0
C14: DOCUMENTACIÓN GRC Debe existir esta documentación: (REVISIÓN DE LAS POLÍTICAS, ESQUEMA SANCIONES Y RECOMPENSAS, OTROS) | I14: =IFERROR(_xlfn.IFS(D14="NO EXISTE DOCUMENTACIÓN, NI MÉTODOS. ORGANIZACIÓN EMPÍRICA. CERO CAPACIDAD DE REACCIÓN",1,E14="EXISTEN DOCUMENTOS. HAY MÉTODOS SIN RIGUROSIDAD. NO HAY PROYECTO PDP. HAY UN DPD. NIVEL MÍNIMO DE SEGURIDAD. BAJA CAPACIDAD DE IDENTIFICAR Y RESTAURAR BRECHAS",2,F14="PROYECTO PDP EN FASE INICIAL PANSI. HAY DPD. HAY APOYO POR EL RTD. NIVEL MÍNIMO DESEADO DE SEGURIDAD. VULNERABILIDADES IDENTIFICADAS Y ATENDIDAS",3,G14="SG-PDP VALIDADO Y EN PRIMER TRIMESTE DE OPERACIÓN. NIVEL DE SEGURIDAD ADECUADO",4),0) -> 0
C15: EJERCICIO DE DERECHOS Y BRECHAS Debe existir esta documentación: (REVISIÓN DOCUMENTADA DE LAS RESPUESTAS AUTORIZADAS POR EL ÁREA JURÍDICA) | I15: =IFERROR(_xlfn.IFS(D15="NO EXISTE DOCUMENTACIÓN, NI MÉTODOS. ORGANIZACIÓN EMPÍRICA. CERO CAPACIDAD DE REACCIÓN",1,E15="EXISTEN DOCUMENTOS. HAY MÉTODOS SIN RIGUROSIDAD. NO HAY PROYECTO PDP. HAY UN DPD. NIVEL MÍNIMO DE SEGURIDAD. BAJA CAPACIDAD DE IDENTIFICAR Y RESTAURAR BRECHAS",2,F15="PROYECTO PDP EN FASE INICIAL PANSI. HAY DPD. HAY APOYO POR EL RTD. NIVEL MÍNIMO DESEADO DE SEGURIDAD. VULNERABILIDADES IDENTIFICADAS Y ATENDIDAS",3,G15="SG-PDP VALIDADO Y EN PRIMER TRIMESTE DE OPERACIÓN. NIVEL DE SEGURIDAD ADECUADO",4),0) -> 0
C16: GARANTIAS ADECUADAS Debe existir esta documentación: (ASEGURARSE DE CUMPLIR CON EL PROCEDIMIENTO QUE ESTABLECE LA RESOLUCIÓN R-004-2026) | I16: =IFERROR(_xlfn.IFS(D16="NO EXISTE DOCUMENTACIÓN, NI MÉTODOS. ORGANIZACIÓN EMPÍRICA. CERO CAPACIDAD DE REACCIÓN",1,E16="EXISTEN DOCUMENTOS. HAY MÉTODOS SIN RIGUROSIDAD. NO HAY PROYECTO PDP. HAY UN DPD. NIVEL MÍNIMO DE SEGURIDAD. BAJA CAPACIDAD DE IDENTIFICAR Y RESTAURAR BRECHAS",2,F16="PROYECTO PDP EN FASE INICIAL PANSI. HAY DPD. HAY APOYO POR EL RTD. NIVEL MÍNIMO DESEADO DE SEGURIDAD. VULNERABILIDADES IDENTIFICADAS Y ATENDIDAS",3,G16="SG-PDP VALIDADO Y EN PRIMER TRIMESTE DE OPERACIÓN. NIVEL DE SEGURIDAD ADECUADO",4),0) -> 0
C17: NORMAS CORPORATIVAS VINCULANTES Debe existir esta documentación: (APLICA PARA ORGANIZACIONES QUE COMUNIQUEN DATOS PERSONALES A SUCURSALES EN OTROS PAISES) | I17: =IFERROR(_xlfn.IFS(D17="NO EXISTE DOCUMENTACIÓN, NI MÉTODOS. ORGANIZACIÓN EMPÍRICA. CERO CAPACIDAD DE REACCIÓN",1,E17="EXISTEN DOCUMENTOS. HAY MÉTODOS SIN RIGUROSIDAD. NO HAY PROYECTO PDP. HAY UN DPD. NIVEL MÍNIMO DE SEGURIDAD. BAJA CAPACIDAD DE IDENTIFICAR Y RESTAURAR BRECHAS",2,F17="PROYECTO PDP EN FASE INICIAL PANSI. HAY DPD. HAY APOYO POR EL RTD. NIVEL MÍNIMO DESEADO DE SEGURIDAD. VULNERABILIDADES IDENTIFICADAS Y ATENDIDAS",3,G17="SG-PDP VALIDADO Y EN PRIMER TRIMESTE DE OPERACIÓN. NIVEL DE SEGURIDAD ADECUADO",4),0) -> 0
H18: ESTADO DE LA TÉCNICA | I18: =AVERAGEIF(I9:I17,"<>0") -> #DIV/0!
D20: ADECUACIÓN DEL NIVEL DE SEGURIDAD (PANSI) ÁREA: JURÍDICAS OBLIGACIÓN LOPDP:2021, ARTÍCULO 47.6
K23: REQUISITO ARTÍCULO 22.2 -RESOLUCIÓN 2025-0028-R (GARANTÍA DE INDEPENDENCIA PARA DPO) | W23: ESTATUS DEL COMPROMISO DE APLICABILIDAD
D24: CAÓTICO | E24: PSEUDO - PROFESIONAL | G24: PROFESIONAL
D25: 1 | E25: MEDIO BAJO 2 | F25: MEDIO ALTO 3 | G25: 4 | H25: ACCIONES MITIGADORAS | K25: RECURSOS NECESARIO | Q25: COMPROMISOS DE APLICABILIDAD | W25: CUMPLIDO | X25: DEMORADO | Y25: EN PROCESO
D26: DOCUMENTACIÓN INEXISTENTE | E26: DOCUMENTACIÓN SIN PDP INCLUIDO | F26: GRC DOCUMENTADO CON PDP INCLUIDO. PANSI FASE 1 | G26: SG-PDP VALIDADO Y EN PRIMER TRIMESTRE OPERATIVO | H26: MEDIDAS, HERRAMIENTAS Y CONTROLES para elevar el nivel del estado de la técnica | K26: HUMANO | L26: TECNOLOGÍCO | M26: FINANCIERO | N26: TIEMPO | O26: INFRAESTRUCTURA | Q26: FECHA PROBABLE INICIO | R26: INVERSIÓN ESTIMADA HORAS - HOMBRE | S26: INVERSIÓN ESTIMADA DINERO | T26: COMENTARIOS
C27: COMUNICADOS Debe existir esta documentación: (AVISOS DE PRIVACIDAD, COMUNICACI[ON PREVIA A LA RECOGIDA DE DATOS, COMUNICADOS AL ECOSISTEMA PDP) | I27: =IFERROR(_xlfn.IFS(D27="NO EXISTE DOCUMENTACIÓN, NI MÉTODOS. ORGANIZACIÓN EMPÍRICA. CERO CAPACIDAD DE REACCIÓN",1,E27="EXISTEN DOCUMENTOS. HAY MÉTODOS SIN RIGUROSIDAD. NO HAY PROYECTO PDP. HAY UN DPD. NIVEL MÍNIMO DE SEGURIDAD. BAJA CAPACIDAD DE IDENTIFICAR Y RESTAURAR BRECHAS",2,F27="PROYECTO PDP EN FASE INICIAL PANSI. HAY DPD. HAY APOYO POR EL RTD. NIVEL MÍNIMO DESEADO DE SEGURIDAD. VULNERABILIDADES IDENTIFICADAS Y ATENDIDAS",3,G27="SG-PDP VALIDADO Y EN PRIMER TRIMESTE DE OPERACIÓN. NIVEL DE SEGURIDAD ADECUADO",4),0) -> 0 | K27: X | M27: X | N27: X | Q27: DESCRITO EN COMENTARIOS | R27: DESCRITO EN COMENTARIOS | S27: DESCRITO EN COMENTARIOS
B28: VULNERABILIDADES JURÍDICAS | C28: CONTRATOS Debe existir esta documentación: (DEBEN INCLUIR REQUISITOS DE CLÁUSULAS R-006-2025 y R-005-2026) | I28: =IFERROR(_xlfn.IFS(D28="NO EXISTE DOCUMENTACIÓN, NI MÉTODOS. ORGANIZACIÓN EMPÍRICA. CERO CAPACIDAD DE REACCIÓN",1,E28="EXISTEN DOCUMENTOS. HAY MÉTODOS SIN RIGUROSIDAD. NO HAY PROYECTO PDP. HAY UN DPD. NIVEL MÍNIMO DE SEGURIDAD. BAJA CAPACIDAD DE IDENTIFICAR Y RESTAURAR BRECHAS",2,F28="PROYECTO PDP EN FASE INICIAL PANSI. HAY DPD. HAY APOYO POR EL RTD. NIVEL MÍNIMO DESEADO DE SEGURIDAD. VULNERABILIDADES IDENTIFICADAS Y ATENDIDAS",3,G28="SG-PDP VALIDADO Y EN PRIMER TRIMESTE DE OPERACIÓN. NIVEL DE SEGURIDAD ADECUADO",4),0) -> 0 | K28: X | M28: X | N28: X | Q28: DESCRITO EN COMENTARIOS | R28: DESCRITO EN COMENTARIOS | S28: DESCRITO EN COMENTARIOS
C29: RESPUESTAS y NOTIFICACIONES Debe existir esta documentación: (EJERCICIO DE DERECHOS, NOTIFICACIÓN A ENTES DE CONTROL, TITULARES, CADENA 3ras PARTES) | I29: =IFERROR(_xlfn.IFS(D29="NO EXISTE DOCUMENTACIÓN, NI MÉTODOS. ORGANIZACIÓN EMPÍRICA. CERO CAPACIDAD DE REACCIÓN",1,E29="EXISTEN DOCUMENTOS. HAY MÉTODOS SIN RIGUROSIDAD. NO HAY PROYECTO PDP. HAY UN DPD. NIVEL MÍNIMO DE SEGURIDAD. BAJA CAPACIDAD DE IDENTIFICAR Y RESTAURAR BRECHAS",2,F29="PROYECTO PDP EN FASE INICIAL PANSI. HAY DPD. HAY APOYO POR EL RTD. NIVEL MÍNIMO DESEADO DE SEGURIDAD. VULNERABILIDADES IDENTIFICADAS Y ATENDIDAS",3,G29="SG-PDP VALIDADO Y EN PRIMER TRIMESTE DE OPERACIÓN. NIVEL DE SEGURIDAD ADECUADO",4),0) -> 0 | K29: X | M29: X | N29: X | Q29: DESCRITO EN COMENTARIOS | R29: DESCRITO EN COMENTARIOS | S29: DESCRITO EN COMENTARIOS
C30: REGISTROS ANTE SPDP Debe existir esta documentación: (EVALUACIONES DE IMPACTO OBLIGATORIAS, DELEGADO DE PROTECCIÓN, BASES DE DATOS, RAT-MTGE) | I30: =IFERROR(_xlfn.IFS(D30="NO EXISTE DOCUMENTACIÓN, NI MÉTODOS. ORGANIZACIÓN EMPÍRICA. CERO CAPACIDAD DE REACCIÓN",1,E30="EXISTEN DOCUMENTOS. HAY MÉTODOS SIN RIGUROSIDAD. NO HAY PROYECTO PDP. HAY UN DPD. NIVEL MÍNIMO DE SEGURIDAD. BAJA CAPACIDAD DE IDENTIFICAR Y RESTAURAR BRECHAS",2,F30="PROYECTO PDP EN FASE INICIAL PANSI. HAY DPD. HAY APOYO POR EL RTD. NIVEL MÍNIMO DESEADO DE SEGURIDAD. VULNERABILIDADES IDENTIFICADAS Y ATENDIDAS",3,G30="SG-PDP VALIDADO Y EN PRIMER TRIMESTE DE OPERACIÓN. NIVEL DE SEGURIDAD ADECUADO",4),0) -> 0 | K30: X | M30: X | N30: X | Q30: DESCRITO EN COMENTARIOS | R30: DESCRITO EN COMENTARIOS | S30: DESCRITO EN COMENTARIOS
C31: EVALUACIONES TÉCNICO- JURÍDICAS Debe existir esta documentación: (EVALUACIONES DE IMPACTO, EVALUACIONES DE INTERÉS LEGÍTIMO, EVALUACIONES TRANSFERENCIAS INTERNACIONALES) | I31: =IFERROR(_xlfn.IFS(D31="NO EXISTE DOCUMENTACIÓN, NI MÉTODOS. ORGANIZACIÓN EMPÍRICA. CERO CAPACIDAD DE REACCIÓN",1,E31="EXISTEN DOCUMENTOS. HAY MÉTODOS SIN RIGUROSIDAD. NO HAY PROYECTO PDP. HAY UN DPD. NIVEL MÍNIMO DE SEGURIDAD. BAJA CAPACIDAD DE IDENTIFICAR Y RESTAURAR BRECHAS",2,F31="PROYECTO PDP EN FASE INICIAL PANSI. HAY DPD. HAY APOYO POR EL RTD. NIVEL MÍNIMO DESEADO DE SEGURIDAD. VULNERABILIDADES IDENTIFICADAS Y ATENDIDAS",3,G31="SG-PDP VALIDADO Y EN PRIMER TRIMESTE DE OPERACIÓN. NIVEL DE SEGURIDAD ADECUADO",4),0) -> 0 | K31: X | M31: X | N31: X | Q31: DESCRITO EN COMENTARIOS | R31: DESCRITO EN COMENTARIOS | S31: DESCRITO EN COMENTARIOS
C32: DOCUMENTACIÓN GRC Debe existir esta documentación: (REVISIÓN DE LAS POLÍTICAS, ESQUEMA SANCIONES Y RECOMPENSAS, OTROS) | I32: =IFERROR(_xlfn.IFS(D32="NO EXISTE DOCUMENTACIÓN, NI MÉTODOS. ORGANIZACIÓN EMPÍRICA. CERO CAPACIDAD DE REACCIÓN",1,E32="EXISTEN DOCUMENTOS. HAY MÉTODOS SIN RIGUROSIDAD. NO HAY PROYECTO PDP. HAY UN DPD. NIVEL MÍNIMO DE SEGURIDAD. BAJA CAPACIDAD DE IDENTIFICAR Y RESTAURAR BRECHAS",2,F32="PROYECTO PDP EN FASE INICIAL PANSI. HAY DPD. HAY APOYO POR EL RTD. NIVEL MÍNIMO DESEADO DE SEGURIDAD. VULNERABILIDADES IDENTIFICADAS Y ATENDIDAS",3,G32="SG-PDP VALIDADO Y EN PRIMER TRIMESTE DE OPERACIÓN. NIVEL DE SEGURIDAD ADECUADO",4),0) -> 0 | K32: X | M32: X | N32: X | Q32: DESCRITO EN COMENTARIOS | R32: DESCRITO EN COMENTARIOS | S32: DESCRITO EN COMENTARIOS
C33: EJERCICIO DE DERECHOS Y BRECHAS Debe existir esta documentación: (REVISIÓN DOCUMENTADA DE LAS RESPUESTAS AUTORIZADAS POR EL ÁREA JURÍDICA) | I33: =IFERROR(_xlfn.IFS(D33="NO EXISTE DOCUMENTACIÓN, NI MÉTODOS. ORGANIZACIÓN EMPÍRICA. CERO CAPACIDAD DE REACCIÓN",1,E33="EXISTEN DOCUMENTOS. HAY MÉTODOS SIN RIGUROSIDAD. NO HAY PROYECTO PDP. HAY UN DPD. NIVEL MÍNIMO DE SEGURIDAD. BAJA CAPACIDAD DE IDENTIFICAR Y RESTAURAR BRECHAS",2,F33="PROYECTO PDP EN FASE INICIAL PANSI. HAY DPD. HAY APOYO POR EL RTD. NIVEL MÍNIMO DESEADO DE SEGURIDAD. VULNERABILIDADES IDENTIFICADAS Y ATENDIDAS",3,G33="SG-PDP VALIDADO Y EN PRIMER TRIMESTE DE OPERACIÓN. NIVEL DE SEGURIDAD ADECUADO",4),0) -> 0 | K33: X | M33: X | N33: X | Q33: DESCRITO EN COMENTARIOS | R33: DESCRITO EN COMENTARIOS | S33: DESCRITO EN COMENTARIOS
C34: GARANTIAS ADECUADAS Debe existir esta documentación: (ASEGURARSE DE CUMPLIR CON EL PROCEDIMIENTO QUE ESTABLECE LA RESOLUCIÓN R-004-2026) | I34: =IFERROR(_xlfn.IFS(D34="NO EXISTE DOCUMENTACIÓN, NI MÉTODOS. ORGANIZACIÓN EMPÍRICA. CERO CAPACIDAD DE REACCIÓN",1,E34="EXISTEN DOCUMENTOS. HAY MÉTODOS SIN RIGUROSIDAD. NO HAY PROYECTO PDP. HAY UN DPD. NIVEL MÍNIMO DE SEGURIDAD. BAJA CAPACIDAD DE IDENTIFICAR Y RESTAURAR BRECHAS",2,F34="PROYECTO PDP EN FASE INICIAL PANSI. HAY DPD. HAY APOYO POR EL RTD. NIVEL MÍNIMO DESEADO DE SEGURIDAD. VULNERABILIDADES IDENTIFICADAS Y ATENDIDAS",3,G34="SG-PDP VALIDADO Y EN PRIMER TRIMESTE DE OPERACIÓN. NIVEL DE SEGURIDAD ADECUADO",4),0) -> 0 | K34: X | M34: X | N34: X | Q34: DESCRITO EN COMENTARIOS | R34: DESCRITO EN COMENTARIOS | S34: DESCRITO EN COMENTARIOS
C35: NORMAS CORPORATIVAS VINCULANTES Debe existir esta documentación: (APLICA PARA ORGANIZACIONES QUE COMUNIQUEN DATOS PERSONALES A SUCURSALES EN OTROS PAISES) | I35: =IFERROR(_xlfn.IFS(D35="NO EXISTE DOCUMENTACIÓN, NI MÉTODOS. ORGANIZACIÓN EMPÍRICA. CERO CAPACIDAD DE REACCIÓN",1,E35="EXISTEN DOCUMENTOS. HAY MÉTODOS SIN RIGUROSIDAD. NO HAY PROYECTO PDP. HAY UN DPD. NIVEL MÍNIMO DE SEGURIDAD. BAJA CAPACIDAD DE IDENTIFICAR Y RESTAURAR BRECHAS",2,F35="PROYECTO PDP EN FASE INICIAL PANSI. HAY DPD. HAY APOYO POR EL RTD. NIVEL MÍNIMO DESEADO DE SEGURIDAD. VULNERABILIDADES IDENTIFICADAS Y ATENDIDAS",3,G35="SG-PDP VALIDADO Y EN PRIMER TRIMESTE DE OPERACIÓN. NIVEL DE SEGURIDAD ADECUADO",4),0) -> 0 | K35: X | M35: X | N35: X | Q35: DESCRITO EN COMENTARIOS | R35: DESCRITO EN COMENTARIOS | S35: DESCRITO EN COMENTARIOS
I37: =AVERAGEIF(I27:I36,"<>0") -> #DIV/0!

Sheet FÍSICAS - OPER  EET + PANSI
D2: EVALUACIÓN DEL ESTADO DE LA TECNICA ÁREA: FÍSICA-OPERATIVAS REQUISITO LOPDP:2021, ARTÍCULO 10.j
D6: CAÓTICO | E6: PSEUDO - PROFESIONAL | G6: PROFESIONAL
D7: 1 | E7: MEDIO BAJO 2 | F7: MEDIO ALTO 3 | G7: 4 | H7: COMENTARIOS
D8: DOCUMENTACIÓN INEXISTENTE | E8: DOCUMENTACIÓN SIN PDP INCLUIDO | F8: GRC DOCUMENTADO CON PDP INCLUIDO. PANSI FASE 1 | G8: SG-PDP VALIDADO Y EN PRIMER TRIMESTRE OPERATIVO
B9: VULNERABILIDADES FÍSICAS - OPERATIVAS | C9: MAPEOS DEL SG-PDP Debe existir esta documentación: (PROCESOS, ECOSISTEMA PDP, ESTACIONES DE TRABAJO, CICLO DE VIDA DEL DATO, 3ras PARTES, OTROS) | I9: =IFERROR(_xlfn.IFS(D9="NO EXISTE DOCUMENTACIÓN, NI MÉTODOS. ORGANIZACIÓN EMPÍRICA. CERO CAPACIDAD DE REACCIÓN",1,E9="EXISTEN DOCUMENTOS. HAY MÉTODOS SIN RIGUROSIDAD. NO HAY PROYECTO PDP. HAY UN DPD. NIVEL MÍNIMO DE SEGURIDAD. BAJA CAPACIDAD DE IDENTIFICAR Y RESTAURAR BRECHAS",2,F9="PROYECTO PDP EN FASE INICIAL PANSI. HAY DPD. HAY APOYO POR EL RTD. NIVEL MÍNIMO DESEADO DE SEGURIDAD. VULNERABILIDADES IDENTIFICADAS Y ATENDIDAS",3,G9="SG-PDP VALIDADO Y EN PRIMER TRIMESTE DE OPERACIÓN. NIVEL DE SEGURIDAD ADECUADO",4),0) -> 0
C10: INTERACCIÓN TITULAR-RESPONSABLE Debe existir esta documentación: (PUNTOS DE CONTACTO DIRECTO CON EL TITULAR: CÁMARAS DE VIDEO, ESTACIONES DE TRABAJO, REDES SOCIALES, PLATAFORMAS, OTROS) | I10: =IFERROR(_xlfn.IFS(D10="NO EXISTE DOCUMENTACIÓN, NI MÉTODOS. ORGANIZACIÓN EMPÍRICA. CERO CAPACIDAD DE REACCIÓN",1,E10="EXISTEN DOCUMENTOS. HAY MÉTODOS SIN RIGUROSIDAD. NO HAY PROYECTO PDP. HAY UN DPD. NIVEL MÍNIMO DE SEGURIDAD. BAJA CAPACIDAD DE IDENTIFICAR Y RESTAURAR BRECHAS",2,F10="PROYECTO PDP EN FASE INICIAL PANSI. HAY DPD. HAY APOYO POR EL RTD. NIVEL MÍNIMO DESEADO DE SEGURIDAD. VULNERABILIDADES IDENTIFICADAS Y ATENDIDAS",3,G10="SG-PDP VALIDADO Y EN PRIMER TRIMESTE DE OPERACIÓN. NIVEL DE SEGURIDAD ADECUADO",4),0) -> 0
C11: MÉTRICAS Y REGISTROS Debe existir esta documentación: (PANSI, RAT-MTGE, EIPD, PLAN SIMULACROS, PLAN COMPETENCIAS, EJERCICIO DE DERECHOS, OTROS ) | I11: =IFERROR(_xlfn.IFS(D11="NO EXISTE DOCUMENTACIÓN, NI MÉTODOS. ORGANIZACIÓN EMPÍRICA. CERO CAPACIDAD DE REACCIÓN",1,E11="EXISTEN DOCUMENTOS. HAY MÉTODOS SIN RIGUROSIDAD. NO HAY PROYECTO PDP. HAY UN DPD. NIVEL MÍNIMO DE SEGURIDAD. BAJA CAPACIDAD DE IDENTIFICAR Y RESTAURAR BRECHAS",2,F11="PROYECTO PDP EN FASE INICIAL PANSI. HAY DPD. HAY APOYO POR EL RTD. NIVEL MÍNIMO DESEADO DE SEGURIDAD. VULNERABILIDADES IDENTIFICADAS Y ATENDIDAS",3,G11="SG-PDP VALIDADO Y EN PRIMER TRIMESTE DE OPERACIÓN. NIVEL DE SEGURIDAD ADECUADO",4),0) -> 0
C12: RUTINAS PDP Debe existir esta documentación: (PROCEDIMIENTOS DOCUMENTADOS DE LAS PRÁCTICAS SEGURAS PARA PDP POR CICLO DE VIDA, PROCESOS O ESTACIONES DE TRABAJO, ACCESOS, MFA, OTROS) | I12: =IFERROR(_xlfn.IFS(D12="NO EXISTE DOCUMENTACIÓN, NI MÉTODOS. ORGANIZACIÓN EMPÍRICA. CERO CAPACIDAD DE REACCIÓN",1,E12="EXISTEN DOCUMENTOS. HAY MÉTODOS SIN RIGUROSIDAD. NO HAY PROYECTO PDP. HAY UN DPD. NIVEL MÍNIMO DE SEGURIDAD. BAJA CAPACIDAD DE IDENTIFICAR Y RESTAURAR BRECHAS",2,F12="PROYECTO PDP EN FASE INICIAL PANSI. HAY DPD. HAY APOYO POR EL RTD. NIVEL MÍNIMO DESEADO DE SEGURIDAD. VULNERABILIDADES IDENTIFICADAS Y ATENDIDAS",3,G12="SG-PDP VALIDADO Y EN PRIMER TRIMESTE DE OPERACIÓN. NIVEL DE SEGURIDAD ADECUADO",4),0) -> 0
C13: PROGRAMA COMPETENCIAS Debe existir esta documentación: (PROGRAMA PERSONALIZADO Y CATEGORIZADO DE FORTALECIMIENTO DE HABILIDADES Y CONOCIMIENTO TÉCNICO PARA MEJOR DESEMPEÑO INDIVIDUAL Y COLECTIVO) | I13: =IFERROR(_xlfn.IFS(D13="NO EXISTE DOCUMENTACIÓN, NI MÉTODOS. ORGANIZACIÓN EMPÍRICA. CERO CAPACIDAD DE REACCIÓN",1,E13="EXISTEN DOCUMENTOS. HAY MÉTODOS SIN RIGUROSIDAD. NO HAY PROYECTO PDP. HAY UN DPD. NIVEL MÍNIMO DE SEGURIDAD. BAJA CAPACIDAD DE IDENTIFICAR Y RESTAURAR BRECHAS",2,F13="PROYECTO PDP EN FASE INICIAL PANSI. HAY DPD. HAY APOYO POR EL RTD. NIVEL MÍNIMO DESEADO DE SEGURIDAD. VULNERABILIDADES IDENTIFICADAS Y ATENDIDAS",3,G13="SG-PDP VALIDADO Y EN PRIMER TRIMESTE DE OPERACIÓN. NIVEL DE SEGURIDAD ADECUADO",4),0) -> 0
C14: PROGRAMA CONCIENCIACIÓN Debe existir esta documentación: (PROGRAMA PERSONALIZADO Y CATEGORIZADO DE FORTALECIMIENTO DE ACTITUD Y LIDERAZGO PARA MEJOR DESEMPEÑO INDIVIDUAL Y COLECTIVO EN PDP) | I14: =IFERROR(_xlfn.IFS(D14="NO EXISTE DOCUMENTACIÓN, NI MÉTODOS. ORGANIZACIÓN EMPÍRICA. CERO CAPACIDAD DE REACCIÓN",1,E14="EXISTEN DOCUMENTOS. HAY MÉTODOS SIN RIGUROSIDAD. NO HAY PROYECTO PDP. HAY UN DPD. NIVEL MÍNIMO DE SEGURIDAD. BAJA CAPACIDAD DE IDENTIFICAR Y RESTAURAR BRECHAS",2,F14="PROYECTO PDP EN FASE INICIAL PANSI. HAY DPD. HAY APOYO POR EL RTD. NIVEL MÍNIMO DESEADO DE SEGURIDAD. VULNERABILIDADES IDENTIFICADAS Y ATENDIDAS",3,G14="SG-PDP VALIDADO Y EN PRIMER TRIMESTE DE OPERACIÓN. NIVEL DE SEGURIDAD ADECUADO",4),0) -> 0
C15: CONTROL DE CAMBIOS Debe existir esta documentación: (PROCEDIMIENTOS DOCUMENTADOS DE LAS RUTINAS PARA CONTROLAR TRANSICIONES Y EVITAR INTERMITENCIAS Y BRECHAS DE DATOS PERSONALES) | I15: =IFERROR(_xlfn.IFS(D15="NO EXISTE DOCUMENTACIÓN, NI MÉTODOS. ORGANIZACIÓN EMPÍRICA. CERO CAPACIDAD DE REACCIÓN",1,E15="EXISTEN DOCUMENTOS. HAY MÉTODOS SIN RIGUROSIDAD. NO HAY PROYECTO PDP. HAY UN DPD. NIVEL MÍNIMO DE SEGURIDAD. BAJA CAPACIDAD DE IDENTIFICAR Y RESTAURAR BRECHAS",2,F15="PROYECTO PDP EN FASE INICIAL PANSI. HAY DPD. HAY APOYO POR EL RTD. NIVEL MÍNIMO DESEADO DE SEGURIDAD. VULNERABILIDADES IDENTIFICADAS Y ATENDIDAS",3,G15="SG-PDP VALIDADO Y EN PRIMER TRIMESTE DE OPERACIÓN. NIVEL DE SEGURIDAD ADECUADO",4),0) -> 0
C16: PROGRAMA DE COMUNICACIÓN PDP Debe existir esta documentación: (CRONOGRAMA DE ACTIVIDADES DISEÑADAS PARA INCULCAR LOS VALORES Y PRINCIPIOS ORGANIZACIONALES) | I16: =IFERROR(_xlfn.IFS(D16="NO EXISTE DOCUMENTACIÓN, NI MÉTODOS. ORGANIZACIÓN EMPÍRICA. CERO CAPACIDAD DE REACCIÓN",1,E16="EXISTEN DOCUMENTOS. HAY MÉTODOS SIN RIGUROSIDAD. NO HAY PROYECTO PDP. HAY UN DPD. NIVEL MÍNIMO DE SEGURIDAD. BAJA CAPACIDAD DE IDENTIFICAR Y RESTAURAR BRECHAS",2,F16="PROYECTO PDP EN FASE INICIAL PANSI. HAY DPD. HAY APOYO POR EL RTD. NIVEL MÍNIMO DESEADO DE SEGURIDAD. VULNERABILIDADES IDENTIFICADAS Y ATENDIDAS",3,G16="SG-PDP VALIDADO Y EN PRIMER TRIMESTE DE OPERACIÓN. NIVEL DE SEGURIDAD ADECUADO",4),0) -> 0
H18: ESTADO DE LA TÉCNICA | I18: =AVERAGEIF(I9:I17,"<>0") -> #DIV/0!
D20: ADECUACIÓN DEL NIVEL DE SEGURIDAD (PANSI) ÁREA: FÍSICA-OPERATIVAS OBLIGACIÓN LOPDP:2021, ARTÍCULO 47.6
K23: REQUISITO ARTÍCULO 22.2 -RESOLUCIÓN 2025-0028-R (GARANTÍA DE INDEPENDENCIA PARA DPO) | W23: ESTATUS DEL COMPROMISO DE APLICABILIDAD
D24: CAÓTICO | E24: PSEUDO - PROFESIONAL | G24: PROFESIONAL
D25: 1 | E25: MEDIO BAJO 2 | F25: MEDIO ALTO 3 | G25: 4 | H25: ACCIONES MITIGADORAS | K25: RECURSOS NECESARIO | Q25: COMPROMISOS DE APLICABILIDAD | W25: CUMPLIDO | X25: DEMORADO | Y25: EN PROCESO
D26: DOCUMENTACIÓN INEXISTENTE | E26: DOCUMENTACIÓN SIN PDP INCLUIDO | F26: GRC DOCUMENTADO CON PDP INCLUIDO. PANSI FASE 1 | G26: SG-PDP VALIDADO Y EN PRIMER TRIMESTRE OPERATIVO | H26: MEDIDAS, HERRAMIENTAS Y CONTROLES para elevar el nivel del estado de la técnica | K26: HUMANO | L26: TECNOLOGÍCO | M26: FINANCIERO | N26: TIEMPO | O26: INFRAESTRUCTURA | Q26: FECHA PROBABLE INICIO | R26: INVERSIÓN ESTIMADA HORAS - HOMBRE | S26: INVERSIÓN ESTIMADA DINERO | T26: COMENTARIOS
B27: VULNERABILIDADES FÍSICAS - OPERATIVAS | C27: MAPEOS DEL SG-PDP Debe existir esta documentación: (PROCESOS, ECOSISTEMA PDP, ESTACIONES DE TRABAJO, CICLO DE VIDA DEL DATO, 3ras PARTES, OTROS) | I27: =IFERROR(_xlfn.IFS(D27="NO EXISTE DOCUMENTACIÓN, NI MÉTODOS. ORGANIZACIÓN EMPÍRICA. CERO CAPACIDAD DE REACCIÓN",1,E27="EXISTEN DOCUMENTOS. HAY MÉTODOS SIN RIGUROSIDAD. NO HAY PROYECTO PDP. HAY UN DPD. NIVEL MÍNIMO DE SEGURIDAD. BAJA CAPACIDAD DE IDENTIFICAR Y RESTAURAR BRECHAS",2,F27="PROYECTO PDP EN FASE INICIAL PANSI. HAY DPD. HAY APOYO POR EL RTD. NIVEL MÍNIMO DESEADO DE SEGURIDAD. VULNERABILIDADES IDENTIFICADAS Y ATENDIDAS",3,G27="SG-PDP VALIDADO Y EN PRIMER TRIMESTE DE OPERACIÓN. NIVEL DE SEGURIDAD ADECUADO",4),0) -> 0 | K27: X | M27: X | N27: X | Q27: DESCRITO EN COMENTARIOS | R27: DESCRITO EN COMENTARIOS | S27: DESCRITO EN COMENTARIOS
C28: INTERACCIÓN TITULAR-RESPONSABLE Debe existir esta documentación: (CÁMARAS DE VIDEO, ESTACIONES DE TRABAJO, REDES SOCIALES, PLATAFORMAS, OTROS) | I28: =IFERROR(_xlfn.IFS(D28="NO EXISTE DOCUMENTACIÓN, NI MÉTODOS. ORGANIZACIÓN EMPÍRICA. CERO CAPACIDAD DE REACCIÓN",1,E28="EXISTEN DOCUMENTOS. HAY MÉTODOS SIN RIGUROSIDAD. NO HAY PROYECTO PDP. HAY UN DPD. NIVEL MÍNIMO DE SEGURIDAD. BAJA CAPACIDAD DE IDENTIFICAR Y RESTAURAR BRECHAS",2,F28="PROYECTO PDP EN FASE INICIAL PANSI. HAY DPD. HAY APOYO POR EL RTD. NIVEL MÍNIMO DESEADO DE SEGURIDAD. VULNERABILIDADES IDENTIFICADAS Y ATENDIDAS",3,G28="SG-PDP VALIDADO Y EN PRIMER TRIMESTE DE OPERACIÓN. NIVEL DE SEGURIDAD ADECUADO",4),0) -> 0 | K28: X | M28: X | N28: X | Q28: DESCRITO EN COMENTARIOS | R28: DESCRITO EN COMENTARIOS | S28: DESCRITO EN COMENTARIOS
C29: MÉTRICAS Y REGISTROS Debe existir esta documentación: (PANSI, RAT-MTGE, EIPD, PLAN SIMULACROS, PLAN COMPETENCIAS, EJERCICIO DE DERECHOS, OTROS ) | I29: =IFERROR(_xlfn.IFS(D29="NO EXISTE DOCUMENTACIÓN, NI MÉTODOS. ORGANIZACIÓN EMPÍRICA. CERO CAPACIDAD DE REACCIÓN",1,E29="EXISTEN DOCUMENTOS. HAY MÉTODOS SIN RIGUROSIDAD. NO HAY PROYECTO PDP. HAY UN DPD. NIVEL MÍNIMO DE SEGURIDAD. BAJA CAPACIDAD DE IDENTIFICAR Y RESTAURAR BRECHAS",2,F29="PROYECTO PDP EN FASE INICIAL PANSI. HAY DPD. HAY APOYO POR EL RTD. NIVEL MÍNIMO DESEADO DE SEGURIDAD. VULNERABILIDADES IDENTIFICADAS Y ATENDIDAS",3,G29="SG-PDP VALIDADO Y EN PRIMER TRIMESTE DE OPERACIÓN. NIVEL DE SEGURIDAD ADECUADO",4),0) -> 0 | K29: X | M29: X | N29: X | Q29: DESCRITO EN COMENTARIOS | R29: DESCRITO EN COMENTARIOS | S29: DESCRITO EN COMENTARIOS
C30: RUTINAS PDP Debe existir esta documentación: (PROCEDIMIENTOS DOCUMENTADOS DE LAS PRÁCTICAS SEGURAS PARA PDP POR CICLO DE VIDA, PROCESOS O ESTACIONES DE TRABAJO) | I30: =IFERROR(_xlfn.IFS(D30="NO EXISTE DOCUMENTACIÓN, NI MÉTODOS. ORGANIZACIÓN EMPÍRICA. CERO CAPACIDAD DE REACCIÓN",1,E30="EXISTEN DOCUMENTOS. HAY MÉTODOS SIN RIGUROSIDAD. NO HAY PROYECTO PDP. HAY UN DPD. NIVEL MÍNIMO DE SEGURIDAD. BAJA CAPACIDAD DE IDENTIFICAR Y RESTAURAR BRECHAS",2,F30="PROYECTO PDP EN FASE INICIAL PANSI. HAY DPD. HAY APOYO POR EL RTD. NIVEL MÍNIMO DESEADO DE SEGURIDAD. VULNERABILIDADES IDENTIFICADAS Y ATENDIDAS",3,G30="SG-PDP VALIDADO Y EN PRIMER TRIMESTE DE OPERACIÓN. NIVEL DE SEGURIDAD ADECUADO",4),0) -> 0 | K30: X | M30: X | N30: X | Q30: DESCRITO EN COMENTARIOS | R30: DESCRITO EN COMENTARIOS | S30: DESCRITO EN COMENTARIOS
C31: PROGRAMA COMPETENCIAS Debe existir esta documentación: (PROGRAMA PERSONALIZADO Y CATEGORIZADO DE FORTALECIMIENTO DE HABILIDADES Y CONOCIMIENTO TÉCNICO PARA MEJOR DESEMPEÑO INDIVIDUAL Y COLECTIVO) | I31: =IFERROR(_xlfn.IFS(D31="NO EXISTE DOCUMENTACIÓN, NI MÉTODOS. ORGANIZACIÓN EMPÍRICA. CERO CAPACIDAD DE REACCIÓN",1,E31="EXISTEN DOCUMENTOS. HAY MÉTODOS SIN RIGUROSIDAD. NO HAY PROYECTO PDP. HAY UN DPD. NIVEL MÍNIMO DE SEGURIDAD. BAJA CAPACIDAD DE IDENTIFICAR Y RESTAURAR BRECHAS",2,F31="PROYECTO PDP EN FASE INICIAL PANSI. HAY DPD. HAY APOYO POR EL RTD. NIVEL MÍNIMO DESEADO DE SEGURIDAD. VULNERABILIDADES IDENTIFICADAS Y ATENDIDAS",3,G31="SG-PDP VALIDADO Y EN PRIMER TRIMESTE DE OPERACIÓN. NIVEL DE SEGURIDAD ADECUADO",4),0) -> 0 | K31: X | M31: X | N31: X | Q31: DESCRITO EN COMENTARIOS | R31: DESCRITO EN COMENTARIOS | S31: DESCRITO EN COMENTARIOS
C32: PROGRAMA CONCIENCIACIÓN Debe existir esta documentación: (PROGRAMA PERSONALIZADO Y CATEGORIZADO DE FORTALECIMIENTO DE ACTITUD Y LIDERAZGO PARA MEJOR DESEMPEÑO INDIVIDUAL Y COLECTIVO EN PDP) | I32: =IFERROR(_xlfn.IFS(D32="NO EXISTE DOCUMENTACIÓN, NI MÉTODOS. ORGANIZACIÓN EMPÍRICA. CERO CAPACIDAD DE REACCIÓN",1,E32="EXISTEN DOCUMENTOS. HAY MÉTODOS SIN RIGUROSIDAD. NO HAY PROYECTO PDP. HAY UN DPD. NIVEL MÍNIMO DE SEGURIDAD. BAJA CAPACIDAD DE IDENTIFICAR Y RESTAURAR BRECHAS",2,F32="PROYECTO PDP EN FASE INICIAL PANSI. HAY DPD. HAY APOYO POR EL RTD. NIVEL MÍNIMO DESEADO DE SEGURIDAD. VULNERABILIDADES IDENTIFICADAS Y ATENDIDAS",3,G32="SG-PDP VALIDADO Y EN PRIMER TRIMESTE DE OPERACIÓN. NIVEL DE SEGURIDAD ADECUADO",4),0) -> 0 | K32: X | M32: X | N32: X | Q32: DESCRITO EN COMENTARIOS | R32: DESCRITO EN COMENTARIOS | S32: DESCRITO EN COMENTARIOS
C33: CONTROL DE CAMBIOS Debe existir esta documentación: (PROCEDIMIENTOS DOCUMENTADOS DE LAS RUTINAS PARA CONTROLAR TRANSICIONES Y EVITAR INTERMITENCIAS Y BRECHAS DE DATOS PERSONALES) | I33: =IFERROR(_xlfn.IFS(D33="NO EXISTE DOCUMENTACIÓN, NI MÉTODOS. ORGANIZACIÓN EMPÍRICA. CERO CAPACIDAD DE REACCIÓN",1,E33="EXISTEN DOCUMENTOS. HAY MÉTODOS SIN RIGUROSIDAD. NO HAY PROYECTO PDP. HAY UN DPD. NIVEL MÍNIMO DE SEGURIDAD. BAJA CAPACIDAD DE IDENTIFICAR Y RESTAURAR BRECHAS",2,F33="PROYECTO PDP EN FASE INICIAL PANSI. HAY DPD. HAY APOYO POR EL RTD. NIVEL MÍNIMO DESEADO DE SEGURIDAD. VULNERABILIDADES IDENTIFICADAS Y ATENDIDAS",3,G33="SG-PDP VALIDADO Y EN PRIMER TRIMESTE DE OPERACIÓN. NIVEL DE SEGURIDAD ADECUADO",4),0) -> 0 | K33: X | M33: X | N33: X | Q33: DESCRITO EN COMENTARIOS | R33: DESCRITO EN COMENTARIOS | S33: DESCRITO EN COMENTARIOS
C34: PROGRAMA DE COMUNICACIÓN PDP Debe existir esta documentación: (CRONOGRAMA DE ACTIVIDADES DISEÑADAS PARA INCULCAR LOS VALORES Y PRINCIPIOS ORGANIZACIONALES) | I34: =IFERROR(_xlfn.IFS(D34="NO EXISTE DOCUMENTACIÓN, NI MÉTODOS. ORGANIZACIÓN EMPÍRICA. CERO CAPACIDAD DE REACCIÓN",1,E34="EXISTEN DOCUMENTOS. HAY MÉTODOS SIN RIGUROSIDAD. NO HAY PROYECTO PDP. HAY UN DPD. NIVEL MÍNIMO DE SEGURIDAD. BAJA CAPACIDAD DE IDENTIFICAR Y RESTAURAR BRECHAS",2,F34="PROYECTO PDP EN FASE INICIAL PANSI. HAY DPD. HAY APOYO POR EL RTD. NIVEL MÍNIMO DESEADO DE SEGURIDAD. VULNERABILIDADES IDENTIFICADAS Y ATENDIDAS",3,G34="SG-PDP VALIDADO Y EN PRIMER TRIMESTE DE OPERACIÓN. NIVEL DE SEGURIDAD ADECUADO",4),0) -> 0 | K34: X | M34: X | N34: X | Q34: DESCRITO EN COMENTARIOS | R34: DESCRITO EN COMENTARIOS | S34: DESCRITO EN COMENTARIOS
I35: =AVERAGEIF(I27:I34,"<>0") -> #DIV/0!

Sheet FÍSICAS - INFRSTRA  EET + PANSI
D2: EVALUACIÓN DEL ESTADO DE LA TECNICA ÁREA: FÍSICA-INFRAESTRUCTURA REQUISITO LOPDP:2021, ARTÍCULO 10.j
D6: CAÓTICO | E6: PSEUDO - PROFESIONAL | G6: PROFESIONAL
D7: 1 | E7: MEDIO BAJO 2 | F7: MEDIO ALTO 3 | G7: 4 | H7: COMENTARIOS
D8: DOCUMENTACIÓN INEXISTENTE | E8: DOCUMENTACIÓN SIN PDP INCLUIDO | F8: GRC DOCUMENTADO CON PDP INCLUIDO. PANSI FASE 1 | G8: SG-PDP VALIDADO Y EN PRIMER TRIMESTRE OPERATIVO
B9: VULNERABILIDADES FÍSICAS - INFRAESTRUCTURA | C9: CUARTO DE SERVIDORES Debe existir esta documentación: (PLAN DE MANTENIMIENTO, CONTRATO CON PROVEEDOR, CONTROL DE ACCESO, SISTEMA DE VIGILANCIA, ESQUEMA DE ORDEN Y LIMPIEZA) | I9: =IFERROR(_xlfn.IFS(D9="NO EXISTE DOCUMENTACIÓN, NI MÉTODOS. ORGANIZACIÓN EMPÍRICA. CERO CAPACIDAD DE REACCIÓN",1,E9="EXISTEN DOCUMENTOS. HAY MÉTODOS SIN RIGUROSIDAD. NO HAY PROYECTO PDP. HAY UN DPD. NIVEL MÍNIMO DE SEGURIDAD. BAJA CAPACIDAD DE IDENTIFICAR Y RESTAURAR BRECHAS",2,F9="PROYECTO PDP EN FASE INICIAL PANSI. HAY DPD. HAY APOYO POR EL RTD. NIVEL MÍNIMO DESEADO DE SEGURIDAD. VULNERABILIDADES IDENTIFICADAS Y ATENDIDAS",3,G9="SG-PDP VALIDADO Y EN PRIMER TRIMESTE DE OPERACIÓN. NIVEL DE SEGURIDAD ADECUADO",4),0) -> 0
C10: ARCHIVOS FÍSICOS Debe existir esta documentación: (PLAN DE MANTENIMIENTO, RESTAURACIÓN, CONTROL DE ACCESO, SISTEMA DE VIGILANCIA, OTROS) | I10: =IFERROR(_xlfn.IFS(D10="NO EXISTE DOCUMENTACIÓN, NI MÉTODOS. ORGANIZACIÓN EMPÍRICA. CERO CAPACIDAD DE REACCIÓN",1,E10="EXISTEN DOCUMENTOS. HAY MÉTODOS SIN RIGUROSIDAD. NO HAY PROYECTO PDP. HAY UN DPD. NIVEL MÍNIMO DE SEGURIDAD. BAJA CAPACIDAD DE IDENTIFICAR Y RESTAURAR BRECHAS",2,F10="PROYECTO PDP EN FASE INICIAL PANSI. HAY DPD. HAY APOYO POR EL RTD. NIVEL MÍNIMO DESEADO DE SEGURIDAD. VULNERABILIDADES IDENTIFICADAS Y ATENDIDAS",3,G10="SG-PDP VALIDADO Y EN PRIMER TRIMESTE DE OPERACIÓN. NIVEL DE SEGURIDAD ADECUADO",4),0) -> 0
C11: AVISOS INTERACCIÓN TITULAR-RESPONSABLE Debe existir esta documentación: (PLAN DE MANTENIMIENTO, ROTACIÓN, RESTAURACIÓN Y ACTUALIZACIÓN DE LOS AVISOS DE PDP PREVIOS A LA RECOGIDA DE DATOS PERSONALES) | I11: =IFERROR(_xlfn.IFS(D11="NO EXISTE DOCUMENTACIÓN, NI MÉTODOS. ORGANIZACIÓN EMPÍRICA. CERO CAPACIDAD DE REACCIÓN",1,E11="EXISTEN DOCUMENTOS. HAY MÉTODOS SIN RIGUROSIDAD. NO HAY PROYECTO PDP. HAY UN DPD. NIVEL MÍNIMO DE SEGURIDAD. BAJA CAPACIDAD DE IDENTIFICAR Y RESTAURAR BRECHAS",2,F11="PROYECTO PDP EN FASE INICIAL PANSI. HAY DPD. HAY APOYO POR EL RTD. NIVEL MÍNIMO DESEADO DE SEGURIDAD. VULNERABILIDADES IDENTIFICADAS Y ATENDIDAS",3,G11="SG-PDP VALIDADO Y EN PRIMER TRIMESTE DE OPERACIÓN. NIVEL DE SEGURIDAD ADECUADO",4),0) -> 0
C12: SEGURIDAD FÍSICA PERIMETRAL Debe existir esta documentación: (PLAN DE MANTENIMIENTO, RESTAURACIÓN, CONTROL DE ACCESO, SISTEMA DE VIGILANCIA Y MONITOREO, OTROS) | I12: =IFERROR(_xlfn.IFS(D12="NO EXISTE DOCUMENTACIÓN, NI MÉTODOS. ORGANIZACIÓN EMPÍRICA. CERO CAPACIDAD DE REACCIÓN",1,E12="EXISTEN DOCUMENTOS. HAY MÉTODOS SIN RIGUROSIDAD. NO HAY PROYECTO PDP. HAY UN DPD. NIVEL MÍNIMO DE SEGURIDAD. BAJA CAPACIDAD DE IDENTIFICAR Y RESTAURAR BRECHAS",2,F12="PROYECTO PDP EN FASE INICIAL PANSI. HAY DPD. HAY APOYO POR EL RTD. NIVEL MÍNIMO DESEADO DE SEGURIDAD. VULNERABILIDADES IDENTIFICADAS Y ATENDIDAS",3,G12="SG-PDP VALIDADO Y EN PRIMER TRIMESTE DE OPERACIÓN. NIVEL DE SEGURIDAD ADECUADO",4),0) -> 0
C13: RUTINAS PDP Debe existir esta documentación: (PROCEDIMIENTOS Y REGISTROS QUE PERMITEN CUMPLIMIENTO DE MEDIDAS Y CONTROLES RECONOCIDOS INTERNACIONALMENTE PARA PROTECCIÓN DE DATOS E INFORMACIÓN) | I13: =IFERROR(_xlfn.IFS(D13="NO EXISTE DOCUMENTACIÓN, NI MÉTODOS. ORGANIZACIÓN EMPÍRICA. CERO CAPACIDAD DE REACCIÓN",1,E13="EXISTEN DOCUMENTOS. HAY MÉTODOS SIN RIGUROSIDAD. NO HAY PROYECTO PDP. HAY UN DPD. NIVEL MÍNIMO DE SEGURIDAD. BAJA CAPACIDAD DE IDENTIFICAR Y RESTAURAR BRECHAS",2,F13="PROYECTO PDP EN FASE INICIAL PANSI. HAY DPD. HAY APOYO POR EL RTD. NIVEL MÍNIMO DESEADO DE SEGURIDAD. VULNERABILIDADES IDENTIFICADAS Y ATENDIDAS",3,G13="SG-PDP VALIDADO Y EN PRIMER TRIMESTE DE OPERACIÓN. NIVEL DE SEGURIDAD ADECUADO",4),0) -> 0
C14: MANTENIMIENTO GENERAL Debe existir esta documentación: (PLAN DE MANTENIMIENTO, REGISTROS DE EJECUCIÓN, MÉTRICAS E INDICADORES QUE VALIDEN LA EFICACIA Y EFICIENCIA DEL PLAN) | I14: =IFERROR(_xlfn.IFS(D14="NO EXISTE DOCUMENTACIÓN, NI MÉTODOS. ORGANIZACIÓN EMPÍRICA. CERO CAPACIDAD DE REACCIÓN",1,E14="EXISTEN DOCUMENTOS. HAY MÉTODOS SIN RIGUROSIDAD. NO HAY PROYECTO PDP. HAY UN DPD. NIVEL MÍNIMO DE SEGURIDAD. BAJA CAPACIDAD DE IDENTIFICAR Y RESTAURAR BRECHAS",2,F14="PROYECTO PDP EN FASE INICIAL PANSI. HAY DPD. HAY APOYO POR EL RTD. NIVEL MÍNIMO DESEADO DE SEGURIDAD. VULNERABILIDADES IDENTIFICADAS Y ATENDIDAS",3,G14="SG-PDP VALIDADO Y EN PRIMER TRIMESTE DE OPERACIÓN. NIVEL DE SEGURIDAD ADECUADO",4),0) -> 0
C15: CABLEADOS Y DISPOSITIVOS Debe existir esta documentación: (PLAN DE MANTENIMIENTO, ROTACIÓN, RESTAURACIÓN Y ACTUALIZACIÓN DEL CABLEADO Y DISPOSITIVOS DE LA PLATAFORMA DIGITAL DE LA ORGANIZACIÓN) | I15: =IFERROR(_xlfn.IFS(D15="NO EXISTE DOCUMENTACIÓN, NI MÉTODOS. ORGANIZACIÓN EMPÍRICA. CERO CAPACIDAD DE REACCIÓN",1,E15="EXISTEN DOCUMENTOS. HAY MÉTODOS SIN RIGUROSIDAD. NO HAY PROYECTO PDP. HAY UN DPD. NIVEL MÍNIMO DE SEGURIDAD. BAJA CAPACIDAD DE IDENTIFICAR Y RESTAURAR BRECHAS",2,F15="PROYECTO PDP EN FASE INICIAL PANSI. HAY DPD. HAY APOYO POR EL RTD. NIVEL MÍNIMO DESEADO DE SEGURIDAD. VULNERABILIDADES IDENTIFICADAS Y ATENDIDAS",3,G15="SG-PDP VALIDADO Y EN PRIMER TRIMESTE DE OPERACIÓN. NIVEL DE SEGURIDAD ADECUADO",4),0) -> 0
C16: GESTIÓN DE INFRAESTRUCTURAS CRÍTICAS Debe existir esta documentación: (PLAN DE MANTENIMIENTO, ROTACIÓN, RESTAURACIÓN Y ACTUALIZACIÓN DE LAS ESTRUCTURAS CRÍTICAS PARA CONTINUIDAD DE NEGOCIO Y SEGURIDAD DE LOS DATOS E INFORMACIÓN) | I16: =IFERROR(_xlfn.IFS(D16="NO EXISTE DOCUMENTACIÓN, NI MÉTODOS. ORGANIZACIÓN EMPÍRICA. CERO CAPACIDAD DE REACCIÓN",1,E16="EXISTEN DOCUMENTOS. HAY MÉTODOS SIN RIGUROSIDAD. NO HAY PROYECTO PDP. HAY UN DPD. NIVEL MÍNIMO DE SEGURIDAD. BAJA CAPACIDAD DE IDENTIFICAR Y RESTAURAR BRECHAS",2,F16="PROYECTO PDP EN FASE INICIAL PANSI. HAY DPD. HAY APOYO POR EL RTD. NIVEL MÍNIMO DESEADO DE SEGURIDAD. VULNERABILIDADES IDENTIFICADAS Y ATENDIDAS",3,G16="SG-PDP VALIDADO Y EN PRIMER TRIMESTE DE OPERACIÓN. NIVEL DE SEGURIDAD ADECUADO",4),0) -> 0
C17: MANTENIMIENTO INFRAESTRUCTURA PROGRAMA DE COMUNICACIÓN PDP Debe existir esta documentación: (PLAN DE MANTENIMIENTO, ROTACIÓN, RESTAURACIÓN Y ACTUALIZACIÓN DE LOS AVISOS, CARTELES Y ESPACIOS DONDE SE DESPLIEGA EL PROGRAMA DE COMUNICACIÓN PDP) | I17: =IFERROR(_xlfn.IFS(D17="NO EXISTE DOCUMENTACIÓN, NI MÉTODOS. ORGANIZACIÓN EMPÍRICA. CERO CAPACIDAD DE REACCIÓN",1,E17="EXISTEN DOCUMENTOS. HAY MÉTODOS SIN RIGUROSIDAD. NO HAY PROYECTO PDP. HAY UN DPD. NIVEL MÍNIMO DE SEGURIDAD. BAJA CAPACIDAD DE IDENTIFICAR Y RESTAURAR BRECHAS",2,F17="PROYECTO PDP EN FASE INICIAL PANSI. HAY DPD. HAY APOYO POR EL RTD. NIVEL MÍNIMO DESEADO DE SEGURIDAD. VULNERABILIDADES IDENTIFICADAS Y ATENDIDAS",3,G17="SG-PDP VALIDADO Y EN PRIMER TRIMESTE DE OPERACIÓN. NIVEL DE SEGURIDAD ADECUADO",4),0) -> 0
H19: ESTADO DE LA TÉCNICA | I19: =AVERAGEIF(I9:I18,"<>0") -> #DIV/0!
D21: ADECUACIÓN DEL NIVEL DE SEGURIDAD (PANSI) ÁREA: FÍSICA-INFRAESTRUCTURA OBLIGACIÓN LOPDP:2021, ARTÍCULO 47.6
K24: REQUISITO ARTÍCULO 22.2 -RESOLUCIÓN 2025-0028-R (GARANTÍA DE INDEPENDENCIA PARA DPO) | W24: ESTATUS DEL COMPROMISO DE APLICABILIDAD
D25: CAÓTICO | E25: PSEUDO - PROFESIONAL | G25: PROFESIONAL
D26: 1 | E26: MEDIO BAJO 2 | F26: MEDIO ALTO 3 | G26: 4 | H26: ACCIONES MITIGADORAS | K26: RECURSOS NECESARIO | Q26: COMPROMISOS DE APLICABILIDAD | W26: CUMPLIDO | X26: DEMORADO | Y26: EN PROCESO
D27: DOCUMENTACIÓN INEXISTENTE | E27: DOCUMENTACIÓN SIN PDP INCLUIDO | F27: GRC DOCUMENTADO CON PDP INCLUIDO. PANSI FASE 1 | G27: SG-PDP VALIDADO Y EN PRIMER TRIMESTRE OPERATIVO | H27: MEDIDAS, HERRAMIENTAS Y CONTROLES para elevar el nivel del estado de la técnica | K27: HUMANO | L27: TECNOLOGÍCO | M27: FINANCIERO | N27: TIEMPO | O27: INFRAESTRUCTURA | Q27: FECHA PROBABLE INICIO | R27: INVERSIÓN ESTIMADA HORAS - HOMBRE | S27: INVERSIÓN ESTIMADA DINERO | T27: COMENTARIOS
B28: VULNERABILIDADES FÍSICAS - INFRAESTRUCTURA | C28: CUARTO DE SERVIDORES Debe existir esta documentación: (PLAN DE MANTENIMIENTO, CONTRATO CON PROVEEDOR, CONTROL DE ACCESO, SISTEMA DE VIGILANCIA, ESQUEMA DE ORDEN Y LIMPIEZA) | I28: =IFERROR(_xlfn.IFS(D28="NO EXISTE DOCUMENTACIÓN, NI MÉTODOS. ORGANIZACIÓN EMPÍRICA. CERO CAPACIDAD DE REACCIÓN",1,E28="EXISTEN DOCUMENTOS. HAY MÉTODOS SIN RIGUROSIDAD. NO HAY PROYECTO PDP. HAY UN DPD. NIVEL MÍNIMO DE SEGURIDAD. BAJA CAPACIDAD DE IDENTIFICAR Y RESTAURAR BRECHAS",2,F28="PROYECTO PDP EN FASE INICIAL PANSI. HAY DPD. HAY APOYO POR EL RTD. NIVEL MÍNIMO DESEADO DE SEGURIDAD. VULNERABILIDADES IDENTIFICADAS Y ATENDIDAS",3,G28="SG-PDP VALIDADO Y EN PRIMER TRIMESTE DE OPERACIÓN. NIVEL DE SEGURIDAD ADECUADO",4),0) -> 0 | K28: X | M28: X | N28: X | Q28: DESCRITO EN COMENTARIOS | R28: DESCRITO EN COMENTARIOS | S28: DESCRITO EN COMENTARIOS
C29: ARCHIVOS FÍSICOS Debe existir esta documentación: (PLAN DE MANTENIMIENTO, RESTAURACIÓN, CONTROL DE ACCESO, SISTEMA DE VIGILANCIA, OTROS) | I29: =IFERROR(_xlfn.IFS(D29="NO EXISTE DOCUMENTACIÓN, NI MÉTODOS. ORGANIZACIÓN EMPÍRICA. CERO CAPACIDAD DE REACCIÓN",1,E29="EXISTEN DOCUMENTOS. HAY MÉTODOS SIN RIGUROSIDAD. NO HAY PROYECTO PDP. HAY UN DPD. NIVEL MÍNIMO DE SEGURIDAD. BAJA CAPACIDAD DE IDENTIFICAR Y RESTAURAR BRECHAS",2,F29="PROYECTO PDP EN FASE INICIAL PANSI. HAY DPD. HAY APOYO POR EL RTD. NIVEL MÍNIMO DESEADO DE SEGURIDAD. VULNERABILIDADES IDENTIFICADAS Y ATENDIDAS",3,G29="SG-PDP VALIDADO Y EN PRIMER TRIMESTE DE OPERACIÓN. NIVEL DE SEGURIDAD ADECUADO",4),0) -> 0 | K29: X | M29: X | N29: X | Q29: DESCRITO EN COMENTARIOS | R29: DESCRITO EN COMENTARIOS | S29: DESCRITO EN COMENTARIOS
C30: AVISOS INTERACCIÓN TITULAR-RESPONSABLE Debe existir esta documentación: (PLAN DE MANTENIMIENTO, ROTACIÓN, RESTAURACIÓN Y ACTUALIZACIÓN DE LOS AVISOS DE PDP PREVIOS A LA RECOGIDA DE DATOS PERSONALES) | I30: =IFERROR(_xlfn.IFS(D30="NO EXISTE DOCUMENTACIÓN, NI MÉTODOS. ORGANIZACIÓN EMPÍRICA. CERO CAPACIDAD DE REACCIÓN",1,E30="EXISTEN DOCUMENTOS. HAY MÉTODOS SIN RIGUROSIDAD. NO HAY PROYECTO PDP. HAY UN DPD. NIVEL MÍNIMO DE SEGURIDAD. BAJA CAPACIDAD DE IDENTIFICAR Y RESTAURAR BRECHAS",2,F30="PROYECTO PDP EN FASE INICIAL PANSI. HAY DPD. HAY APOYO POR EL RTD. NIVEL MÍNIMO DESEADO DE SEGURIDAD. VULNERABILIDADES IDENTIFICADAS Y ATENDIDAS",3,G30="SG-PDP VALIDADO Y EN PRIMER TRIMESTE DE OPERACIÓN. NIVEL DE SEGURIDAD ADECUADO",4),0) -> 0 | K30: X | M30: X | N30: X | Q30: DESCRITO EN COMENTARIOS | R30: DESCRITO EN COMENTARIOS | S30: DESCRITO EN COMENTARIOS
C31: SEGURIDAD FÍSICA PERIMETRAL Debe existir esta documentación: (PLAN DE MANTENIMIENTO, RESTAURACIÓN, CONTROL DE ACCESO, SISTEMA DE VIGILANCIA Y MONITOREO, OTROS) | I31: =IFERROR(_xlfn.IFS(D31="NO EXISTE DOCUMENTACIÓN, NI MÉTODOS. ORGANIZACIÓN EMPÍRICA. CERO CAPACIDAD DE REACCIÓN",1,E31="EXISTEN DOCUMENTOS. HAY MÉTODOS SIN RIGUROSIDAD. NO HAY PROYECTO PDP. HAY UN DPD. NIVEL MÍNIMO DE SEGURIDAD. BAJA CAPACIDAD DE IDENTIFICAR Y RESTAURAR BRECHAS",2,F31="PROYECTO PDP EN FASE INICIAL PANSI. HAY DPD. HAY APOYO POR EL RTD. NIVEL MÍNIMO DESEADO DE SEGURIDAD. VULNERABILIDADES IDENTIFICADAS Y ATENDIDAS",3,G31="SG-PDP VALIDADO Y EN PRIMER TRIMESTE DE OPERACIÓN. NIVEL DE SEGURIDAD ADECUADO",4),0) -> 0 | K31: X | M31: X | N31: X | Q31: DESCRITO EN COMENTARIOS | R31: DESCRITO EN COMENTARIOS | S31: DESCRITO EN COMENTARIOS
C32: RUTINAS PDP Debe existir esta documentación: (PROCEDIMIENTOS Y REGISTROS QUE PERMITEN CUMPLIMIENTO DE MEDIDAS Y CONTROLES RECONOCIDOS INTERNACIONALMENTE PARA PROTECCIÓN DE DATOS E INFORMACIÓN) | I32: =IFERROR(_xlfn.IFS(D32="NO EXISTE DOCUMENTACIÓN, NI MÉTODOS. ORGANIZACIÓN EMPÍRICA. CERO CAPACIDAD DE REACCIÓN",1,E32="EXISTEN DOCUMENTOS. HAY MÉTODOS SIN RIGUROSIDAD. NO HAY PROYECTO PDP. HAY UN DPD. NIVEL MÍNIMO DE SEGURIDAD. BAJA CAPACIDAD DE IDENTIFICAR Y RESTAURAR BRECHAS",2,F32="PROYECTO PDP EN FASE INICIAL PANSI. HAY DPD. HAY APOYO POR EL RTD. NIVEL MÍNIMO DESEADO DE SEGURIDAD. VULNERABILIDADES IDENTIFICADAS Y ATENDIDAS",3,G32="SG-PDP VALIDADO Y EN PRIMER TRIMESTE DE OPERACIÓN. NIVEL DE SEGURIDAD ADECUADO",4),0) -> 0 | K32: X | M32: X | N32: X | Q32: DESCRITO EN COMENTARIOS | R32: DESCRITO EN COMENTARIOS | S32: DESCRITO EN COMENTARIOS
C33: MANTENIMIENTO GENERAL Debe existir esta documentación: (PLAN DE MANTENIMIENTO, REGISTROS DE EJECUCIÓN, MÉTRICAS E INDICADORES QUE VALIDEN LA EFICACIA Y EFICIENCIA DEL PLAN) | I33: =IFERROR(_xlfn.IFS(D33="NO EXISTE DOCUMENTACIÓN, NI MÉTODOS. ORGANIZACIÓN EMPÍRICA. CERO CAPACIDAD DE REACCIÓN",1,E33="EXISTEN DOCUMENTOS. HAY MÉTODOS SIN RIGUROSIDAD. NO HAY PROYECTO PDP. HAY UN DPD. NIVEL MÍNIMO DE SEGURIDAD. BAJA CAPACIDAD DE IDENTIFICAR Y RESTAURAR BRECHAS",2,F33="PROYECTO PDP EN FASE INICIAL PANSI. HAY DPD. HAY APOYO POR EL RTD. NIVEL MÍNIMO DESEADO DE SEGURIDAD. VULNERABILIDADES IDENTIFICADAS Y ATENDIDAS",3,G33="SG-PDP VALIDADO Y EN PRIMER TRIMESTE DE OPERACIÓN. NIVEL DE SEGURIDAD ADECUADO",4),0) -> 0 | K33: X | M33: X | N33: X | Q33: DESCRITO EN COMENTARIOS | R33: DESCRITO EN COMENTARIOS | S33: DESCRITO EN COMENTARIOS
C34: CABLEADOS Y DISPOSITIVOS Debe existir esta documentación: (PLAN DE MANTENIMIENTO, ROTACIÓN, RESTAURACIÓN Y ACTUALIZACIÓN DEL CABLEADO Y DISPOSITIVOS DE LA PLATAFORMA DIGITAL DE LA ORGANIZACIÓN) | I34: =IFERROR(_xlfn.IFS(D34="NO EXISTE DOCUMENTACIÓN, NI MÉTODOS. ORGANIZACIÓN EMPÍRICA. CERO CAPACIDAD DE REACCIÓN",1,E34="EXISTEN DOCUMENTOS. HAY MÉTODOS SIN RIGUROSIDAD. NO HAY PROYECTO PDP. HAY UN DPD. NIVEL MÍNIMO DE SEGURIDAD. BAJA CAPACIDAD DE IDENTIFICAR Y RESTAURAR BRECHAS",2,F34="PROYECTO PDP EN FASE INICIAL PANSI. HAY DPD. HAY APOYO POR EL RTD. NIVEL MÍNIMO DESEADO DE SEGURIDAD. VULNERABILIDADES IDENTIFICADAS Y ATENDIDAS",3,G34="SG-PDP VALIDADO Y EN PRIMER TRIMESTE DE OPERACIÓN. NIVEL DE SEGURIDAD ADECUADO",4),0) -> 0 | K34: X | M34: X | N34: X | Q34: DESCRITO EN COMENTARIOS | R34: DESCRITO EN COMENTARIOS | S34: DESCRITO EN COMENTARIOS
C35: GESTIÓN DE INFRAESTRUCTURAS CRÍTICAS Debe existir esta documentación: (PLAN DE MANTENIMIENTO, ROTACIÓN, RESTAURACIÓN Y ACTUALIZACIÓN DE LAS ESTRUCTURAS CRÍTICAS PARA CONTINUIDAD DE NEGOCIO Y SEGURIDAD DE LOS DATOS E INFORMACIÓN) | I35: =IFERROR(_xlfn.IFS(D35="NO EXISTE DOCUMENTACIÓN, NI MÉTODOS. ORGANIZACIÓN EMPÍRICA. CERO CAPACIDAD DE REACCIÓN",1,E35="EXISTEN DOCUMENTOS. HAY MÉTODOS SIN RIGUROSIDAD. NO HAY PROYECTO PDP. HAY UN DPD. NIVEL MÍNIMO DE SEGURIDAD. BAJA CAPACIDAD DE IDENTIFICAR Y RESTAURAR BRECHAS",2,F35="PROYECTO PDP EN FASE INICIAL PANSI. HAY DPD. HAY APOYO POR EL RTD. NIVEL MÍNIMO DESEADO DE SEGURIDAD. VULNERABILIDADES IDENTIFICADAS Y ATENDIDAS",3,G35="SG-PDP VALIDADO Y EN PRIMER TRIMESTE DE OPERACIÓN. NIVEL DE SEGURIDAD ADECUADO",4),0) -> 0 | K35: X | M35: X | N35: X | Q35: DESCRITO EN COMENTARIOS | R35: DESCRITO EN COMENTARIOS | S35: DESCRITO EN COMENTARIOS
C36: MANTENIMIENTO INFRAESTRUCTURA PROGRAMA DE COMUNICACIÓN PDP Debe existir esta documentación: (PLAN DE MANTENIMIENTO, ROTACIÓN, RESTAURACIÓN Y ACTUALIZACIÓN DE LOS AVISOS, CARTELES Y ESPACIOS DONDE SE DESPLIEGA EL PROGRAMA DE COMUNICACIÓN PDP) | I36: =IFERROR(_xlfn.IFS(D36="NO EXISTE DOCUMENTACIÓN, NI MÉTODOS. ORGANIZACIÓN EMPÍRICA. CERO CAPACIDAD DE REACCIÓN",1,E36="EXISTEN DOCUMENTOS. HAY MÉTODOS SIN RIGUROSIDAD. NO HAY PROYECTO PDP. HAY UN DPD. NIVEL MÍNIMO DE SEGURIDAD. BAJA CAPACIDAD DE IDENTIFICAR Y RESTAURAR BRECHAS",2,F36="PROYECTO PDP EN FASE INICIAL PANSI. HAY DPD. HAY APOYO POR EL RTD. NIVEL MÍNIMO DESEADO DE SEGURIDAD. VULNERABILIDADES IDENTIFICADAS Y ATENDIDAS",3,G36="SG-PDP VALIDADO Y EN PRIMER TRIMESTE DE OPERACIÓN. NIVEL DE SEGURIDAD ADECUADO",4),0) -> 0 | K36: X | M36: X | N36: X | Q36: DESCRITO EN COMENTARIOS | R36: DESCRITO EN COMENTARIOS | S36: DESCRITO EN COMENTARIOS
I37: =AVERAGEIF(I29:I36,"<>0") -> #DIV/0!

Sheet TÉCNICAS COMPET EET + PANSI
D2: EVALUACIÓN DEL ESTADO DE LA TECNICA ÁREA: TÉCNICAS - COMPETENCIAS REQUISITO LOPDP:2021, ARTÍCULO 10.j
D6: CAÓTICO | E6: PSEUDO - PROFESIONAL | G6: PROFESIONAL
D7: 1 | E7: MEDIO BAJO 2 | F7: MEDIO ALTO 3 | G7: 4 | H7: COMENTARIOS
D8: DOCUMENTACIÓN INEXISTENTE | E8: DOCUMENTACIÓN SIN PDP INCLUIDO | F8: GRC DOCUMENTADO CON PDP INCLUIDO. PANSI FASE 1 | G8: SG-PDP VALIDADO Y EN PRIMER TRIMESTRE OPERATIVO
C9: TRIADA PDP Debe existir esta documentación: (CAPACITACIÓN SOBRE FUNDAMENTOS BÁSICOS Y OBJETIVOS DE LA LOPDP, EL RGLOPDP Y LAS RESOLUCIONES EMITIDAS POR LA SPDP Y NORMATIVA APLICABLE EN MATERIA DE PDP) | I9: =IFERROR(_xlfn.IFS(D9="NO EXISTE DOCUMENTACIÓN, NI MÉTODOS. ORGANIZACIÓN EMPÍRICA. CERO CAPACIDAD DE REACCIÓN",1,E9="EXISTEN DOCUMENTOS. HAY MÉTODOS SIN RIGUROSIDAD. NO HAY PROYECTO PDP. HAY UN DPD. NIVEL MÍNIMO DE SEGURIDAD. BAJA CAPACIDAD DE IDENTIFICAR Y RESTAURAR BRECHAS",2,F9="PROYECTO PDP EN FASE INICIAL PANSI. HAY DPD. HAY APOYO POR EL RTD. NIVEL MÍNIMO DESEADO DE SEGURIDAD. VULNERABILIDADES IDENTIFICADAS Y ATENDIDAS",3,G9="SG-PDP VALIDADO Y EN PRIMER TRIMESTE DE OPERACIÓN. NIVEL DE SEGURIDAD ADECUADO",4),0) -> 0
B10: VULNERABILIDADES TÉCNICAS - COMPETENCIAS | C10: SERIE ISO 27000 Debe existir esta documentación: (CAPACITACIÓN SOBRE FUNDAMENTOS BÁSICOS Y OBJETIVOS LA NORMA ISO PARA SEGURIDAD DE LA INFORMACIÓN Y SU RELACIÓN CON UN SG-PDP) | I10: =IFERROR(_xlfn.IFS(D10="NO EXISTE DOCUMENTACIÓN, NI MÉTODOS. ORGANIZACIÓN EMPÍRICA. CERO CAPACIDAD DE REACCIÓN",1,E10="EXISTEN DOCUMENTOS. HAY MÉTODOS SIN RIGUROSIDAD. NO HAY PROYECTO PDP. HAY UN DPD. NIVEL MÍNIMO DE SEGURIDAD. BAJA CAPACIDAD DE IDENTIFICAR Y RESTAURAR BRECHAS",2,F10="PROYECTO PDP EN FASE INICIAL PANSI. HAY DPD. HAY APOYO POR EL RTD. NIVEL MÍNIMO DESEADO DE SEGURIDAD. VULNERABILIDADES IDENTIFICADAS Y ATENDIDAS",3,G10="SG-PDP VALIDADO Y EN PRIMER TRIMESTE DE OPERACIÓN. NIVEL DE SEGURIDAD ADECUADO",4),0) -> 0
C11: NIS2, PLAN NACIONAL CIBERSEGURIDAD Debe existir esta documentación: (CAPACITACIÓN SOBRE FUNDAMENTOS BÁSICOS Y OBJETIVOS DE ESTANDARES INTERNACIONALES PARA APLICACIÓN DE CONTROLES PARA SEGURIDAD DE LA INFORMACIÓN Y SU RELACIÓN CON UN SG-PDP) | I11: =IFERROR(_xlfn.IFS(D11="NO EXISTE DOCUMENTACIÓN, NI MÉTODOS. ORGANIZACIÓN EMPÍRICA. CERO CAPACIDAD DE REACCIÓN",1,E11="EXISTEN DOCUMENTOS. HAY MÉTODOS SIN RIGUROSIDAD. NO HAY PROYECTO PDP. HAY UN DPD. NIVEL MÍNIMO DE SEGURIDAD. BAJA CAPACIDAD DE IDENTIFICAR Y RESTAURAR BRECHAS",2,F11="PROYECTO PDP EN FASE INICIAL PANSI. HAY DPD. HAY APOYO POR EL RTD. NIVEL MÍNIMO DESEADO DE SEGURIDAD. VULNERABILIDADES IDENTIFICADAS Y ATENDIDAS",3,G11="SG-PDP VALIDADO Y EN PRIMER TRIMESTE DE OPERACIÓN. NIVEL DE SEGURIDAD ADECUADO",4),0) -> 0
C12: FUNDAMENTOS SISTEMAS DE GESTIÓN e ISO 19011 Debe existir esta documentación: (CAPACITACIÓN SOBRE FUNDAMENTOS BÁSICOS Y OBJETIVOS DE LA NORMA ISO PARA REALIZACIÓN DE AUDITORÍAS A SISTEMAS DE GESTIÓN Y SU RELACIÓN CON UN SG-PDP) | I12: =IFERROR(_xlfn.IFS(D12="NO EXISTE DOCUMENTACIÓN, NI MÉTODOS. ORGANIZACIÓN EMPÍRICA. CERO CAPACIDAD DE REACCIÓN",1,E12="EXISTEN DOCUMENTOS. HAY MÉTODOS SIN RIGUROSIDAD. NO HAY PROYECTO PDP. HAY UN DPD. NIVEL MÍNIMO DE SEGURIDAD. BAJA CAPACIDAD DE IDENTIFICAR Y RESTAURAR BRECHAS",2,F12="PROYECTO PDP EN FASE INICIAL PANSI. HAY DPD. HAY APOYO POR EL RTD. NIVEL MÍNIMO DESEADO DE SEGURIDAD. VULNERABILIDADES IDENTIFICADAS Y ATENDIDAS",3,G12="SG-PDP VALIDADO Y EN PRIMER TRIMESTE DE OPERACIÓN. NIVEL DE SEGURIDAD ADECUADO",4),0) -> 0
C13: FUNDAMENTOS GESTIÓN DE PROYECTOS Debe existir esta documentación: (CAPACITACIÓN SOBRE FUNDAMENTOS BÁSICOS Y OBJETIVOS DE METODOLOGÍAS PARA GESTIONAR PROYECTOS COMPLEJOS Y SU RELACIÓN CON UN SG-PDP) | I13: =IFERROR(_xlfn.IFS(D13="NO EXISTE DOCUMENTACIÓN, NI MÉTODOS. ORGANIZACIÓN EMPÍRICA. CERO CAPACIDAD DE REACCIÓN",1,E13="EXISTEN DOCUMENTOS. HAY MÉTODOS SIN RIGUROSIDAD. NO HAY PROYECTO PDP. HAY UN DPD. NIVEL MÍNIMO DE SEGURIDAD. BAJA CAPACIDAD DE IDENTIFICAR Y RESTAURAR BRECHAS",2,F13="PROYECTO PDP EN FASE INICIAL PANSI. HAY DPD. HAY APOYO POR EL RTD. NIVEL MÍNIMO DESEADO DE SEGURIDAD. VULNERABILIDADES IDENTIFICADAS Y ATENDIDAS",3,G13="SG-PDP VALIDADO Y EN PRIMER TRIMESTE DE OPERACIÓN. NIVEL DE SEGURIDAD ADECUADO",4),0) -> 0
C14: FUNDAMENTOS CONTROL ESTADÍSTICO DE PROCESOS Debe existir esta documentación: (CAPACITACIÓN SOBRE FUNDAMENTOS BÁSICOS Y OBJETIVOS DEL CONTROL ESTADISTICO DE PROCESOS Y SU RELACIÓN CON UN SG-PDP) | I14: =IFERROR(_xlfn.IFS(D14="NO EXISTE DOCUMENTACIÓN, NI MÉTODOS. ORGANIZACIÓN EMPÍRICA. CERO CAPACIDAD DE REACCIÓN",1,E14="EXISTEN DOCUMENTOS. HAY MÉTODOS SIN RIGUROSIDAD. NO HAY PROYECTO PDP. HAY UN DPD. NIVEL MÍNIMO DE SEGURIDAD. BAJA CAPACIDAD DE IDENTIFICAR Y RESTAURAR BRECHAS",2,F14="PROYECTO PDP EN FASE INICIAL PANSI. HAY DPD. HAY APOYO POR EL RTD. NIVEL MÍNIMO DESEADO DE SEGURIDAD. VULNERABILIDADES IDENTIFICADAS Y ATENDIDAS",3,G14="SG-PDP VALIDADO Y EN PRIMER TRIMESTE DE OPERACIÓN. NIVEL DE SEGURIDAD ADECUADO",4),0) -> 0
C15: FUNDAMENTOS ADMINISTRACIÓN EMPRESAS Debe existir esta documentación: (CAPACITACIÓN SOBRE FUNDAMENTOS BÁSICOS Y OBJETIVOS DE DISTINTAS METODOLOGÍAS Y HERRAMIENTAS PARA ADMINISTRACIÓN DE EMPRESAS Y SU RELACIÓN CON UN SG-PDP) | I15: =IFERROR(_xlfn.IFS(D15="NO EXISTE DOCUMENTACIÓN, NI MÉTODOS. ORGANIZACIÓN EMPÍRICA. CERO CAPACIDAD DE REACCIÓN",1,E15="EXISTEN DOCUMENTOS. HAY MÉTODOS SIN RIGUROSIDAD. NO HAY PROYECTO PDP. HAY UN DPD. NIVEL MÍNIMO DE SEGURIDAD. BAJA CAPACIDAD DE IDENTIFICAR Y RESTAURAR BRECHAS",2,F15="PROYECTO PDP EN FASE INICIAL PANSI. HAY DPD. HAY APOYO POR EL RTD. NIVEL MÍNIMO DESEADO DE SEGURIDAD. VULNERABILIDADES IDENTIFICADAS Y ATENDIDAS",3,G15="SG-PDP VALIDADO Y EN PRIMER TRIMESTE DE OPERACIÓN. NIVEL DE SEGURIDAD ADECUADO",4),0) -> 0
C16: BUENAS PRÁCTICAS CIBERSEGURIDAD Debe existir esta documentación: (CAPACITACIÓN SOBRE FUNDAMENTOS BÁSICOS Y OBJETIVOS DE MEJORES PRÁCTICAS EN CIBERSEGURIDAD Y SU RELACIÓN CON UN SG-PDP) | I16: =IFERROR(_xlfn.IFS(D16="NO EXISTE DOCUMENTACIÓN, NI MÉTODOS. ORGANIZACIÓN EMPÍRICA. CERO CAPACIDAD DE REACCIÓN",1,E16="EXISTEN DOCUMENTOS. HAY MÉTODOS SIN RIGUROSIDAD. NO HAY PROYECTO PDP. HAY UN DPD. NIVEL MÍNIMO DE SEGURIDAD. BAJA CAPACIDAD DE IDENTIFICAR Y RESTAURAR BRECHAS",2,F16="PROYECTO PDP EN FASE INICIAL PANSI. HAY DPD. HAY APOYO POR EL RTD. NIVEL MÍNIMO DESEADO DE SEGURIDAD. VULNERABILIDADES IDENTIFICADAS Y ATENDIDAS",3,G16="SG-PDP VALIDADO Y EN PRIMER TRIMESTE DE OPERACIÓN. NIVEL DE SEGURIDAD ADECUADO",4),0) -> 0
H18: ESTADO DE LA TÉCNICA | I18: =AVERAGEIF(I9:I17,"<>0") -> #DIV/0!
D20: ADECUACIÓN DEL NIVEL DE SEGURIDAD (PANSI) ÁREA: TÉCNICAS - COMPETENCIAS OBLIGACIÓN LOPDP:2021, ARTÍCULO 47.6
K23: REQUISITO ARTÍCULO 22.2 -RESOLUCIÓN 2025-0028-R (GARANTÍA DE INDEPENDENCIA PARA DPO) | W23: ESTATUS DEL COMPROMISO DE APLICABILIDAD
D24: CAÓTICO | E24: PSEUDO - PROFESIONAL | G24: PROFESIONAL
D25: 1 | E25: MEDIO BAJO 2 | F25: MEDIO ALTO 3 | G25: 4 | H25: ACCIONES MITIGADORAS | K25: RECURSOS NECESARIO | Q25: COMPROMISOS DE APLICABILIDAD | W25: CUMPLIDO | X25: DEMORADO | Y25: EN PROCESO
D26: DOCUMENTACIÓN INEXISTENTE | E26: DOCUMENTACIÓN SIN PDP INCLUIDO | F26: GRC DOCUMENTADO CON PDP INCLUIDO. PANSI FASE 1 | G26: SG-PDP VALIDADO Y EN PRIMER TRIMESTRE OPERATIVO | H26: MEDIDAS, HERRAMIENTAS Y CONTROLES para elevar el nivel del estado de la técnica | K26: HUMANO | L26: TECNOLOGÍCO | M26: FINANCIERO | N26: TIEMPO | O26: INFRAESTRUCTURA | Q26: FECHA PROBABLE INICIO | R26: INVERSIÓN ESTIMADA HORAS - HOMBRE | S26: INVERSIÓN ESTIMADA DINERO | T26: COMENTARIOS
C27: TRIADA PDP Debe existir esta documentación: (CAPACITACIÓN SOBRE FUNDAMENTOS BÁSICOS Y OBJETIVOS DE LA LOPDP, EL RGLOPDP Y LAS RESOLUCIONES EMITIDAS POR LA SPDP Y NORMATIVA APLICABLE EN MATERIA DE PDP) | I27: =IFERROR(_xlfn.IFS(D27="NO EXISTE DOCUMENTACIÓN, NI MÉTODOS. ORGANIZACIÓN EMPÍRICA. CERO CAPACIDAD DE REACCIÓN",1,E27="EXISTEN DOCUMENTOS. HAY MÉTODOS SIN RIGUROSIDAD. NO HAY PROYECTO PDP. HAY UN DPD. NIVEL MÍNIMO DE SEGURIDAD. BAJA CAPACIDAD DE IDENTIFICAR Y RESTAURAR BRECHAS",2,F27="PROYECTO PDP EN FASE INICIAL PANSI. HAY DPD. HAY APOYO POR EL RTD. NIVEL MÍNIMO DESEADO DE SEGURIDAD. VULNERABILIDADES IDENTIFICADAS Y ATENDIDAS",3,G27="SG-PDP VALIDADO Y EN PRIMER TRIMESTE DE OPERACIÓN. NIVEL DE SEGURIDAD ADECUADO",4),0) -> 0 | K27: X | M27: X | N27: X | Q27: DESCRITO EN COMENTARIOS | R27: DESCRITO EN COMENTARIOS | S27: DESCRITO EN COMENTARIOS
B28: VULNERABILIDADES TÉCNICAS - COMPETENCIAS | C28: SERIE ISO 27000 Debe existir esta documentación: (CAPACITACIÓN SOBRE FUNDAMENTOS BÁSICOS Y OBJETIVOS LA NORMA ISO PARA SEGURIDAD DE LA INFORMACIÓN Y SU RELACIÓN CON UN SG-PDP) | I28: =IFERROR(_xlfn.IFS(D28="NO EXISTE DOCUMENTACIÓN, NI MÉTODOS. ORGANIZACIÓN EMPÍRICA. CERO CAPACIDAD DE REACCIÓN",1,E28="EXISTEN DOCUMENTOS. HAY MÉTODOS SIN RIGUROSIDAD. NO HAY PROYECTO PDP. HAY UN DPD. NIVEL MÍNIMO DE SEGURIDAD. BAJA CAPACIDAD DE IDENTIFICAR Y RESTAURAR BRECHAS",2,F28="PROYECTO PDP EN FASE INICIAL PANSI. HAY DPD. HAY APOYO POR EL RTD. NIVEL MÍNIMO DESEADO DE SEGURIDAD. VULNERABILIDADES IDENTIFICADAS Y ATENDIDAS",3,G28="SG-PDP VALIDADO Y EN PRIMER TRIMESTE DE OPERACIÓN. NIVEL DE SEGURIDAD ADECUADO",4),0) -> 0 | K28: X | M28: X | N28: X | Q28: DESCRITO EN COMENTARIOS | R28: DESCRITO EN COMENTARIOS | S28: DESCRITO EN COMENTARIOS
C29: NIS2, PLAN NACIONAL CIBERSEGURIDAD Debe existir esta documentación: (CAPACITACIÓN SOBRE FUNDAMENTOS BÁSICOS Y OBJETIVOS DE ESTANDARES INTERNACIONALES PARA APLICACIÓN DE CONTROLES PARA SEGURIDAD DE LA INFORMACIÓN Y SU RELACIÓN CON UN SG-PDP) | I29: =IFERROR(_xlfn.IFS(D29="NO EXISTE DOCUMENTACIÓN, NI MÉTODOS. ORGANIZACIÓN EMPÍRICA. CERO CAPACIDAD DE REACCIÓN",1,E29="EXISTEN DOCUMENTOS. HAY MÉTODOS SIN RIGUROSIDAD. NO HAY PROYECTO PDP. HAY UN DPD. NIVEL MÍNIMO DE SEGURIDAD. BAJA CAPACIDAD DE IDENTIFICAR Y RESTAURAR BRECHAS",2,F29="PROYECTO PDP EN FASE INICIAL PANSI. HAY DPD. HAY APOYO POR EL RTD. NIVEL MÍNIMO DESEADO DE SEGURIDAD. VULNERABILIDADES IDENTIFICADAS Y ATENDIDAS",3,G29="SG-PDP VALIDADO Y EN PRIMER TRIMESTE DE OPERACIÓN. NIVEL DE SEGURIDAD ADECUADO",4),0) -> 0 | K29: X | M29: X | N29: X | Q29: DESCRITO EN COMENTARIOS | R29: DESCRITO EN COMENTARIOS | S29: DESCRITO EN COMENTARIOS
C30: FUNDAMENTOS SISTEMAS DE GESTIÓN e ISO 19011 Debe existir esta documentación: (CAPACITACIÓN SOBRE FUNDAMENTOS BÁSICOS Y OBJETIVOS DE LA NORMA ISO PARA REALIZACIÓN DE AUDITORÍAS A SISTEMAS DE GESTIÓN Y SU RELACIÓN CON UN SG-PDP) | I30: =IFERROR(_xlfn.IFS(D30="NO EXISTE DOCUMENTACIÓN, NI MÉTODOS. ORGANIZACIÓN EMPÍRICA. CERO CAPACIDAD DE REACCIÓN",1,E30="EXISTEN DOCUMENTOS. HAY MÉTODOS SIN RIGUROSIDAD. NO HAY PROYECTO PDP. HAY UN DPD. NIVEL MÍNIMO DE SEGURIDAD. BAJA CAPACIDAD DE IDENTIFICAR Y RESTAURAR BRECHAS",2,F30="PROYECTO PDP EN FASE INICIAL PANSI. HAY DPD. HAY APOYO POR EL RTD. NIVEL MÍNIMO DESEADO DE SEGURIDAD. VULNERABILIDADES IDENTIFICADAS Y ATENDIDAS",3,G30="SG-PDP VALIDADO Y EN PRIMER TRIMESTE DE OPERACIÓN. NIVEL DE SEGURIDAD ADECUADO",4),0) -> 0 | K30: X | M30: X | N30: X | Q30: DESCRITO EN COMENTARIOS | R30: DESCRITO EN COMENTARIOS | S30: DESCRITO EN COMENTARIOS
C31: FUNDAMENTOS GESTIÓN DE PROYECTOS Debe existir esta documentación: (CAPACITACIÓN SOBRE FUNDAMENTOS BÁSICOS Y OBJETIVOS DE METODOLOGÍAS PARA GESTIONAR PROYECTOS COMPLEJOS Y SU RELACIÓN CON UN SG-PDP) | I31: =IFERROR(_xlfn.IFS(D31="NO EXISTE DOCUMENTACIÓN, NI MÉTODOS. ORGANIZACIÓN EMPÍRICA. CERO CAPACIDAD DE REACCIÓN",1,E31="EXISTEN DOCUMENTOS. HAY MÉTODOS SIN RIGUROSIDAD. NO HAY PROYECTO PDP. HAY UN DPD. NIVEL MÍNIMO DE SEGURIDAD. BAJA CAPACIDAD DE IDENTIFICAR Y RESTAURAR BRECHAS",2,F31="PROYECTO PDP EN FASE INICIAL PANSI. HAY DPD. HAY APOYO POR EL RTD. NIVEL MÍNIMO DESEADO DE SEGURIDAD. VULNERABILIDADES IDENTIFICADAS Y ATENDIDAS",3,G31="SG-PDP VALIDADO Y EN PRIMER TRIMESTE DE OPERACIÓN. NIVEL DE SEGURIDAD ADECUADO",4),0) -> 0 | K31: X | M31: X | N31: X | Q31: DESCRITO EN COMENTARIOS | R31: DESCRITO EN COMENTARIOS | S31: DESCRITO EN COMENTARIOS
C32: FUNDAMENTOS CONTROL ESTADÍSTICO DE PROCESOS Debe existir esta documentación: (CAPACITACIÓN SOBRE FUNDAMENTOS BÁSICOS Y OBJETIVOS DEL CONTROL ESTADISTICO DE PROCESOS Y SU RELACIÓN CON UN SG-PDP) | I32: =IFERROR(_xlfn.IFS(D32="NO EXISTE DOCUMENTACIÓN, NI MÉTODOS. ORGANIZACIÓN EMPÍRICA. CERO CAPACIDAD DE REACCIÓN",1,E32="EXISTEN DOCUMENTOS. HAY MÉTODOS SIN RIGUROSIDAD. NO HAY PROYECTO PDP. HAY UN DPD. NIVEL MÍNIMO DE SEGURIDAD. BAJA CAPACIDAD DE IDENTIFICAR Y RESTAURAR BRECHAS",2,F32="PROYECTO PDP EN FASE INICIAL PANSI. HAY DPD. HAY APOYO POR EL RTD. NIVEL MÍNIMO DESEADO DE SEGURIDAD. VULNERABILIDADES IDENTIFICADAS Y ATENDIDAS",3,G32="SG-PDP VALIDADO Y EN PRIMER TRIMESTE DE OPERACIÓN. NIVEL DE SEGURIDAD ADECUADO",4),0) -> 0 | K32: X | M32: X | N32: X | Q32: DESCRITO EN COMENTARIOS | R32: DESCRITO EN COMENTARIOS | S32: DESCRITO EN COMENTARIOS
C33: FUNDAMENTOS ADMINISTRACIÓN EMPRESAS Debe existir esta documentación: (CAPACITACIÓN SOBRE FUNDAMENTOS BÁSICOS Y OBJETIVOS DE DISTINTAS METODOLOGÍAS Y HERRAMIENTAS PARA ADMINISTRACIÓN DE EMPRESAS Y SU RELACIÓN CON UN SG-PDP) | I33: =IFERROR(_xlfn.IFS(D33="NO EXISTE DOCUMENTACIÓN, NI MÉTODOS. ORGANIZACIÓN EMPÍRICA. CERO CAPACIDAD DE REACCIÓN",1,E33="EXISTEN DOCUMENTOS. HAY MÉTODOS SIN RIGUROSIDAD. NO HAY PROYECTO PDP. HAY UN DPD. NIVEL MÍNIMO DE SEGURIDAD. BAJA CAPACIDAD DE IDENTIFICAR Y RESTAURAR BRECHAS",2,F33="PROYECTO PDP EN FASE INICIAL PANSI. HAY DPD. HAY APOYO POR EL RTD. NIVEL MÍNIMO DESEADO DE SEGURIDAD. VULNERABILIDADES IDENTIFICADAS Y ATENDIDAS",3,G33="SG-PDP VALIDADO Y EN PRIMER TRIMESTE DE OPERACIÓN. NIVEL DE SEGURIDAD ADECUADO",4),0) -> 0 | K33: X | M33: X | N33: X | Q33: DESCRITO EN COMENTARIOS | R33: DESCRITO EN COMENTARIOS | S33: DESCRITO EN COMENTARIOS
C34: BUENAS PRÁCTICAS CIBERSEGURIDAD Debe existir esta documentación: (CAPACITACIÓN SOBRE FUNDAMENTOS BÁSICOS Y OBJETIVOS DE MEJORES PRÁCTICAS EN CIBERSEGURIDAD Y SU RELACIÓN CON UN SG-PDP) | I34: =IFERROR(_xlfn.IFS(D34="NO EXISTE DOCUMENTACIÓN, NI MÉTODOS. ORGANIZACIÓN EMPÍRICA. CERO CAPACIDAD DE REACCIÓN",1,E34="EXISTEN DOCUMENTOS. HAY MÉTODOS SIN RIGUROSIDAD. NO HAY PROYECTO PDP. HAY UN DPD. NIVEL MÍNIMO DE SEGURIDAD. BAJA CAPACIDAD DE IDENTIFICAR Y RESTAURAR BRECHAS",2,F34="PROYECTO PDP EN FASE INICIAL PANSI. HAY DPD. HAY APOYO POR EL RTD. NIVEL MÍNIMO DESEADO DE SEGURIDAD. VULNERABILIDADES IDENTIFICADAS Y ATENDIDAS",3,G34="SG-PDP VALIDADO Y EN PRIMER TRIMESTE DE OPERACIÓN. NIVEL DE SEGURIDAD ADECUADO",4),0) -> 0 | K34: X | M34: X | N34: X | Q34: DESCRITO EN COMENTARIOS | R34: DESCRITO EN COMENTARIOS | S34: DESCRITO EN COMENTARIOS
I35: =AVERAGEIF(I29:I34,"<>0") -> #DIV/0!

Sheet TÉCNICAS TECNOL EET + PANSI
D2: EVALUACIÓN DEL ESTADO DE LA TECNICA ÁREA: TÉCNICAS - TECNOLOGÍA REQUISITO LOPDP:2021, ARTÍCULO 10.j
D6: CAÓTICO | E6: PSEUDO - PROFESIONAL | G6: PROFESIONAL
D7: 1 | E7: MEDIO BAJO 2 | F7: MEDIO ALTO 3 | G7: 4 | H7: COMENTARIOS
D8: DOCUMENTACIÓN INEXISTENTE | E8: DOCUMENTACIÓN SIN PDP INCLUIDO | F8: GRC DOCUMENTADO CON PDP INCLUIDO. PANSI FASE 1 | G8: SG-PDP VALIDADO Y EN PRIMER TRIMESTRE OPERATIVO
C9: INVENTARIO DE ACTIVOS DE LOS DATOS Debe existir esta documentación: (CÓDIGO DE ATIVO, DISPOSITIVO, CLASE, MARCA, RED ASOCIADA, CATEGORIA, POLÍTICA DE GESTIÓN, OTROS) | I9: =IFERROR(_xlfn.IFS(D9="NO EXISTE DOCUMENTACIÓN, NI MÉTODOS. ORGANIZACIÓN EMPÍRICA. CERO CAPACIDAD DE REACCIÓN",1,E9="EXISTEN DOCUMENTOS. HAY MÉTODOS SIN RIGUROSIDAD. NO HAY PROYECTO PDP. HAY UN DPD. NIVEL MÍNIMO DE SEGURIDAD. BAJA CAPACIDAD DE IDENTIFICAR Y RESTAURAR BRECHAS",2,F9="PROYECTO PDP EN FASE INICIAL PANSI. HAY DPD. HAY APOYO POR EL RTD. NIVEL MÍNIMO DESEADO DE SEGURIDAD. VULNERABILIDADES IDENTIFICADAS Y ATENDIDAS",3,G9="SG-PDP VALIDADO Y EN PRIMER TRIMESTE DE OPERACIÓN. NIVEL DE SEGURIDAD ADECUADO",4),0) -> 0
B10: VULNERABILIDADES TÉCNICAS - TECNOLOGÍA | C10: GESTIÓN PLATAFORMAS DIGITALES Debe existir esta documentación: (CONTRATO CO PROVEEDOR, CLÁUSULA DE PDP, CARACTERIZACIÓN DE LA CADENA 3ras PARTES, EVIDENCIA DE ESQUEMA PDP, CARPETA DEL PROVEEDOR) | I10: =IFERROR(_xlfn.IFS(D10="NO EXISTE DOCUMENTACIÓN, NI MÉTODOS. ORGANIZACIÓN EMPÍRICA. CERO CAPACIDAD DE REACCIÓN",1,E10="EXISTEN DOCUMENTOS. HAY MÉTODOS SIN RIGUROSIDAD. NO HAY PROYECTO PDP. HAY UN DPD. NIVEL MÍNIMO DE SEGURIDAD. BAJA CAPACIDAD DE IDENTIFICAR Y RESTAURAR BRECHAS",2,F10="PROYECTO PDP EN FASE INICIAL PANSI. HAY DPD. HAY APOYO POR EL RTD. NIVEL MÍNIMO DESEADO DE SEGURIDAD. VULNERABILIDADES IDENTIFICADAS Y ATENDIDAS",3,G10="SG-PDP VALIDADO Y EN PRIMER TRIMESTE DE OPERACIÓN. NIVEL DE SEGURIDAD ADECUADO",4),0) -> 0
C11: GESTIÓN SERVICIOS NUBE Debe existir esta documentación: (CONTRATO CO PROVEEDOR, CLÁUSULA DE PDP, CARACTERIZACIÓN DE LA CADENA 3ras PARTES, EVIDENCIA DE ESQUEMA PDP, CARPETA DEL PROVEEDOR) | I11: =IFERROR(_xlfn.IFS(D11="NO EXISTE DOCUMENTACIÓN, NI MÉTODOS. ORGANIZACIÓN EMPÍRICA. CERO CAPACIDAD DE REACCIÓN",1,E11="EXISTEN DOCUMENTOS. HAY MÉTODOS SIN RIGUROSIDAD. NO HAY PROYECTO PDP. HAY UN DPD. NIVEL MÍNIMO DE SEGURIDAD. BAJA CAPACIDAD DE IDENTIFICAR Y RESTAURAR BRECHAS",2,F11="PROYECTO PDP EN FASE INICIAL PANSI. HAY DPD. HAY APOYO POR EL RTD. NIVEL MÍNIMO DESEADO DE SEGURIDAD. VULNERABILIDADES IDENTIFICADAS Y ATENDIDAS",3,G11="SG-PDP VALIDADO Y EN PRIMER TRIMESTE DE OPERACIÓN. NIVEL DE SEGURIDAD ADECUADO",4),0) -> 0
C12: GESTIÓN ACCESOS REMOTOS Debe existir esta documentación: (LISTADO DE ACTIVOS, LISTADO DE DISPOSITIVOS, LISTADO USUARIOS, PROTOCOLO DE ACCESOS, PROTOCOLO DE SIMULACROS) | I12: =IFERROR(_xlfn.IFS(D12="NO EXISTE DOCUMENTACIÓN, NI MÉTODOS. ORGANIZACIÓN EMPÍRICA. CERO CAPACIDAD DE REACCIÓN",1,E12="EXISTEN DOCUMENTOS. HAY MÉTODOS SIN RIGUROSIDAD. NO HAY PROYECTO PDP. HAY UN DPD. NIVEL MÍNIMO DE SEGURIDAD. BAJA CAPACIDAD DE IDENTIFICAR Y RESTAURAR BRECHAS",2,F12="PROYECTO PDP EN FASE INICIAL PANSI. HAY DPD. HAY APOYO POR EL RTD. NIVEL MÍNIMO DESEADO DE SEGURIDAD. VULNERABILIDADES IDENTIFICADAS Y ATENDIDAS",3,G12="SG-PDP VALIDADO Y EN PRIMER TRIMESTE DE OPERACIÓN. NIVEL DE SEGURIDAD ADECUADO",4),0) -> 0
C13: GESTIÓN DE CLAVES Debe existir esta documentación: (LISTADO DE ACTIVOS, LISTADO DE DISPOSITIVOS, LISTADO USUARIOS, PROTOCOLO DE ACCESOS, PROTOCOLO DE SIMULACRO) | I13: =IFERROR(_xlfn.IFS(D13="NO EXISTE DOCUMENTACIÓN, NI MÉTODOS. ORGANIZACIÓN EMPÍRICA. CERO CAPACIDAD DE REACCIÓN",1,E13="EXISTEN DOCUMENTOS. HAY MÉTODOS SIN RIGUROSIDAD. NO HAY PROYECTO PDP. HAY UN DPD. NIVEL MÍNIMO DE SEGURIDAD. BAJA CAPACIDAD DE IDENTIFICAR Y RESTAURAR BRECHAS",2,F13="PROYECTO PDP EN FASE INICIAL PANSI. HAY DPD. HAY APOYO POR EL RTD. NIVEL MÍNIMO DESEADO DE SEGURIDAD. VULNERABILIDADES IDENTIFICADAS Y ATENDIDAS",3,G13="SG-PDP VALIDADO Y EN PRIMER TRIMESTE DE OPERACIÓN. NIVEL DE SEGURIDAD ADECUADO",4),0) -> 0
C14: GESTIÓN DE EQUIPOS CRÍTICO Debe existir esta documentación: (LISTADO DE ACTIVOS, LISTADO DE DISPOSITIVOS, LISTADO USUARIOS, PLAN DE MANTENIMINETO, MÉTRICAS E INDICADORES, REGISTRO DE SIMULACROS) | I14: =IFERROR(_xlfn.IFS(D14="NO EXISTE DOCUMENTACIÓN, NI MÉTODOS. ORGANIZACIÓN EMPÍRICA. CERO CAPACIDAD DE REACCIÓN",1,E14="EXISTEN DOCUMENTOS. HAY MÉTODOS SIN RIGUROSIDAD. NO HAY PROYECTO PDP. HAY UN DPD. NIVEL MÍNIMO DE SEGURIDAD. BAJA CAPACIDAD DE IDENTIFICAR Y RESTAURAR BRECHAS",2,F14="PROYECTO PDP EN FASE INICIAL PANSI. HAY DPD. HAY APOYO POR EL RTD. NIVEL MÍNIMO DESEADO DE SEGURIDAD. VULNERABILIDADES IDENTIFICADAS Y ATENDIDAS",3,G14="SG-PDP VALIDADO Y EN PRIMER TRIMESTE DE OPERACIÓN. NIVEL DE SEGURIDAD ADECUADO",4),0) -> 0
C15: GESTIÓN DE EQUIPOS PERSONALES (PATD) Debe existir esta documentación: (LISTADO DE ACTIVOS, LISTADO DE DISPOSITIVOS, LISTADO USUARIOS, PLAN DE MANTENIMINETO, MÉTRICAS E INDICADORES, REGISTRO DE SIMULACROS) | I15: =IFERROR(_xlfn.IFS(D15="NO EXISTE DOCUMENTACIÓN, NI MÉTODOS. ORGANIZACIÓN EMPÍRICA. CERO CAPACIDAD DE REACCIÓN",1,E15="EXISTEN DOCUMENTOS. HAY MÉTODOS SIN RIGUROSIDAD. NO HAY PROYECTO PDP. HAY UN DPD. NIVEL MÍNIMO DE SEGURIDAD. BAJA CAPACIDAD DE IDENTIFICAR Y RESTAURAR BRECHAS",2,F15="PROYECTO PDP EN FASE INICIAL PANSI. HAY DPD. HAY APOYO POR EL RTD. NIVEL MÍNIMO DESEADO DE SEGURIDAD. VULNERABILIDADES IDENTIFICADAS Y ATENDIDAS",3,G15="SG-PDP VALIDADO Y EN PRIMER TRIMESTE DE OPERACIÓN. NIVEL DE SEGURIDAD ADECUADO",4),0) -> 0
C16: GESTIÓN DE PRIVILEGIOS (ZERO TRUST) Debe existir esta documentación: (LISTADO DE ACTIVOS, LISTADO DE DISPOSITIVOS, LISTADO USUARIOS, PLAN DE MANTENIMINETO, MÉTRICAS E INDICADORES, REGISTRO DE SIMULACROS) | I16: =IFERROR(_xlfn.IFS(D16="NO EXISTE DOCUMENTACIÓN, NI MÉTODOS. ORGANIZACIÓN EMPÍRICA. CERO CAPACIDAD DE REACCIÓN",1,E16="EXISTEN DOCUMENTOS. HAY MÉTODOS SIN RIGUROSIDAD. NO HAY PROYECTO PDP. HAY UN DPD. NIVEL MÍNIMO DE SEGURIDAD. BAJA CAPACIDAD DE IDENTIFICAR Y RESTAURAR BRECHAS",2,F16="PROYECTO PDP EN FASE INICIAL PANSI. HAY DPD. HAY APOYO POR EL RTD. NIVEL MÍNIMO DESEADO DE SEGURIDAD. VULNERABILIDADES IDENTIFICADAS Y ATENDIDAS",3,G16="SG-PDP VALIDADO Y EN PRIMER TRIMESTE DE OPERACIÓN. NIVEL DE SEGURIDAD ADECUADO",4),0) -> 0
C17: GESTIÓN SIMULACROS Y CIBERSEGURIDAD Debe existir esta documentación: (LISTADO DE ACTIVOS, LISTADO DE DISPOSITIVOS, LISTADO USUARIOS, PLAN DE MANTENIMINETO, MÉTRICAS E INDICADORES, REGISTRO DE SIMULACROS) | I17: =IFERROR(_xlfn.IFS(D17="NO EXISTE DOCUMENTACIÓN, NI MÉTODOS. ORGANIZACIÓN EMPÍRICA. CERO CAPACIDAD DE REACCIÓN",1,E17="EXISTEN DOCUMENTOS. HAY MÉTODOS SIN RIGUROSIDAD. NO HAY PROYECTO PDP. HAY UN DPD. NIVEL MÍNIMO DE SEGURIDAD. BAJA CAPACIDAD DE IDENTIFICAR Y RESTAURAR BRECHAS",2,F17="PROYECTO PDP EN FASE INICIAL PANSI. HAY DPD. HAY APOYO POR EL RTD. NIVEL MÍNIMO DESEADO DE SEGURIDAD. VULNERABILIDADES IDENTIFICADAS Y ATENDIDAS",3,G17="SG-PDP VALIDADO Y EN PRIMER TRIMESTE DE OPERACIÓN. NIVEL DE SEGURIDAD ADECUADO",4),0) -> 0
C18: ENCRIPTACIÓN Y SEUDONIMIZACIÓN Debe existir esta documentación: (CUMPLIR CON LA RESOLUCIÓN No. SPDP-SPD-2025-0030-R) | I18: =IFERROR(_xlfn.IFS(D18="NO EXISTE DOCUMENTACIÓN, NI MÉTODOS. ORGANIZACIÓN EMPÍRICA. CERO CAPACIDAD DE REACCIÓN",1,E18="EXISTEN DOCUMENTOS. HAY MÉTODOS SIN RIGUROSIDAD. NO HAY PROYECTO PDP. HAY UN DPD. NIVEL MÍNIMO DE SEGURIDAD. BAJA CAPACIDAD DE IDENTIFICAR Y RESTAURAR BRECHAS",2,F18="PROYECTO PDP EN FASE INICIAL PANSI. HAY DPD. HAY APOYO POR EL RTD. NIVEL MÍNIMO DESEADO DE SEGURIDAD. VULNERABILIDADES IDENTIFICADAS Y ATENDIDAS",3,G18="SG-PDP VALIDADO Y EN PRIMER TRIMESTE DE OPERACIÓN. NIVEL DE SEGURIDAD ADECUADO",4),0) -> 0
H19: ESTADO DE LA TÉCNICA | I19: =AVERAGEIF(I9:I18,"<>0") -> #DIV/0!
D21: ADECUACIÓN DEL NIVEL DE SEGURIDAD (PANSI) ÁREA: TÉCNICAS - TECNOLOGÍA OBLIGACIÓN LOPDP:2021, ARTÍCULO 47.6
K24: REQUISITO ARTÍCULO 22.2 -RESOLUCIÓN 2025-0028-R (GARANTÍA DE INDEPENDENCIA PARA DPO) | W24: ESTATUS DEL COMPROMISO DE APLICABILIDAD
D25: CAÓTICO | E25: PSEUDO - PROFESIONAL | G25: PROFESIONAL
D26: 1 | E26: MEDIO BAJO 2 | F26: MEDIO ALTO 3 | G26: 4 | H26: ACCIONES MITIGADORAS | K26: RECURSOS NECESARIO | Q26: COMPROMISOS DE APLICABILIDAD | W26: CUMPLIDO | X26: DEMORADO | Y26: EN PROCESO
D27: DOCUMENTACIÓN INEXISTENTE | E27: DOCUMENTACIÓN SIN PDP INCLUIDO | F27: GRC DOCUMENTADO CON PDP INCLUIDO. PANSI FASE 1 | G27: SG-PDP VALIDADO Y EN PRIMER TRIMESTRE OPERATIVO | H27: MEDIDAS, HERRAMIENTAS Y CONTROLES para elevar el nivel del estado de la técnica | K27: HUMANO | L27: TECNOLOGÍCO | M27: FINANCIERO | N27: TIEMPO | O27: INFRAESTRUCTURA | Q27: FECHA PROBABLE INICIO | R27: INVERSIÓN ESTIMADA HORAS - HOMBRE | S27: INVERSIÓN ESTIMADA DINERO | T27: COMENTARIOS
C28: INVENTARIO DE ACTIVOS DE LOS DATOS Debe existir esta documentación: (CÓDIGO DE ATIVO, DISPOSITIVO, CLASE, MARCA, RED ASOCIADA, CATEGORIA, POLÍTICA DE GESTIÓN, OTROS) | I28: =IFERROR(_xlfn.IFS(D28="NO EXISTE DOCUMENTACIÓN, NI MÉTODOS. ORGANIZACIÓN EMPÍRICA. CERO CAPACIDAD DE REACCIÓN",1,E28="EXISTEN DOCUMENTOS. HAY MÉTODOS SIN RIGUROSIDAD. NO HAY PROYECTO PDP. HAY UN DPD. NIVEL MÍNIMO DE SEGURIDAD. BAJA CAPACIDAD DE IDENTIFICAR Y RESTAURAR BRECHAS",2,F28="PROYECTO PDP EN FASE INICIAL PANSI. HAY DPD. HAY APOYO POR EL RTD. NIVEL MÍNIMO DESEADO DE SEGURIDAD. VULNERABILIDADES IDENTIFICADAS Y ATENDIDAS",3,G28="SG-PDP VALIDADO Y EN PRIMER TRIMESTE DE OPERACIÓN. NIVEL DE SEGURIDAD ADECUADO",4),0) -> 0 | K28: X | M28: X | N28: X | Q28: DESCRITO EN COMENTARIOS | R28: DESCRITO EN COMENTARIOS | S28: DESCRITO EN COMENTARIOS
B29: VULNERABILIDADES TÉCNICAS - TECNOLOGÍA | C29: GESTIÓN PLATAFORMAS DIGITALES Debe existir esta documentación: (CONTRATO CO PROVEEDOR, CLÁUSULA DE PDP, CARACTERIZACIÓN DE LA CADENA 3ras PARTES, EVIDENCIA DE ESQUEMA PDP, CARPETA DEL PROVEEDOR) | I29: =IFERROR(_xlfn.IFS(D29="NO EXISTE DOCUMENTACIÓN, NI MÉTODOS. ORGANIZACIÓN EMPÍRICA. CERO CAPACIDAD DE REACCIÓN",1,E29="EXISTEN DOCUMENTOS. HAY MÉTODOS SIN RIGUROSIDAD. NO HAY PROYECTO PDP. HAY UN DPD. NIVEL MÍNIMO DE SEGURIDAD. BAJA CAPACIDAD DE IDENTIFICAR Y RESTAURAR BRECHAS",2,F29="PROYECTO PDP EN FASE INICIAL PANSI. HAY DPD. HAY APOYO POR EL RTD. NIVEL MÍNIMO DESEADO DE SEGURIDAD. VULNERABILIDADES IDENTIFICADAS Y ATENDIDAS",3,G29="SG-PDP VALIDADO Y EN PRIMER TRIMESTE DE OPERACIÓN. NIVEL DE SEGURIDAD ADECUADO",4),0) -> 0 | K29: X | M29: X | N29: X | Q29: DESCRITO EN COMENTARIOS | R29: DESCRITO EN COMENTARIOS | S29: DESCRITO EN COMENTARIOS
C30: GESTIÓN SERVICIOS NUBE Debe existir esta documentación: (CONTRATO CO PROVEEDOR, CLÁUSULA DE PDP, CARACTERIZACIÓN DE LA CADENA 3ras PARTES, EVIDENCIA DE ESQUEMA PDP, CARPETA DEL PROVEEDOR) | I30: =IFERROR(_xlfn.IFS(D30="NO EXISTE DOCUMENTACIÓN, NI MÉTODOS. ORGANIZACIÓN EMPÍRICA. CERO CAPACIDAD DE REACCIÓN",1,E30="EXISTEN DOCUMENTOS. HAY MÉTODOS SIN RIGUROSIDAD. NO HAY PROYECTO PDP. HAY UN DPD. NIVEL MÍNIMO DE SEGURIDAD. BAJA CAPACIDAD DE IDENTIFICAR Y RESTAURAR BRECHAS",2,F30="PROYECTO PDP EN FASE INICIAL PANSI. HAY DPD. HAY APOYO POR EL RTD. NIVEL MÍNIMO DESEADO DE SEGURIDAD. VULNERABILIDADES IDENTIFICADAS Y ATENDIDAS",3,G30="SG-PDP VALIDADO Y EN PRIMER TRIMESTE DE OPERACIÓN. NIVEL DE SEGURIDAD ADECUADO",4),0) -> 0 | K30: X | M30: X | N30: X | Q30: DESCRITO EN COMENTARIOS | R30: DESCRITO EN COMENTARIOS | S30: DESCRITO EN COMENTARIOS
C31: GESTIÓN ACCESOS REMOTOS Debe existir esta documentación: (LISTADO DE ACTIVOS, LISTADO DE DISPOSITIVOS, LISTADO USUARIOS, PROTOCOLO DE ACCESOS, PROTOCOLO DE SIMULACROS) | I31: =IFERROR(_xlfn.IFS(D31="NO EXISTE DOCUMENTACIÓN, NI MÉTODOS. ORGANIZACIÓN EMPÍRICA. CERO CAPACIDAD DE REACCIÓN",1,E31="EXISTEN DOCUMENTOS. HAY MÉTODOS SIN RIGUROSIDAD. NO HAY PROYECTO PDP. HAY UN DPD. NIVEL MÍNIMO DE SEGURIDAD. BAJA CAPACIDAD DE IDENTIFICAR Y RESTAURAR BRECHAS",2,F31="PROYECTO PDP EN FASE INICIAL PANSI. HAY DPD. HAY APOYO POR EL RTD. NIVEL MÍNIMO DESEADO DE SEGURIDAD. VULNERABILIDADES IDENTIFICADAS Y ATENDIDAS",3,G31="SG-PDP VALIDADO Y EN PRIMER TRIMESTE DE OPERACIÓN. NIVEL DE SEGURIDAD ADECUADO",4),0) -> 0 | K31: X | M31: X | N31: X | Q31: DESCRITO EN COMENTARIOS | R31: DESCRITO EN COMENTARIOS | S31: DESCRITO EN COMENTARIOS
C32: GESTIÓN DE CLAVES Debe existir esta documentación: (LISTADO DE ACTIVOS, LISTADO DE DISPOSITIVOS, LISTADO USUARIOS, PROTOCOLO DE ACCESOS, PROTOCOLO DE SIMULACRO) | I32: =IFERROR(_xlfn.IFS(D32="NO EXISTE DOCUMENTACIÓN, NI MÉTODOS. ORGANIZACIÓN EMPÍRICA. CERO CAPACIDAD DE REACCIÓN",1,E32="EXISTEN DOCUMENTOS. HAY MÉTODOS SIN RIGUROSIDAD. NO HAY PROYECTO PDP. HAY UN DPD. NIVEL MÍNIMO DE SEGURIDAD. BAJA CAPACIDAD DE IDENTIFICAR Y RESTAURAR BRECHAS",2,F32="PROYECTO PDP EN FASE INICIAL PANSI. HAY DPD. HAY APOYO POR EL RTD. NIVEL MÍNIMO DESEADO DE SEGURIDAD. VULNERABILIDADES IDENTIFICADAS Y ATENDIDAS",3,G32="SG-PDP VALIDADO Y EN PRIMER TRIMESTE DE OPERACIÓN. NIVEL DE SEGURIDAD ADECUADO",4),0) -> 0 | K32: X | M32: X | N32: X | Q32: DESCRITO EN COMENTARIOS | R32: DESCRITO EN COMENTARIOS | S32: DESCRITO EN COMENTARIOS
C33: GESTIÓN DE EQUIPOS CRÍTICO Debe existir esta documentación: (LISTADO DE ACTIVOS, LISTADO DE DISPOSITIVOS, LISTADO USUARIOS, PLAN DE MANTENIMINETO, MÉTRICAS E INDICADORES, REGISTRO DE SIMULACROS) | I33: =IFERROR(_xlfn.IFS(D33="NO EXISTE DOCUMENTACIÓN, NI MÉTODOS. ORGANIZACIÓN EMPÍRICA. CERO CAPACIDAD DE REACCIÓN",1,E33="EXISTEN DOCUMENTOS. HAY MÉTODOS SIN RIGUROSIDAD. NO HAY PROYECTO PDP. HAY UN DPD. NIVEL MÍNIMO DE SEGURIDAD. BAJA CAPACIDAD DE IDENTIFICAR Y RESTAURAR BRECHAS",2,F33="PROYECTO PDP EN FASE INICIAL PANSI. HAY DPD. HAY APOYO POR EL RTD. NIVEL MÍNIMO DESEADO DE SEGURIDAD. VULNERABILIDADES IDENTIFICADAS Y ATENDIDAS",3,G33="SG-PDP VALIDADO Y EN PRIMER TRIMESTE DE OPERACIÓN. NIVEL DE SEGURIDAD ADECUADO",4),0) -> 0 | K33: X | M33: X | N33: X | Q33: DESCRITO EN COMENTARIOS | R33: DESCRITO EN COMENTARIOS | S33: DESCRITO EN COMENTARIOS
C34: GESTIÓN DE EQUIPOS PERSONALES (PATD) Debe existir esta documentación: (LISTADO DE ACTIVOS, LISTADO DE DISPOSITIVOS, LISTADO USUARIOS, PLAN DE MANTENIMINETO, MÉTRICAS E INDICADORES, REGISTRO DE SIMULACROS) | I34: =IFERROR(_xlfn.IFS(D34="NO EXISTE DOCUMENTACIÓN, NI MÉTODOS. ORGANIZACIÓN EMPÍRICA. CERO CAPACIDAD DE REACCIÓN",1,E34="EXISTEN DOCUMENTOS. HAY MÉTODOS SIN RIGUROSIDAD. NO HAY PROYECTO PDP. HAY UN DPD. NIVEL MÍNIMO DE SEGURIDAD. BAJA CAPACIDAD DE IDENTIFICAR Y RESTAURAR BRECHAS",2,F34="PROYECTO PDP EN FASE INICIAL PANSI. HAY DPD. HAY APOYO POR EL RTD. NIVEL MÍNIMO DESEADO DE SEGURIDAD. VULNERABILIDADES IDENTIFICADAS Y ATENDIDAS",3,G34="SG-PDP VALIDADO Y EN PRIMER TRIMESTE DE OPERACIÓN. NIVEL DE SEGURIDAD ADECUADO",4),0) -> 0 | K34: X | M34: X | N34: X | Q34: DESCRITO EN COMENTARIOS | R34: DESCRITO EN COMENTARIOS | S34: DESCRITO EN COMENTARIOS
C35: GESTIÓN DE PRIVILEGIOS (ZERO TRUST) Debe existir esta documentación: (LISTADO DE ACTIVOS, LISTADO DE DISPOSITIVOS, LISTADO USUARIOS, PLAN DE MANTENIMINETO, MÉTRICAS E INDICADORES, REGISTRO DE SIMULACROS) | I35: =IFERROR(_xlfn.IFS(D35="NO EXISTE DOCUMENTACIÓN, NI MÉTODOS. ORGANIZACIÓN EMPÍRICA. CERO CAPACIDAD DE REACCIÓN",1,E35="EXISTEN DOCUMENTOS. HAY MÉTODOS SIN RIGUROSIDAD. NO HAY PROYECTO PDP. HAY UN DPD. NIVEL MÍNIMO DE SEGURIDAD. BAJA CAPACIDAD DE IDENTIFICAR Y RESTAURAR BRECHAS",2,F35="PROYECTO PDP EN FASE INICIAL PANSI. HAY DPD. HAY APOYO POR EL RTD. NIVEL MÍNIMO DESEADO DE SEGURIDAD. VULNERABILIDADES IDENTIFICADAS Y ATENDIDAS",3,G35="SG-PDP VALIDADO Y EN PRIMER TRIMESTE DE OPERACIÓN. NIVEL DE SEGURIDAD ADECUADO",4),0) -> 0 | K35: X | M35: X | N35: X | Q35: DESCRITO EN COMENTARIOS | R35: DESCRITO EN COMENTARIOS | S35: DESCRITO EN COMENTARIOS
C36: GESTIÓN SIMULACROS Y CIBERSEGURIDAD Debe existir esta documentación: (LISTADO DE ACTIVOS, LISTADO DE DISPOSITIVOS, LISTADO USUARIOS, PLAN DE MANTENIMINETO, MÉTRICAS E INDICADORES, REGISTRO DE SIMULACROS) | I36: =IFERROR(_xlfn.IFS(D36="NO EXISTE DOCUMENTACIÓN, NI MÉTODOS. ORGANIZACIÓN EMPÍRICA. CERO CAPACIDAD DE REACCIÓN",1,E36="EXISTEN DOCUMENTOS. HAY MÉTODOS SIN RIGUROSIDAD. NO HAY PROYECTO PDP. HAY UN DPD. NIVEL MÍNIMO DE SEGURIDAD. BAJA CAPACIDAD DE IDENTIFICAR Y RESTAURAR BRECHAS",2,F36="PROYECTO PDP EN FASE INICIAL PANSI. HAY DPD. HAY APOYO POR EL RTD. NIVEL MÍNIMO DESEADO DE SEGURIDAD. VULNERABILIDADES IDENTIFICADAS Y ATENDIDAS",3,G36="SG-PDP VALIDADO Y EN PRIMER TRIMESTE DE OPERACIÓN. NIVEL DE SEGURIDAD ADECUADO",4),0) -> 0 | K36: X | M36: X | N36: X | Q36: DESCRITO EN COMENTARIOS | R36: DESCRITO EN COMENTARIOS | S36: DESCRITO EN COMENTARIOS
C37: ENCRIPTACIÓN Y SEUDONIMIZACIÓN Debe existir esta documentación: (CUMPLIR CON LA RESOLUCIÓN No. SPDP-SPD-2025-0030-R) | I37: =IFERROR(_xlfn.IFS(D37="NO EXISTE DOCUMENTACIÓN, NI MÉTODOS. ORGANIZACIÓN EMPÍRICA. CERO CAPACIDAD DE REACCIÓN",1,E37="EXISTEN DOCUMENTOS. HAY MÉTODOS SIN RIGUROSIDAD. NO HAY PROYECTO PDP. HAY UN DPD. NIVEL MÍNIMO DE SEGURIDAD. BAJA CAPACIDAD DE IDENTIFICAR Y RESTAURAR BRECHAS",2,F37="PROYECTO PDP EN FASE INICIAL PANSI. HAY DPD. HAY APOYO POR EL RTD. NIVEL MÍNIMO DESEADO DE SEGURIDAD. VULNERABILIDADES IDENTIFICADAS Y ATENDIDAS",3,G37="SG-PDP VALIDADO Y EN PRIMER TRIMESTE DE OPERACIÓN. NIVEL DE SEGURIDAD ADECUADO",4),0) -> 0 | K37: X | M37: X | N37: X | Q37: DESCRITO EN COMENTARIOS | R37: DESCRITO EN COMENTARIOS | S37: DESCRITO EN COMENTARIOS
I38: =AVERAGEIF(I28:I37,"<>0") -> #DIV/0!

Sheet DASHBOARD EET - PANSI
B5: ESTADO DE LA TÉCNICA POR AREAS 2025 | N5: ESTADO DE LA TÉCNICA PROYECTADO 2026 POR AREAS

Sheet NIVEL DE SEGURIDAD
D3: CALIFICACIÓN DEL NIVEL DE SEGURIDAD SOBRE CUATRO RASGOS ORGANIZACIONALES
L5: REQUISITO ARTÍCULO 22.2 -RESOLUCIÓN 2025-0028-R (GARANTÍA DE INDEPENDENCIA PARA DPO) | X5: ESTATUS DEL COMPROMISO DE APLICABILIDAD
D7: CAÓTICO | E7: PSEUDO - PROFESIONAL | G7: PROFESIONAL | L7: RECURSOS NECESARIO | R7: COMPROMISOS DE APLICABILIDAD | X7: CUMPLIDO | Y7: DEMORADO | Z7: EN PROCESO
C8: RASGOS ORGANIZACONALES | D8: 1 | E8: MEDIO BAJO 2 | F8: MEDIO ALTO 3 NIVEL SEGURIDAD MÍNIMO DESEADO | G8: 4 | H8: COMENTARIOS - AMENAZAS - ALERTAS | I8: NIVEL INICIAL | J8: NIVEL ESPERADO | L8: HUMANO | M8: TECNOLOGÍCO | N8: FINANCIERO | O8: TIEMPO | P8: INFRAESTRUCTURA | R8: FECHA PROBABLE CUMPLIMIENTO | S8: INVERSIÓN ESTIMADA HORAS - HOMBRE | T8: INVERSIÓN ESTIMADA DINERO | U8: COMENTARIOS
C9: ESTADO DE LA TÉCNICA | D9: =IF(I9<=1.99,"NIVEL ET ROJO - CAÓTICO - INICIAR UN PROYECTO SG-PDP CON ESTE NIVEL DE SEGURIDAD SERÁ UN FRACASO - ES IMPERATIVO ELEVAR EL ESTADO DE LA TÉCNICA",IF(I9>3.99,"NIVEL ET AZUL - PROFESIONAL",IF(AND(I9>=1.99,I9<=2.99),"NIVEL ET NARANJA - BAJO - INICIAR UN PROYECTO SG-PDP CON ESTE NIVEL DE SEGURIDAD SERÁ UN FRACASO - ES IMPERATIVO ELEVAR EL ESTADO DE LA TÉCNICA","NIVEL ET VERDE-MÍNIMO DESEADO"))) -> #DIV/0! | I9: =+'Análisis NSI'!B17 -> #DIV/0! | J9: META >3 | L9: X | N9: X | O9: X | R9: DESCRITO EN COMENTARIOS | S9: DESCRITO EN COMENTARIOS | T9: DESCRITO EN COMENTARIOS | U9: 1.- Los compromisos del primer trimestre deben ser cubiertos en su totalidad ya que son la base sobre la que se construirá el esquema sistémico para la protección de datos personales. 2.- La mayor inversión será la compra del esquema sistémico para protección de datos personales Skillman-PDP. Otras inversiones como señalética para avisos en puntos de interacció Titular-Responsable o programa de carteleras informativas PDP serán inculidos una vez se aprueben las cotizaciones presentadas y el presupuesto para cubrir estos rubros
C10: SISTEMA DE GESTIÓN PARA EL GRC | E10: HAY PLAN ESTRATEGICO. SIN PLAN DE CONTINUIDAD DE NEGOCIO. SG VOLUNTARIO Y VALIDADO. FASE I PANSI TOMARÁ 3< MESES<6 Y LUEGO INICIA EL PROYECTO SG-PDP | I10: =IFERROR(_xlfn.IFS(D10="NO HAY NINGÚN TIPO DE DOCUMENTACIÓN. NO HAY PLAN ESTRATEGICO. GESTIÓN POR REACCIÓN. FASE I PANSI TOMARÁ 6< MESES<9 Y LUEGO INICIA EL PROYECTO SG-PDP",1,E10="HAY PLAN ESTRATEGICO. SIN PLAN DE CONTINUIDAD DE NEGOCIO. SG VOLUNTARIO Y VALIDADO. FASE I PANSI TOMARÁ 3< MESES<6 Y LUEGO INICIA EL PROYECTO SG-PDP",2,F10="FASE I PANSI COMPLETADA. INICIA PROYECTO SG-PDP TOMARÁ 6< MESES<9 PARA SER VALIDADO CON 1ra AUDITORÍA INTERNA",3,G10="SG-PDP MANTENIDO, MEJORADO Y RESILIENTE ",4),0) -> 2 | J10: META >3 | L10: X | N10: X | O10: X | R10: DESCRITO EN COMENTARIOS | S10: DESCRITO EN COMENTARIOS | T10: DESCRITO EN COMENTARIOS | U10: 1.- Se inicia con la implantación de la documentación del esquema sistémico Skillman-PDP. 2.- La personalización de la documentación de Skillman-PDP puede extenderse hasta cuatro meses 3.- Las métricas e indicadores de desempeño iniciales se alimentarán iniciando el cuarto trimestre 2026. El SG-PDP iniciaría con los indicadores Nivel de seguridad (47.6 LOPDP:2021) y Evaluación del DPO (22.2 de R-028-2025). 4.- Para los meses de marzo 2027 o abril 2027 se estaría realizando la auditoría interna para validar el SG-PDP
C11: MODELO PARA TOMA DE DECISIONES | E11: ESTRUCTURA ORGANIZACIONAL RESPETADA Y JERARQUÍAS DEFINIDAS. NO HAY MÉTRICAS ASOCIADAS A PDP. NADA SE HACE SIN APROBACIÓN DE LA MÁXIMA AUTORIDAD. | I11: =IFERROR(_xlfn.IFS(D11="NO EXISTE NINGÚN MODELO PARA TOMAR DECISIONES INFORMADAS. LAS DECISIONES SON POR REACCIÓN, POR JERARQUÍA E IMPROVISACIÓN.",1,E11="ESTRUCTURA ORGANIZACIONAL RESPETADA Y JERARQUÍAS DEFINIDAS. NO HAY MÉTRICAS ASOCIADAS A PDP. NADA SE HACE SIN APROBACIÓN DE LA MÁXIMA AUTORIDAD.",2,F11="FASE I DEL PANSI IMPACTA SOBRE LA TOMA DE DECISIONES INFORMADAS. INCLUIDOS MÉTRICAS Y KPI's LAS DEL PANSI, EIPD. NO TODO LO DECIDE LA MÁXIMA AUTORIDAD.",3,G11="SE DECIDE RIGUROSAMENTE SOBRE LAS TENDENCIAS QUE MUESTREN LOS KPI DEL SG-PDP. SE CUMPLE DE MANERA RIGUROSA EL CRONOGRAMA DE SIMULACROS Y EL CRONOGRAMA DE AUDITORÍAS.",4),0) -> 2 | J11: META >3 | L11: X | N11: X | O11: X | R11: DESCRITO EN COMENTARIOS | S11: DESCRITO EN COMENTARIOS | T11: DESCRITO EN COMENTARIOS | U11: 1.- Los compromisos del primer trimestre deben ser cubiertos en su totalidad ya que el fortalecimiento del estado de la técnica, impacta de manera directa y positiva sobre el rasgo organizacional Toma de Desiciones Informadas. 2.- Las métricas e indicadores de desempeño iniciales se alimentarán iniciando el cuarto trimestre 2026. El SG-PDP iniciaría con los indicadores Nivel de seguridad (47.6 LOPDP:2021) y Evaluación del DPO (22.2 de R-028-2025). 3.- El inicio de la toma de decisiones informadas depende de las capacitaciones del programa de profesionalización y cosncienciación. Para primer trimestre 2027 se podrán observar las tendencias iniciales de los indicadores Nivel de seguridad (47.6 LOPDP:2021) y Evaluación del DPO (22.2 de R-028-2025). 4.- LA garantía de que el nivel de madurez organizacional se mantenga y continue fortaleciendose dependerá de la continuidad que se le de a los programas de competencias técnicas y conscienciación derivado de los simulacros y las lecciones tomadas luego de su realización.
C12: GESTIÓN DE RESULTADOS | E12: MÉTRICAS Y KPI's CON POCA RIGUROSIDAD DE SEGUIMIENTO. NO INCLUYEN PDP. TODA ACCIÓN DEBE SER APROBADA POR LA MÁXIMA AUTORIDAD | I12: =IFERROR(_xlfn.IFS(D12="NO EXISTE NINGÚN MODELO PARA GESTIONAR RESULTADOS. SE ACTUA POR REACCIÓN, IMPROVISACIÓN Y SIN COMUNICACIÓN ENTRE ÁREAS",1,E12="MÉTRICAS Y KPI's CON POCA RIGUROSIDAD DE SEGUIMIENTO. NO INCLUYEN PDP. TODA ACCIÓN DEBE SER APROBADA POR LA MÁXIMA AUTORIDAD",2,F12="TOMA DE DECISIONES INFORMADAS DIRECCIONA Y ORDENA LA GESTIÓN DE RESULTADOS. TRABAJO EN EQUIPO SOBRE OBJETIVOS ORGAIZACIONALES CLAROS",3,G12="LA GESTIÓN DE RESULTADOS SE BASA RIGUROSAMENTE SOBRE LAS TENDENCIAS QUE MUESTREN LOS KPI DEL SG-PDP. SE CUMPLE DE MANERA RIGUROSA EL CRONOGRAMA DE SIMULACROS Y EL CRONOGRAMA DE AUDITORÍAS.",4),0) -> 2 | J12: META >3 | L12: X | N12: X | O12: X | R12: DESCRITO EN COMENTARIOS | S12: DESCRITO EN COMENTARIOS | T12: DESCRITO EN COMENTARIOS | U12: 1.- Los compromisos del primer trimestre deben ser cubiertos en su totalidad ya que el fortalecimiento del estado de la técnica, impacta de manera directa y positiva sobre el rasgo organizacional Toma de Desiciones Informadas. 2.- Con el fortalecimiento del estado de la técnica y el inicio del seguimiento a la tendencia de métricas e indicadores para su ajuste o reforzamiento, el rasgo organizacional Gestión de Resultados será fortalecido.
H15: NIVEL DE SEGURIDAD 2025 | I15: =AVERAGE(I9:I12) -> #DIV/0!

Sheet Análisis
A4: Etiquetas de fila | B4: WEB | C4: DIGITAL | D4: PATD | E4: REMOTO
A5: FISICAS - OPERACIÓN | B5: 2.3333333 | C5: 2.5 | D5: 2.1666667 | E5: 3
A6: INTERACCIÓN TITULAR-RESPONSABLE | B6: 3 | C6: 4 | D6: 1 | E6: 4
A7: MAPEO DE PATD | B7: 1 | C7: 3 | D7: 2 | E7: 4
A8: PROGRAMA CONCIENCIACIÓN (GENERAL, PATD y EQUIPO PDP) | B8: 2 | C8: 3 | D8: 1 | E8: 3
A9: PROGRAMA DE CAPACITACIÓN (GENERAL, PATD y EQUIPO PDP) | B9: 1 | C9: 3 | D9: 2 | E9: 4
A10: REGISTROS PDP | B10: 4 | C10: 1 | D10: 4 | E10: 1
A11: RUTINAS PDP | B11: 3 | C11: 1 | D11: 3 | E11: 2
A12: Total general | B12: 2.3333333 | C12: 2.5 | D12: 2.1666667 | E12: 3

Sheet Análisis 2 (2)
A2: MEDIDAS | B2: FISICAS - OPERACIÓN
A4: Etiquetas de fila | B4: WEB | C4: DIGITAL | D4: PATD | E4: REMOTO | F4: CALIFICACIÓN | K4: SUBMEDIDA | L4: WEB | M4: DIGITAL | N4: PATD | O4: REMOTO | P4: CALIFICACION
A5: INTERACCIÓN TITULAR-RESPONSABLE | B5: 3 | C5: 4 | D5: 1 | E5: 4 | F5: 12 | K5: =A5 -> INTERACCIÓN TITULAR-RESPONSABLE | L5: =GETPIVOTDATA(" WEB",$A$4) -> 14 | M5: =GETPIVOTDATA(" DIGITAL",$A$4) -> 15 | N5: =GETPIVOTDATA(" PATD",$A$4) -> 13 | O5: =GETPIVOTDATA(" REMOTO",$A$4) -> 18 | P5: =GETPIVOTDATA(" CALIFICACIÓN",$A$4) -> 60
A6: MAPEO DE PATD | B6: 1 | C6: 3 | D6: 2 | E6: 4 | F6: 10 | P6: {=_xlfn.IFS($P$5<=6,"1",AND($P$5>6,$P$5<=10),"2",AND($P$5>10,$P$5<=14),"3",$P$5>14,"4")} -> 4 | Q6: {=_xlfn.IFS($P$5<=6,"BAJO",AND($P$5>6,$P$5<=10),"MEDIO BAJO",AND($P$5>10,$P$5<=14),"MEDIO ALTO",$P$5>14,"PROFESIONAL")} -> PROFESIONAL
A7: PROGRAMA CONCIENCIACIÓN (GENERAL, PATD y EQUIPO PDP) | B7: 2 | C7: 3 | D7: 1 | E7: 3 | F7: 9
A8: PROGRAMA DE CAPACITACIÓN (GENERAL, PATD y EQUIPO PDP) | B8: 1 | C8: 3 | D8: 2 | E8: 4 | F8: 10
A9: REGISTROS PDP | B9: 4 | C9: 1 | D9: 4 | E9: 1 | F9: 10 | K9: WEB | N9: DIGITAL | T9: REMOTO | W9: CALIFICACION
A10: RUTINAS PDP | B10: 3 | C10: 1 | D10: 3 | E10: 2 | F10: 9 | K10: INDICADOR | L10: =L5-0.5 -> 13.5 | N10: INDICADOR | O10: =M5-0.5 -> 14.5 | Q10: PATD | R10: =N5-0.5 -> 12.5 | T10: INDICADOR | U10: =O5-0.5 -> 17.5 | W10: INDICADOR | X10: =P6-0.5 -> 3.5
A11: Total general | B11: 14 | C11: 15 | D11: 13 | E11: 18 | F11: 60 | K11: AGUJA | L11: 0.25 | N11: AGUJA | O11: 0.25 | Q11: INDICADOR | R11: 0.25 | T11: AGUJA | U11: 0.25 | W11: AGUJA | X11: 0.25
K12: RESTO | L12: =8-L10-L11 -> -5.75 | N12: RESTO | O12: =8-O10-O11 -> -6.75 | Q12: AGUJA | R12: =8-R10-R11 -> -4.75 | T12: RESTO | U12: =8-U10-U11 -> -9.75 | W12: RESTO | X12: =8-X10-X11 -> 4.25
Q13: RESTO
J27: 4 | K27: 5 | L27: 6 | M27: 7 | N27: 8 | O27: 9 | P27: 10 | Q27: 11 | R27: 12 | S27: 13 | T27: 14 | U27: 15 | V27: 16
J28: POBRE | M28: MEDIO BAJO | Q28: MEDIO ALTO | U28: PROFESIONAL
